Workbook
Name ACTIVE_REPS: '⚙ Lists'!$M$3:$M$6
Name ALL_BEDS: '⚙ Lists'!$Y$3:$Y$28
Name CLOSERS: '⚙ Lists'!$S$3:$S$5
Name DO_NOT_READMIT: '⚙ Lists'!$N$4:$N$8
Name FACILITY: '⚙ Lists'!$D$3:$D$6
Name HP_ROOMS: '⚙ Lists'!$T$3:$T$16
Name HPE_ROOMS: '⚙ Lists'!$U$3:$U$14
Name INS_TYPE: '⚙ Lists'!$F$3:$F$11
Name INSURANCE_OK: '⚙ Lists'!$E$3:$E$16
Name LOC: '⚙ Lists'!$C$3:$C$8
Name MONTHS: '⚙ Lists'!$W$3:$W$10
Name NON_CONTRACTED: '⚙ Lists'!$L$3:$L$17
Name PLAN_LOS: '⚙ Lists'!$V$3:$V$11
Name REF_CAT: '⚙ Lists'!$G$3:$G$11
Name REPS: '⚙ Lists'!$A$3:$A$8
Name STATUS: '⚙ Lists'!$B$3:$B$8
Name TEMP: '⚙ Lists'!$H$3:$H$5
Name YESNO: '⚙ Lists'!$I$3:$I$4

Sheet 📊 Dashboard
A1: 🏥 HARMONY PLACE — ADMISSIONS DASHBOARD
A2: ="Updated: "&TEXT(NOW(),"ddd M/D h:MM AM/PM") -> Updated: Wed 6/17 12:48 PM | E2: ="Total: "&(COUNTIF('🛏 HP Bed Board'!B10:B23,"Occupied")+(COUNTIF('🛏 HPE Bed Board'!B11:B16,"Occupied")+COUNTIF('🛏 HPE Bed Board'!B18:B23,"Occupied")))&"/26 · "&(COUNTIF('🛏 HP Bed Board'!B10:B23,"Open")+(COUNTIF('🛏 HPE Bed Board'!B11:B16,"Open")+COUNTIF('🛏 HPE Bed Board'!B18:B23,"Open")))&" open" -> Total: 20/26 · 5 open
A4: 🛏 COMMAND CENTER — LIVE CENSUS & FLOW
A5: HP Census | B5: HPE Census | C5: Total | D5: Open Beds | E5: Reserved | F5: Adm MTD | G5: Conv % | H5: Proj 7d
A6: =COUNTIF('🛏 HP Bed Board'!B10:B23,"Occupied")&"/14" -> 11/14 | B6: =(COUNTIF('🛏 HPE Bed Board'!B11:B16,"Occupied")+COUNTIF('🛏 HPE Bed Board'!B18:B23,"Occupied"))&"/12" -> 9/12 | C6: =(COUNTIF('🛏 HP Bed Board'!B10:B23,"Occupied")+(COUNTIF('🛏 HPE Bed Board'!B11:B16,"Occupied")+COUNTIF('🛏 HPE Bed Board'!B18:B23,"Occupied")))&"/26" -> 20/26 | D6: =COUNTIF('🛏 HP Bed Board'!B10:B23,"Open")+(COUNTIF('🛏 HPE Bed Board'!B11:B16,"Open")+COUNTIF('🛏 HPE Bed Board'!B18:B23,"Open")) -> 5 | E6: =COUNTIF('🛏 HP Bed Board'!B10:B23,"Reserved")+(COUNTIF('🛏 HPE Bed Board'!B11:B16,"Reserved")+COUNTIF('🛏 HPE Bed Board'!B18:B23,"Reserved")) -> 1 | F6: =$C$74 -> 13 | G6: =$D$74 -> 1 | H6: =$G$74 -> 17
A8: =" ⚠ DISCHARGE WATCH — Next 7 days ("&SUM('⚙ Census Engine'!$AB$10:$AB$35)&" discharging)" -> ⚠ DISCHARGE WATCH — Next 7 days (4 discharging)
A9: Client | B9: Fac | C9: Room | D9: Admit | E9: Day # | F9: DC Date | G9: To DC | H9: Rep | I9: LOC | J9: Financial
A10: =IFERROR(INDEX('⚙ Census Engine'!$AD$10:$AD$35,MATCH(ROW()-9,'⚙ Census Engine'!$AC$10:$AC$35,0)),"") -> Rhonda Baim | B10: =IFERROR(INDEX('⚙ Census Engine'!$AE$10:$AE$35,MATCH(ROW()-9,'⚙ Census Engine'!$AC$10:$AC$35,0)),"") -> HPE | C10: =IFERROR(INDEX('⚙ Census Engine'!$AF$10:$AF$35,MATCH(ROW()-9,'⚙ Census Engine'!$AC$10:$AC$35,0)),"") -> H1-2A | D10: =IFERROR(INDEX('⚙ Census Engine'!$AG$10:$AG$35,MATCH(ROW()-9,'⚙ Census Engine'!$AC$10:$AC$35,0)),"") -> 5/24 | E10: =IFERROR(INDEX('⚙ Census Engine'!$AH$10:$AH$35,MATCH(ROW()-9,'⚙ Census Engine'!$AC$10:$AC$35,0)),"") -> 24 | F10: =IFERROR(INDEX('⚙ Census Engine'!$AI$10:$AI$35,MATCH(ROW()-9,'⚙ Census Engine'!$AC$10:$AC$35,0)),"") -> 6/23 | G10: =IFERROR(INDEX('⚙ Census Engine'!$AJ$10:$AJ$35,MATCH(ROW()-9,'⚙ Census Engine'!$AC$10:$AC$35,0)),"") -> 6d | H10: =IFERROR(INDEX('⚙ Census Engine'!$AK$10:$AK$35,MATCH(ROW()-9,'⚙ Census Engine'!$AC$10:$AC$35,0)),"") -> Nelson | I10: =IFERROR(INDEX('⚙ Census Engine'!$AL$10:$AL$35,MATCH(ROW()-9,'⚙ Census Engine'!$AC$10:$AC$35,0)),"") -> DTX | J10: =IFERROR(INDEX('⚙ Census Engine'!$AM$10:$AM$35,MATCH(ROW()-9,'⚙ Census Engine'!$AC$10:$AC$35,0)),"") -> Anthem BC
A11: =IFERROR(INDEX('⚙ Census Engine'!$AD$10:$AD$35,MATCH(ROW()-9,'⚙ Census Engine'!$AC$10:$AC$35,0)),"") -> Darian Loehner | B11: =IFERROR(INDEX('⚙ Census Engine'!$AE$10:$AE$35,MATCH(ROW()-9,'⚙ Census Engine'!$AC$10:$AC$35,0)),"") -> HP | C11: =IFERROR(INDEX('⚙ Census Engine'!$AF$10:$AF$35,MATCH(ROW()-9,'⚙ Census Engine'!$AC$10:$AC$35,0)),"") -> M2-B | D11: =IFERROR(INDEX('⚙ Census Engine'!$AG$10:$AG$35,MATCH(ROW()-9,'⚙ Census Engine'!$AC$10:$AC$35,0)),"") -> 6/10 | E11: =IFERROR(INDEX('⚙ Census Engine'!$AH$10:$AH$35,MATCH(ROW()-9,'⚙ Census Engine'!$AC$10:$AC$35,0)),"") -> 7 | F11: =IFERROR(INDEX('⚙ Census Engine'!$AI$10:$AI$35,MATCH(ROW()-9,'⚙ Census Engine'!$AC$10:$AC$35,0)),"") -> 6/20 | G11: =IFERROR(INDEX('⚙ Census Engine'!$AJ$10:$AJ$35,MATCH(ROW()-9,'⚙ Census Engine'!$AC$10:$AC$35,0)),"") -> 3d | H11: =IFERROR(INDEX('⚙ Census Engine'!$AK$10:$AK$35,MATCH(ROW()-9,'⚙ Census Engine'!$AC$10:$AC$35,0)),"") -> Amy | I11: =IFERROR(INDEX('⚙ Census Engine'!$AL$10:$AL$35,MATCH(ROW()-9,'⚙ Census Engine'!$AC$10:$AC$35,0)),"") -> DTX | J11: =IFERROR(INDEX('⚙ Census Engine'!$AM$10:$AM$35,MATCH(ROW()-9,'⚙ Census Engine'!$AC$10:$AC$35,0)),"") -> Aetna
A12: =IFERROR(INDEX('⚙ Census Engine'!$AD$10:$AD$35,MATCH(ROW()-9,'⚙ Census Engine'!$AC$10:$AC$35,0)),"") -> Monica Gamboa | B12: =IFERROR(INDEX('⚙ Census Engine'!$AE$10:$AE$35,MATCH(ROW()-9,'⚙ Census Engine'!$AC$10:$AC$35,0)),"") -> HP | C12: =IFERROR(INDEX('⚙ Census Engine'!$AF$10:$AF$35,MATCH(ROW()-9,'⚙ Census Engine'!$AC$10:$AC$35,0)),"") -> M3-B | D12: =IFERROR(INDEX('⚙ Census Engine'!$AG$10:$AG$35,MATCH(ROW()-9,'⚙ Census Engine'!$AC$10:$AC$35,0)),"") -> 6/11 | E12: =IFERROR(INDEX('⚙ Census Engine'!$AH$10:$AH$35,MATCH(ROW()-9,'⚙ Census Engine'!$AC$10:$AC$35,0)),"") -> 6 | F12: =IFERROR(INDEX('⚙ Census Engine'!$AI$10:$AI$35,MATCH(ROW()-9,'⚙ Census Engine'!$AC$10:$AC$35,0)),"") -> 6/21 | G12: =IFERROR(INDEX('⚙ Census Engine'!$AJ$10:$AJ$35,MATCH(ROW()-9,'⚙ Census Engine'!$AC$10:$AC$35,0)),"") -> 4d | H12: =IFERROR(INDEX('⚙ Census Engine'!$AK$10:$AK$35,MATCH(ROW()-9,'⚙ Census Engine'!$AC$10:$AC$35,0)),"") -> Amy | I12: =IFERROR(INDEX('⚙ Census Engine'!$AL$10:$AL$35,MATCH(ROW()-9,'⚙ Census Engine'!$AC$10:$AC$35,0)),"") -> DTX/RTC | J12: =IFERROR(INDEX('⚙ Census Engine'!$AM$10:$AM$35,MATCH(ROW()-9,'⚙ Census Engine'!$AC$10:$AC$35,0)),"") -> Molina CA
A13: =IFERROR(INDEX('⚙ Census Engine'!$AD$10:$AD$35,MATCH(ROW()-9,'⚙ Census Engine'!$AC$10:$AC$35,0)),"") -> Allisa Leuvrey | B13: =IFERROR(INDEX('⚙ Census Engine'!$AE$10:$AE$35,MATCH(ROW()-9,'⚙ Census Engine'!$AC$10:$AC$35,0)),"") -> HPE | C13: =IFERROR(INDEX('⚙ Census Engine'!$AF$10:$AF$35,MATCH(ROW()-9,'⚙ Census Engine'!$AC$10:$AC$35,0)),"") -> H1-1A | D13: =IFERROR(INDEX('⚙ Census Engine'!$AG$10:$AG$35,MATCH(ROW()-9,'⚙ Census Engine'!$AC$10:$AC$35,0)),"") -> 6/12 | E13: =IFERROR(INDEX('⚙ Census Engine'!$AH$10:$AH$35,MATCH(ROW()-9,'⚙ Census Engine'!$AC$10:$AC$35,0)),"") -> 5 | F13: =IFERROR(INDEX('⚙ Census Engine'!$AI$10:$AI$35,MATCH(ROW()-9,'⚙ Census Engine'!$AC$10:$AC$35,0)),"") -> 6/19 | G13: =IFERROR(INDEX('⚙ Census Engine'!$AJ$10:$AJ$35,MATCH(ROW()-9,'⚙ Census Engine'!$AC$10:$AC$35,0)),"") -> 2d | H13: =IFERROR(INDEX('⚙ Census Engine'!$AK$10:$AK$35,MATCH(ROW()-9,'⚙ Census Engine'!$AC$10:$AC$35,0)),"") -> Amy | I13: =IFERROR(INDEX('⚙ Census Engine'!$AL$10:$AL$35,MATCH(ROW()-9,'⚙ Census Engine'!$AC$10:$AC$35,0)),"") -> DTX | J13: =IFERROR(INDEX('⚙ Census Engine'!$AM$10:$AM$35,MATCH(ROW()-9,'⚙ Census Engine'!$AC$10:$AC$35,0)),"") -> Blue Shield CA
A14: =IFERROR(INDEX('⚙ Census Engine'!$AD$10:$AD$35,MATCH(ROW()-9,'⚙ Census Engine'!$AC$10:$AC$35,0)),"") | B14: =IFERROR(INDEX('⚙ Census Engine'!$AE$10:$AE$35,MATCH(ROW()-9,'⚙ Census Engine'!$AC$10:$AC$35,0)),"") | C14: =IFERROR(INDEX('⚙ Census Engine'!$AF$10:$AF$35,MATCH(ROW()-9,'⚙ Census Engine'!$AC$10:$AC$35,0)),"") | D14: =IFERROR(INDEX('⚙ Census Engine'!$AG$10:$AG$35,MATCH(ROW()-9,'⚙ Census Engine'!$AC$10:$AC$35,0)),"") | E14: =IFERROR(INDEX('⚙ Census Engine'!$AH$10:$AH$35,MATCH(ROW()-9,'⚙ Census Engine'!$AC$10:$AC$35,0)),"") | F14: =IFERROR(INDEX('⚙ Census Engine'!$AI$10:$AI$35,MATCH(ROW()-9,'⚙ Census Engine'!$AC$10:$AC$35,0)),"") | G14: =IFERROR(INDEX('⚙ Census Engine'!$AJ$10:$AJ$35,MATCH(ROW()-9,'⚙ Census Engine'!$AC$10:$AC$35,0)),"") | H14: =IFERROR(INDEX('⚙ Census Engine'!$AK$10:$AK$35,MATCH(ROW()-9,'⚙ Census Engine'!$AC$10:$AC$35,0)),"") | I14: =IFERROR(INDEX('⚙ Census Engine'!$AL$10:$AL$35,MATCH(ROW()-9,'⚙ Census Engine'!$AC$10:$AC$35,0)),"") | J14: =IFERROR(INDEX('⚙ Census Engine'!$AM$10:$AM$35,MATCH(ROW()-9,'⚙ Census Engine'!$AC$10:$AC$35,0)),"")
A15: =IFERROR(INDEX('⚙ Census Engine'!$AD$10:$AD$35,MATCH(ROW()-9,'⚙ Census Engine'!$AC$10:$AC$35,0)),"") | B15: =IFERROR(INDEX('⚙ Census Engine'!$AE$10:$AE$35,MATCH(ROW()-9,'⚙ Census Engine'!$AC$10:$AC$35,0)),"") | C15: =IFERROR(INDEX('⚙ Census Engine'!$AF$10:$AF$35,MATCH(ROW()-9,'⚙ Census Engine'!$AC$10:$AC$35,0)),"") | D15: =IFERROR(INDEX('⚙ Census Engine'!$AG$10:$AG$35,MATCH(ROW()-9,'⚙ Census Engine'!$AC$10:$AC$35,0)),"") | E15: =IFERROR(INDEX('⚙ Census Engine'!$AH$10:$AH$35,MATCH(ROW()-9,'⚙ Census Engine'!$AC$10:$AC$35,0)),"") | F15: =IFERROR(INDEX('⚙ Census Engine'!$AI$10:$AI$35,MATCH(ROW()-9,'⚙ Census Engine'!$AC$10:$AC$35,0)),"") | G15: =IFERROR(INDEX('⚙ Census Engine'!$AJ$10:$AJ$35,MATCH(ROW()-9,'⚙ Census Engine'!$AC$10:$AC$35,0)),"") | H15: =IFERROR(INDEX('⚙ Census Engine'!$AK$10:$AK$35,MATCH(ROW()-9,'⚙ Census Engine'!$AC$10:$AC$35,0)),"") | I15: =IFERROR(INDEX('⚙ Census Engine'!$AL$10:$AL$35,MATCH(ROW()-9,'⚙ Census Engine'!$AC$10:$AC$35,0)),"") | J15: =IFERROR(INDEX('⚙ Census Engine'!$AM$10:$AM$35,MATCH(ROW()-9,'⚙ Census Engine'!$AC$10:$AC$35,0)),"")
A16: =IFERROR(INDEX('⚙ Census Engine'!$AD$10:$AD$35,MATCH(ROW()-9,'⚙ Census Engine'!$AC$10:$AC$35,0)),"") | B16: =IFERROR(INDEX('⚙ Census Engine'!$AE$10:$AE$35,MATCH(ROW()-9,'⚙ Census Engine'!$AC$10:$AC$35,0)),"") | C16: =IFERROR(INDEX('⚙ Census Engine'!$AF$10:$AF$35,MATCH(ROW()-9,'⚙ Census Engine'!$AC$10:$AC$35,0)),"") | D16: =IFERROR(INDEX('⚙ Census Engine'!$AG$10:$AG$35,MATCH(ROW()-9,'⚙ Census Engine'!$AC$10:$AC$35,0)),"") | E16: =IFERROR(INDEX('⚙ Census Engine'!$AH$10:$AH$35,MATCH(ROW()-9,'⚙ Census Engine'!$AC$10:$AC$35,0)),"") | F16: =IFERROR(INDEX('⚙ Census Engine'!$AI$10:$AI$35,MATCH(ROW()-9,'⚙ Census Engine'!$AC$10:$AC$35,0)),"") | G16: =IFERROR(INDEX('⚙ Census Engine'!$AJ$10:$AJ$35,MATCH(ROW()-9,'⚙ Census Engine'!$AC$10:$AC$35,0)),"") | H16: =IFERROR(INDEX('⚙ Census Engine'!$AK$10:$AK$35,MATCH(ROW()-9,'⚙ Census Engine'!$AC$10:$AC$35,0)),"") | I16: =IFERROR(INDEX('⚙ Census Engine'!$AL$10:$AL$35,MATCH(ROW()-9,'⚙ Census Engine'!$AC$10:$AC$35,0)),"") | J16: =IFERROR(INDEX('⚙ Census Engine'!$AM$10:$AM$35,MATCH(ROW()-9,'⚙ Census Engine'!$AC$10:$AC$35,0)),"")
A17: =IFERROR(INDEX('⚙ Census Engine'!$AD$10:$AD$35,MATCH(ROW()-9,'⚙ Census Engine'!$AC$10:$AC$35,0)),"") | B17: =IFERROR(INDEX('⚙ Census Engine'!$AE$10:$AE$35,MATCH(ROW()-9,'⚙ Census Engine'!$AC$10:$AC$35,0)),"") | C17: =IFERROR(INDEX('⚙ Census Engine'!$AF$10:$AF$35,MATCH(ROW()-9,'⚙ Census Engine'!$AC$10:$AC$35,0)),"") | D17: =IFERROR(INDEX('⚙ Census Engine'!$AG$10:$AG$35,MATCH(ROW()-9,'⚙ Census Engine'!$AC$10:$AC$35,0)),"") | E17: =IFERROR(INDEX('⚙ Census Engine'!$AH$10:$AH$35,MATCH(ROW()-9,'⚙ Census Engine'!$AC$10:$AC$35,0)),"") | F17: =IFERROR(INDEX('⚙ Census Engine'!$AI$10:$AI$35,MATCH(ROW()-9,'⚙ Census Engine'!$AC$10:$AC$35,0)),"") | G17: =IFERROR(INDEX('⚙ Census Engine'!$AJ$10:$AJ$35,MATCH(ROW()-9,'⚙ Census Engine'!$AC$10:$AC$35,0)),"") | H17: =IFERROR(INDEX('⚙ Census Engine'!$AK$10:$AK$35,MATCH(ROW()-9,'⚙ Census Engine'!$AC$10:$AC$35,0)),"") | I17: =IFERROR(INDEX('⚙ Census Engine'!$AL$10:$AL$35,MATCH(ROW()-9,'⚙ Census Engine'!$AC$10:$AC$35,0)),"") | J17: =IFERROR(INDEX('⚙ Census Engine'!$AM$10:$AM$35,MATCH(ROW()-9,'⚙ Census Engine'!$AC$10:$AC$35,0)),"")
A18: =IFERROR(INDEX('⚙ Census Engine'!$AD$10:$AD$35,MATCH(ROW()-9,'⚙ Census Engine'!$AC$10:$AC$35,0)),"") | B18: =IFERROR(INDEX('⚙ Census Engine'!$AE$10:$AE$35,MATCH(ROW()-9,'⚙ Census Engine'!$AC$10:$AC$35,0)),"") | C18: =IFERROR(INDEX('⚙ Census Engine'!$AF$10:$AF$35,MATCH(ROW()-9,'⚙ Census Engine'!$AC$10:$AC$35,0)),"") | D18: =IFERROR(INDEX('⚙ Census Engine'!$AG$10:$AG$35,MATCH(ROW()-9,'⚙ Census Engine'!$AC$10:$AC$35,0)),"") | E18: =IFERROR(INDEX('⚙ Census Engine'!$AH$10:$AH$35,MATCH(ROW()-9,'⚙ Census Engine'!$AC$10:$AC$35,0)),"") | F18: =IFERROR(INDEX('⚙ Census Engine'!$AI$10:$AI$35,MATCH(ROW()-9,'⚙ Census Engine'!$AC$10:$AC$35,0)),"") | G18: =IFERROR(INDEX('⚙ Census Engine'!$AJ$10:$AJ$35,MATCH(ROW()-9,'⚙ Census Engine'!$AC$10:$AC$35,0)),"") | H18: =IFERROR(INDEX('⚙ Census Engine'!$AK$10:$AK$35,MATCH(ROW()-9,'⚙ Census Engine'!$AC$10:$AC$35,0)),"") | I18: =IFERROR(INDEX('⚙ Census Engine'!$AL$10:$AL$35,MATCH(ROW()-9,'⚙ Census Engine'!$AC$10:$AC$35,0)),"") | J18: =IFERROR(INDEX('⚙ Census Engine'!$AM$10:$AM$35,MATCH(ROW()-9,'⚙ Census Engine'!$AC$10:$AC$35,0)),"")
A19: =IFERROR(INDEX('⚙ Census Engine'!$AD$10:$AD$35,MATCH(ROW()-9,'⚙ Census Engine'!$AC$10:$AC$35,0)),"") | B19: =IFERROR(INDEX('⚙ Census Engine'!$AE$10:$AE$35,MATCH(ROW()-9,'⚙ Census Engine'!$AC$10:$AC$35,0)),"") | C19: =IFERROR(INDEX('⚙ Census Engine'!$AF$10:$AF$35,MATCH(ROW()-9,'⚙ Census Engine'!$AC$10:$AC$35,0)),"") | D19: =IFERROR(INDEX('⚙ Census Engine'!$AG$10:$AG$35,MATCH(ROW()-9,'⚙ Census Engine'!$AC$10:$AC$35,0)),"") | E19: =IFERROR(INDEX('⚙ Census Engine'!$AH$10:$AH$35,MATCH(ROW()-9,'⚙ Census Engine'!$AC$10:$AC$35,0)),"") | F19: =IFERROR(INDEX('⚙ Census Engine'!$AI$10:$AI$35,MATCH(ROW()-9,'⚙ Census Engine'!$AC$10:$AC$35,0)),"") | G19: =IFERROR(INDEX('⚙ Census Engine'!$AJ$10:$AJ$35,MATCH(ROW()-9,'⚙ Census Engine'!$AC$10:$AC$35,0)),"") | H19: =IFERROR(INDEX('⚙ Census Engine'!$AK$10:$AK$35,MATCH(ROW()-9,'⚙ Census Engine'!$AC$10:$AC$35,0)),"") | I19: =IFERROR(INDEX('⚙ Census Engine'!$AL$10:$AL$35,MATCH(ROW()-9,'⚙ Census Engine'!$AC$10:$AC$35,0)),"") | J19: =IFERROR(INDEX('⚙ Census Engine'!$AM$10:$AM$35,MATCH(ROW()-9,'⚙ Census Engine'!$AC$10:$AC$35,0)),"")
A20: =IFERROR(INDEX('⚙ Census Engine'!$AD$10:$AD$35,MATCH(ROW()-9,'⚙ Census Engine'!$AC$10:$AC$35,0)),"") | B20: =IFERROR(INDEX('⚙ Census Engine'!$AE$10:$AE$35,MATCH(ROW()-9,'⚙ Census Engine'!$AC$10:$AC$35,0)),"") | C20: =IFERROR(INDEX('⚙ Census Engine'!$AF$10:$AF$35,MATCH(ROW()-9,'⚙ Census Engine'!$AC$10:$AC$35,0)),"") | D20: =IFERROR(INDEX('⚙ Census Engine'!$AG$10:$AG$35,MATCH(ROW()-9,'⚙ Census Engine'!$AC$10:$AC$35,0)),"") | E20: =IFERROR(INDEX('⚙ Census Engine'!$AH$10:$AH$35,MATCH(ROW()-9,'⚙ Census Engine'!$AC$10:$AC$35,0)),"") | F20: =IFERROR(INDEX('⚙ Census Engine'!$AI$10:$AI$35,MATCH(ROW()-9,'⚙ Census Engine'!$AC$10:$AC$35,0)),"") | G20: =IFERROR(INDEX('⚙ Census Engine'!$AJ$10:$AJ$35,MATCH(ROW()-9,'⚙ Census Engine'!$AC$10:$AC$35,0)),"") | H20: =IFERROR(INDEX('⚙ Census Engine'!$AK$10:$AK$35,MATCH(ROW()-9,'⚙ Census Engine'!$AC$10:$AC$35,0)),"") | I20: =IFERROR(INDEX('⚙ Census Engine'!$AL$10:$AL$35,MATCH(ROW()-9,'⚙ Census Engine'!$AC$10:$AC$35,0)),"") | J20: =IFERROR(INDEX('⚙ Census Engine'!$AM$10:$AM$35,MATCH(ROW()-9,'⚙ Census Engine'!$AC$10:$AC$35,0)),"")
A21: =IFERROR(INDEX('⚙ Census Engine'!$AD$10:$AD$35,MATCH(ROW()-9,'⚙ Census Engine'!$AC$10:$AC$35,0)),"") | B21: =IFERROR(INDEX('⚙ Census Engine'!$AE$10:$AE$35,MATCH(ROW()-9,'⚙ Census Engine'!$AC$10:$AC$35,0)),"") | C21: =IFERROR(INDEX('⚙ Census Engine'!$AF$10:$AF$35,MATCH(ROW()-9,'⚙ Census Engine'!$AC$10:$AC$35,0)),"") | D21: =IFERROR(INDEX('⚙ Census Engine'!$AG$10:$AG$35,MATCH(ROW()-9,'⚙ Census Engine'!$AC$10:$AC$35,0)),"") | E21: =IFERROR(INDEX('⚙ Census Engine'!$AH$10:$AH$35,MATCH(ROW()-9,'⚙ Census Engine'!$AC$10:$AC$35,0)),"") | F21: =IFERROR(INDEX('⚙ Census Engine'!$AI$10:$AI$35,MATCH(ROW()-9,'⚙ Census Engine'!$AC$10:$AC$35,0)),"") | G21: =IFERROR(INDEX('⚙ Census Engine'!$AJ$10:$AJ$35,MATCH(ROW()-9,'⚙ Census Engine'!$AC$10:$AC$35,0)),"") | H21: =IFERROR(INDEX('⚙ Census Engine'!$AK$10:$AK$35,MATCH(ROW()-9,'⚙ Census Engine'!$AC$10:$AC$35,0)),"") | I21: =IFERROR(INDEX('⚙ Census Engine'!$AL$10:$AL$35,MATCH(ROW()-9,'⚙ Census Engine'!$AC$10:$AC$35,0)),"") | J21: =IFERROR(INDEX('⚙ Census Engine'!$AM$10:$AM$35,MATCH(ROW()-9,'⚙ Census Engine'!$AC$10:$AC$35,0)),"")
A23: 📥 SCHEDULED INTAKES — auto-pulled from Pipeline (Status = Scheduled)
A24: Client | B24: Rep | C24: Fac | D24: LOC | E24: Insurance | F24: Intake | G24: VOB
A25: =IFERROR(INDEX('🔥 Pipeline'!$C:$C,MATCH(ROW()-24,'⚙ Pipeline Engine'!$AB:$AB,0)),"") -> Tara Shinde | B25: =IFERROR(INDEX('🔥 Pipeline'!$B:$B,MATCH(ROW()-24,'⚙ Pipeline Engine'!$AB:$AB,0)),"") -> Amy | C25: =IFERROR(INDEX('🔥 Pipeline'!$F:$F,MATCH(ROW()-24,'⚙ Pipeline Engine'!$AB:$AB,0)),"") -> HPE | D25: =IFERROR(INDEX('🔥 Pipeline'!$E:$E,MATCH(ROW()-24,'⚙ Pipeline Engine'!$AB:$AB,0)),"") -> DTX/RTC | E25: =IFERROR(INDEX('🔥 Pipeline'!$I:$I,MATCH(ROW()-24,'⚙ Pipeline Engine'!$AB:$AB,0)),"") -> BCBS IL | F25: =IFERROR(INDEX('🔥 Pipeline'!$H:$H,MATCH(ROW()-24,'⚙ Pipeline Engine'!$AB:$AB,0)),"") -> 46192 | G25: =IFERROR(INDEX('🔥 Pipeline'!$G:$G,MATCH(ROW()-24,'⚙ Pipeline Engine'!$AB:$AB,0)),"") -> ✓
A26: =IFERROR(INDEX('🔥 Pipeline'!$C:$C,MATCH(ROW()-24,'⚙ Pipeline Engine'!$AB:$AB,0)),"") | B26: =IFERROR(INDEX('🔥 Pipeline'!$B:$B,MATCH(ROW()-24,'⚙ Pipeline Engine'!$AB:$AB,0)),"") | C26: =IFERROR(INDEX('🔥 Pipeline'!$F:$F,MATCH(ROW()-24,'⚙ Pipeline Engine'!$AB:$AB,0)),"") | D26: =IFERROR(INDEX('🔥 Pipeline'!$E:$E,MATCH(ROW()-24,'⚙ Pipeline Engine'!$AB:$AB,0)),"") | E26: =IFERROR(INDEX('🔥 Pipeline'!$I:$I,MATCH(ROW()-24,'⚙ Pipeline Engine'!$AB:$AB,0)),"") | F26: =IFERROR(INDEX('🔥 Pipeline'!$H:$H,MATCH(ROW()-24,'⚙ Pipeline Engine'!$AB:$AB,0)),"") | G26: =IFERROR(INDEX('🔥 Pipeline'!$G:$G,MATCH(ROW()-24,'⚙ Pipeline Engine'!$AB:$AB,0)),"")
A27: =IFERROR(INDEX('🔥 Pipeline'!$C:$C,MATCH(ROW()-24,'⚙ Pipeline Engine'!$AB:$AB,0)),"") | B27: =IFERROR(INDEX('🔥 Pipeline'!$B:$B,MATCH(ROW()-24,'⚙ Pipeline Engine'!$AB:$AB,0)),"") | C27: =IFERROR(INDEX('🔥 Pipeline'!$F:$F,MATCH(ROW()-24,'⚙ Pipeline Engine'!$AB:$AB,0)),"") | D27: =IFERROR(INDEX('🔥 Pipeline'!$E:$E,MATCH(ROW()-24,'⚙ Pipeline Engine'!$AB:$AB,0)),"") | E27: =IFERROR(INDEX('🔥 Pipeline'!$I:$I,MATCH(ROW()-24,'⚙ Pipeline Engine'!$AB:$AB,0)),"") | F27: =IFERROR(INDEX('🔥 Pipeline'!$H:$H,MATCH(ROW()-24,'⚙ Pipeline Engine'!$AB:$AB,0)),"") | G27: =IFERROR(INDEX('🔥 Pipeline'!$G:$G,MATCH(ROW()-24,'⚙ Pipeline Engine'!$AB:$AB,0)),"")
A28: =IFERROR(INDEX('🔥 Pipeline'!$C:$C,MATCH(ROW()-24,'⚙ Pipeline Engine'!$AB:$AB,0)),"") | B28: =IFERROR(INDEX('🔥 Pipeline'!$B:$B,MATCH(ROW()-24,'⚙ Pipeline Engine'!$AB:$AB,0)),"") | C28: =IFERROR(INDEX('🔥 Pipeline'!$F:$F,MATCH(ROW()-24,'⚙ Pipeline Engine'!$AB:$AB,0)),"") | D28: =IFERROR(INDEX('🔥 Pipeline'!$E:$E,MATCH(ROW()-24,'⚙ Pipeline Engine'!$AB:$AB,0)),"") | E28: =IFERROR(INDEX('🔥 Pipeline'!$I:$I,MATCH(ROW()-24,'⚙ Pipeline Engine'!$AB:$AB,0)),"") | F28: =IFERROR(INDEX('🔥 Pipeline'!$H:$H,MATCH(ROW()-24,'⚙ Pipeline Engine'!$AB:$AB,0)),"") | G28: =IFERROR(INDEX('🔥 Pipeline'!$G:$G,MATCH(ROW()-24,'⚙ Pipeline Engine'!$AB:$AB,0)),"")
A29: =IFERROR(INDEX('🔥 Pipeline'!$C:$C,MATCH(ROW()-24,'⚙ Pipeline Engine'!$AB:$AB,0)),"") | B29: =IFERROR(INDEX('🔥 Pipeline'!$B:$B,MATCH(ROW()-24,'⚙ Pipeline Engine'!$AB:$AB,0)),"") | C29: =IFERROR(INDEX('🔥 Pipeline'!$F:$F,MATCH(ROW()-24,'⚙ Pipeline Engine'!$AB:$AB,0)),"") | D29: =IFERROR(INDEX('🔥 Pipeline'!$E:$E,MATCH(ROW()-24,'⚙ Pipeline Engine'!$AB:$AB,0)),"") | E29: =IFERROR(INDEX('🔥 Pipeline'!$I:$I,MATCH(ROW()-24,'⚙ Pipeline Engine'!$AB:$AB,0)),"") | F29: =IFERROR(INDEX('🔥 Pipeline'!$H:$H,MATCH(ROW()-24,'⚙ Pipeline Engine'!$AB:$AB,0)),"") | G29: =IFERROR(INDEX('🔥 Pipeline'!$G:$G,MATCH(ROW()-24,'⚙ Pipeline Engine'!$AB:$AB,0)),"")
A30: =IFERROR(INDEX('🔥 Pipeline'!$C:$C,MATCH(ROW()-24,'⚙ Pipeline Engine'!$AB:$AB,0)),"") | B30: =IFERROR(INDEX('🔥 Pipeline'!$B:$B,MATCH(ROW()-24,'⚙ Pipeline Engine'!$AB:$AB,0)),"") | C30: =IFERROR(INDEX('🔥 Pipeline'!$F:$F,MATCH(ROW()-24,'⚙ Pipeline Engine'!$AB:$AB,0)),"") | D30: =IFERROR(INDEX('🔥 Pipeline'!$E:$E,MATCH(ROW()-24,'⚙ Pipeline Engine'!$AB:$AB,0)),"") | E30: =IFERROR(INDEX('🔥 Pipeline'!$I:$I,MATCH(ROW()-24,'⚙ Pipeline Engine'!$AB:$AB,0)),"") | F30: =IFERROR(INDEX('🔥 Pipeline'!$H:$H,MATCH(ROW()-24,'⚙ Pipeline Engine'!$AB:$AB,0)),"") | G30: =IFERROR(INDEX('🔥 Pipeline'!$G:$G,MATCH(ROW()-24,'⚙ Pipeline Engine'!$AB:$AB,0)),"")
A31: =IFERROR(INDEX('🔥 Pipeline'!$C:$C,MATCH(ROW()-24,'⚙ Pipeline Engine'!$AB:$AB,0)),"") | B31: =IFERROR(INDEX('🔥 Pipeline'!$B:$B,MATCH(ROW()-24,'⚙ Pipeline Engine'!$AB:$AB,0)),"") | C31: =IFERROR(INDEX('🔥 Pipeline'!$F:$F,MATCH(ROW()-24,'⚙ Pipeline Engine'!$AB:$AB,0)),"") | D31: =IFERROR(INDEX('🔥 Pipeline'!$E:$E,MATCH(ROW()-24,'⚙ Pipeline Engine'!$AB:$AB,0)),"") | E31: =IFERROR(INDEX('🔥 Pipeline'!$I:$I,MATCH(ROW()-24,'⚙ Pipeline Engine'!$AB:$AB,0)),"") | F31: =IFERROR(INDEX('🔥 Pipeline'!$H:$H,MATCH(ROW()-24,'⚙ Pipeline Engine'!$AB:$AB,0)),"") | G31: =IFERROR(INDEX('🔥 Pipeline'!$G:$G,MATCH(ROW()-24,'⚙ Pipeline Engine'!$AB:$AB,0)),"")
A33: =" 📈 ADMISSIONS BY REP — "&'⚙ Lists'!$AB$10&" (current month · auto-rolls)" -> 📈 ADMISSIONS BY REP — 📋 Jun 2026 (current month · auto-rolls)
A34: Rep | B34: Admits | C34: Pace | D34: Met-CT | E34: Met-CT %
A35: Amy (weekdays) | B35: =SUMIFS('⚙ Production Engine'!$C:$C,'⚙ Production Engine'!$A:$A,'⚙ Lists'!$AB$10,'⚙ Production Engine'!$B:$B,"Amy") -> 5 | C35: =REPT("█",B35)&REPT("░",MAX(0,15-B35)) -> █████░░░░░░░░░░ | D35: =SUMIFS('⚙ Production Engine'!$D:$D,'⚙ Production Engine'!$A:$A,'⚙ Lists'!$AB$10,'⚙ Production Engine'!$B:$B,"Amy") -> 5 | E35: =IFERROR(IF(B35=0,"—",D35/B35),"—") -> 1
A36: Nelson (weekdays) | B36: =SUMIFS('⚙ Production Engine'!$C:$C,'⚙ Production Engine'!$A:$A,'⚙ Lists'!$AB$10,'⚙ Production Engine'!$B:$B,"Nelson") -> 2 | C36: =REPT("█",B36)&REPT("░",MAX(0,15-B36)) -> ██░░░░░░░░░░░░░ | D36: =SUMIFS('⚙ Production Engine'!$D:$D,'⚙ Production Engine'!$A:$A,'⚙ Lists'!$AB$10,'⚙ Production Engine'!$B:$B,"Nelson") -> 2 | E36: =IFERROR(IF(B36=0,"—",D36/B36),"—") -> 1
A37: Matthew (weekends) | B37: =SUMIFS('⚙ Production Engine'!$C:$C,'⚙ Production Engine'!$A:$A,'⚙ Lists'!$AB$10,'⚙ Production Engine'!$B:$B,"Matthew") -> 4 | C37: =REPT("█",B37)&REPT("░",MAX(0,15-B37)) -> ████░░░░░░░░░░░ | D37: =SUMIFS('⚙ Production Engine'!$D:$D,'⚙ Production Engine'!$A:$A,'⚙ Lists'!$AB$10,'⚙ Production Engine'!$B:$B,"Matthew") -> 1 | E37: =IFERROR(IF(B37=0,"—",D37/B37),"—") -> 0.25
A38: Ahbra (evenings) | B38: =SUMIFS('⚙ Production Engine'!$C:$C,'⚙ Production Engine'!$A:$A,'⚙ Lists'!$AB$10,'⚙ Production Engine'!$B:$B,"Ahbra") -> 2 | C38: =REPT("█",B38)&REPT("░",MAX(0,15-B38)) -> ██░░░░░░░░░░░░░ | D38: =SUMIFS('⚙ Production Engine'!$D:$D,'⚙ Production Engine'!$A:$A,'⚙ Lists'!$AB$10,'⚙ Production Engine'!$B:$B,"Ahbra") -> 1 | E38: =IFERROR(IF(B38=0,"—",D38/B38),"—") -> 0.5
A39: Amos (on leave) | B39: =SUMIFS('⚙ Production Engine'!$C:$C,'⚙ Production Engine'!$A:$A,'⚙ Lists'!$AB$10,'⚙ Production Engine'!$B:$B,"Amos") -> 0 | C39: =REPT("█",B39)&REPT("░",MAX(0,15-B39)) -> ░░░░░░░░░░░░░░░ | D39: =SUMIFS('⚙ Production Engine'!$D:$D,'⚙ Production Engine'!$A:$A,'⚙ Lists'!$AB$10,'⚙ Production Engine'!$B:$B,"Amos") -> 0 | E39: =IFERROR(IF(B39=0,"—",D39/B39),"—") -> —
A40: TEAM | B40: =SUM(B35:B39) -> 13 | D40: =SUM(D35:D39) -> 9 | E40: =IFERROR(D40/B40,"—") -> 0.69230769
A42: 📊 OCCUPANCY & OPEN-BED REVENUE AT RISK
A43: House | B43: Occupied | C43: Capacity | D43: Open
A44: Harmony Place (HP) | B44: =COUNTIF('🛏 HP Bed Board'!B10:B23,"Occupied") -> 11 | C44: 14 | D44: =COUNTIF('🛏 HP Bed Board'!B10:B23,"Open") -> 3 | E44: =REPT("█",ROUND(B44/C44*20,0))&REPT("░",20-ROUND(B44/C44*20,0))&" "&TEXT(B44/C44,"0%") -> ████████████████░░░░ 79%
A45: Harmony Place East (HPE) | B45: =(COUNTIF('🛏 HPE Bed Board'!B11:B16,"Occupied")+COUNTIF('🛏 HPE Bed Board'!B18:B23,"Occupied")) -> 9 | C45: 12 | D45: =(COUNTIF('🛏 HPE Bed Board'!B11:B16,"Open")+COUNTIF('🛏 HPE Bed Board'!B18:B23,"Open")) -> 2 | E45: =REPT("█",ROUND(B45/C45*20,0))&REPT("░",20-ROUND(B45/C45*20,0))&" "&TEXT(B45/C45,"0%") -> ███████████████░░░░░ 75%
A46: COMBINED | B46: =B44+B45 -> 20 | C46: =C44+C45 -> 26 | D46: =D44+D45 -> 5 | E46: =REPT("█",ROUND(B46/C46*20,0))&REPT("░",20-ROUND(B46/C46*20,0))&" "&TEXT(B46/C46,"0%") -> ███████████████░░░░░ 77%
A48: Avg reimbursed bed-day rate (edit) | D48: 1150
A49: Billable days per month (edit) | D49: 30
A50: ⚠ Open-bed revenue at risk / month | D50: =D46*D48*D49 -> 172500
A51: Est. monthly billings at current census | D51: =B46*D48*D49 -> 690000
A53: 🔥 PIPELINE FUNNEL (live)
A54: Scheduled | B54: =REPT("█",D54*2)&REPT("░",MAX(0,20-D54*2)) -> ██░░░░░░░░░░░░░░░░░░ | D54: =COUNTIF('🔥 Pipeline'!$D$5:$D$40,"Scheduled") -> 1
A55: Prospect | B55: =REPT("█",D55*2)&REPT("░",MAX(0,20-D55*2)) -> ████████████░░░░░░░░ | D55: =COUNTIF('🔥 Pipeline'!$D$5:$D$40,"Prospect") -> 6
A56: Lead | B56: =REPT("█",D56*2)&REPT("░",MAX(0,20-D56*2)) -> ██████████░░░░░░░░░░ | D56: =COUNTIF('🔥 Pipeline'!$D$5:$D$40,"Lead") -> 5
A57: Hold | B57: =REPT("█",D57*2)&REPT("░",MAX(0,20-D57*2)) -> ░░░░░░░░░░░░░░░░░░░░ | D57: =COUNTIF('🔥 Pipeline'!$D$5:$D$40,"Hold") -> 0
A58: Total active leads | D58: =SUM(D54:D57) -> 12
A59: ⚠ Leads owned by Amos (on leave) — reassign | D59: =COUNTIF('🔥 Pipeline'!$B$5:$B$40,"Amos") -> 0
A61: ⚠ WATCH FLAGS
A62: Blue Shield CA share of this month's admits | D62: =IFERROR(COUNTIF(CHOOSE('⚙ Lists'!$AB$8,'📋 May 2026'!$M$5:$M$60,'📋 Jun 2026'!$M$5:$M$60,'📋 Jul 2026'!$M$5:$M$60,'📋 Aug 2026'!$M$5:$M$60,'📋 Sep 2026'!$M$5:$M$60,'📋 Oct 2026'!$M$5:$M$60,'📋 Nov 2026'!$M$5:$M$60,'📋 Dec 2026'!$M$5:$M$60),"Blue Shield CA")/COUNTIF(CHOOSE('⚙ Lists'!$AB$8,'📋 May 2026'!$B$5:$B$60,'📋 Jun 2026'!$B$5:$B$60,'📋 Jul 2026'!$B$5:$B$60,'📋 Aug 2026'!$B$5:$B$60,'📋 Sep 2026'!$B$5:$B$60,'📋 Oct 2026'!$B$5:$B$60,'📋 Nov 2026'!$B$5:$B$60,'📋 Dec 2026'!$B$5:$B$60),"?*"),0) -> 0.30769231
A63: Pipeline leads on NON-contracted payers | D63: =SUMPRODUCT(COUNTIF(NON_CONTRACTED,'🔥 Pipeline'!$I$5:$I$40)) -> 0
A64: Weekday closers active (Amy, Nelson) | D64: 2
A66: 🤝 BD REFERRALS — Ahbra
A67: Referrals SENT (this month) | D67: =IFERROR(IF(CHOOSE('⚙ Lists'!$AB$8,'📋 May 2026'!$K$2,'📋 Jun 2026'!$K$2,'📋 Jul 2026'!$K$2,'📋 Aug 2026'!$K$2,'📋 Sep 2026'!$K$2,'📋 Oct 2026'!$K$2,'📋 Nov 2026'!$K$2,'📋 Dec 2026'!$K$2)=0,"—",CHOOSE('⚙ Lists'!$AB$8,'📋 May 2026'!$K$2,'📋 Jun 2026'!$K$2,'📋 Jul 2026'!$K$2,'📋 Aug 2026'!$K$2,'📋 Sep 2026'!$K$2,'📋 Oct 2026'!$K$2,'📋 Nov 2026'!$K$2,'📋 Dec 2026'!$K$2)),"—") -> —
A68: Referrals ADMITTED (auto) | D68: =COUNTIF(CHOOSE('⚙ Lists'!$AB$8,'📋 May 2026'!$L$5:$L$60,'📋 Jun 2026'!$L$5:$L$60,'📋 Jul 2026'!$L$5:$L$60,'📋 Aug 2026'!$L$5:$L$60,'📋 Sep 2026'!$L$5:$L$60,'📋 Oct 2026'!$L$5:$L$60,'📋 Nov 2026'!$L$5:$L$60,'📋 Dec 2026'!$L$5:$L$60),"*Ahbra*") -> 2
A69: Conversion rate | D69: =IFERROR(D68/D67,"—") -> —
A72: 📈 PIPELINE & FLOW KPIs
A73: New Leads MTD | B73: Assessments | C73: Admissions MTD | D73: Conversion % | E73: Sched ≤7d | F73: Disch ≤7d | G73: Proj Census
A74: =COUNTIFS('🔥 Pipeline'!$S$5:$S$40,">="&(EOMONTH(TODAY(),-1)+1),'🔥 Pipeline'!$S$5:$S$40,"<="&TODAY()) -> 8 | B74: =COUNTIF('🔥 Pipeline'!$N$5:$N$40,"Completed") -> 1 | C74: =IFERROR(COUNTA(CHOOSE('⚙ Lists'!$AB$8,'📋 May 2026'!$B$5:$B$60,'📋 Jun 2026'!$B$5:$B$60,'📋 Jul 2026'!$B$5:$B$60,'📋 Aug 2026'!$B$5:$B$60,'📋 Sep 2026'!$B$5:$B$60,'📋 Oct 2026'!$B$5:$B$60,'📋 Nov 2026'!$B$5:$B$60,'📋 Dec 2026'!$B$5:$B$60)),0) -> 13 | D74: =IFERROR($C$74/($C$74+COUNTIF('🔥 Pipeline'!$P$5:$P$40,"Lost")+COUNTIF('🔥 Pipeline'!$P$5:$P$40,"Declined")+COUNTIF('🔥 Pipeline'!$P$5:$P$40,"Referred Out")),"—") -> 1 | E74: =COUNTIFS('🔥 Pipeline'!$D$5:$D$40,"Scheduled",'🔥 Pipeline'!$H$5:$H$40,">="&TODAY(),'🔥 Pipeline'!$H$5:$H$40,"<="&(TODAY()+7)) -> 1 | F74: =COUNTIFS('🛏 HP Bed Board'!B10:B23,"Occupied",'🛏 HP Bed Board'!H10:H23,">="&TODAY(),'🛏 HP Bed Board'!H10:H23,"<="&TODAY()+7)+COUNTIFS('🛏 HPE Bed Board'!B11:B16,"Occupied",'🛏 HPE Bed Board'!H11:H16,">="&TODAY(),'🛏 HPE Bed Board'!H11:H16,"<="&TODAY()+7)+COUNTIFS('🛏 HPE Bed Board'!B18:B23,"Occupied",'🛏 HPE Bed Board'!H18:H23,">="&TODAY(),'🛏 HPE Bed Board'!H18:H23,"<="&TODAY()+7) -> 4 | G74: =(COUNTIF('🛏 HP Bed Board'!B10:B23,"Occupied")+(COUNTIF('🛏 HPE Bed Board'!B11:B16,"Occupied")+COUNTIF('🛏 HPE Bed Board'!B18:B23,"Occupied")))-$F$74+$E$74 -> 17

Sheet 🖨 Meeting
A1: 🏥 HARMONY PLACE — ADMISSIONS MEETING
A2: ="As of "&TEXT(NOW(),"dddd, mmmm d, yyyy") -> As of Wednesday, June 17, 2026
A4: 🛏 CENSUS SNAPSHOT
A5: HP Census | B5: HPE Census | C5: Total | D5: Open Beds | E5: Reserved | F5: Adm MTD | G5: Conv % | H5: Proj 7d
A6: ='📊 Dashboard'!A6 -> 11/14 | B6: ='📊 Dashboard'!B6 -> 9/12 | C6: ='📊 Dashboard'!C6 -> 20/26 | D6: ='📊 Dashboard'!D6 -> 5 | E6: ='📊 Dashboard'!E6 -> 1 | F6: ='📊 Dashboard'!F6 -> 13 | G6: ='📊 Dashboard'!G6 -> 1 | H6: ='📊 Dashboard'!H6 -> 17
A8: =" ⚠ DISCHARGE WATCH — NEXT 7 DAYS ("&SUM('⚙ Census Engine'!$AB$10:$AB$35)&" total)" -> ⚠ DISCHARGE WATCH — NEXT 7 DAYS (4 total)
A9: Client | B9: Fac | C9: Room | D9: Admit | E9: Day # | F9: DC Date | G9: To DC | H9: Rep | I9: LOC | J9: Financial
A10: ='📊 Dashboard'!A10 -> Rhonda Baim | B10: ='📊 Dashboard'!B10 -> HPE | C10: ='📊 Dashboard'!C10 -> H1-2A | D10: ='📊 Dashboard'!D10 -> 5/24 | E10: ='📊 Dashboard'!E10 -> 24 | F10: ='📊 Dashboard'!F10 -> 6/23 | G10: ='📊 Dashboard'!G10 -> 6d | H10: ='📊 Dashboard'!H10 -> Nelson | ... J10: ='📊 Dashboard'!J10 -> Anthem BC
A11: ='📊 Dashboard'!A11 -> Darian Loehner | B11: ='📊 Dashboard'!B11 -> HP | C11: ='📊 Dashboard'!C11 -> M2-B | D11: ='📊 Dashboard'!D11 -> 6/10 | E11: ='📊 Dashboard'!E11 -> 7 | F11: ='📊 Dashboard'!F11 -> 6/20 | G11: ='📊 Dashboard'!G11 -> 3d | H11: ='📊 Dashboard'!H11 -> Amy | ... J11: ='📊 Dashboard'!J11 -> Aetna
A12: ='📊 Dashboard'!A12 -> Monica Gamboa | B12: ='📊 Dashboard'!B12 -> HP | C12: ='📊 Dashboard'!C12 -> M3-B | D12: ='📊 Dashboard'!D12 -> 6/11 | E12: ='📊 Dashboard'!E12 -> 6 | F12: ='📊 Dashboard'!F12 -> 6/21 | G12: ='📊 Dashboard'!G12 -> 4d | H12: ='📊 Dashboard'!H12 -> Amy | ... J12: ='📊 Dashboard'!J12 -> Molina CA
A13: ='📊 Dashboard'!A13 -> Allisa Leuvrey | B13: ='📊 Dashboard'!B13 -> HPE | C13: ='📊 Dashboard'!C13 -> H1-1A | D13: ='📊 Dashboard'!D13 -> 6/12 | E13: ='📊 Dashboard'!E13 -> 5 | F13: ='📊 Dashboard'!F13 -> 6/19 | G13: ='📊 Dashboard'!G13 -> 2d | H13: ='📊 Dashboard'!H13 -> Amy | ... J13: ='📊 Dashboard'!J13 -> Blue Shield CA
A14: ='📊 Dashboard'!A14 | B14: ='📊 Dashboard'!B14 | C14: ='📊 Dashboard'!C14 | D14: ='📊 Dashboard'!D14 | E14: ='📊 Dashboard'!E14 | F14: ='📊 Dashboard'!F14 | G14: ='📊 Dashboard'!G14 | H14: ='📊 Dashboard'!H14 | ... J14: ='📊 Dashboard'!J14
A15: ='📊 Dashboard'!A15 | B15: ='📊 Dashboard'!B15 | C15: ='📊 Dashboard'!C15 | D15: ='📊 Dashboard'!D15 | E15: ='📊 Dashboard'!E15 | F15: ='📊 Dashboard'!F15 | G15: ='📊 Dashboard'!G15 | H15: ='📊 Dashboard'!H15 | ... J15: ='📊 Dashboard'!J15
A16: ='📊 Dashboard'!A16 | B16: ='📊 Dashboard'!B16 | C16: ='📊 Dashboard'!C16 | D16: ='📊 Dashboard'!D16 | E16: ='📊 Dashboard'!E16 | F16: ='📊 Dashboard'!F16 | G16: ='📊 Dashboard'!G16 | H16: ='📊 Dashboard'!H16 | ... J16: ='📊 Dashboard'!J16
A17: ='📊 Dashboard'!A17 | B17: ='📊 Dashboard'!B17 | C17: ='📊 Dashboard'!C17 | D17: ='📊 Dashboard'!D17 | E17: ='📊 Dashboard'!E17 | F17: ='📊 Dashboard'!F17 | G17: ='📊 Dashboard'!G17 | H17: ='📊 Dashboard'!H17 | ... J17: ='📊 Dashboard'!J17
A19: =" 📅 SCHEDULED INTAKES ("&COUNTIF('🔥 Pipeline'!$D$5:$D$100,"Scheduled")&" scheduled)" -> 📅 SCHEDULED INTAKES (1 scheduled)
A20: Client | B20: Rep | C20: Fac | D20: LOC | E20: Insurance | F20: Intake | G20: VOB
A21: ='📊 Dashboard'!A25 -> Tara Shinde | B21: ='📊 Dashboard'!B25 -> Amy | C21: ='📊 Dashboard'!C25 -> HPE | D21: ='📊 Dashboard'!D25 -> DTX/RTC | E21: ='📊 Dashboard'!E25 -> BCBS IL | F21: ='📊 Dashboard'!F25 -> 46192 | G21: ='📊 Dashboard'!G25 -> ✓
A22: ='📊 Dashboard'!A26 | B22: ='📊 Dashboard'!B26 | C22: ='📊 Dashboard'!C26 | D22: ='📊 Dashboard'!D26 | E22: ='📊 Dashboard'!E26 | F22: ='📊 Dashboard'!F26 | G22: ='📊 Dashboard'!G26
A23: ='📊 Dashboard'!A27 | B23: ='📊 Dashboard'!B27 | C23: ='📊 Dashboard'!C27 | D23: ='📊 Dashboard'!D27 | E23: ='📊 Dashboard'!E27 | F23: ='📊 Dashboard'!F27 | G23: ='📊 Dashboard'!G27
A24: ='📊 Dashboard'!A28 | B24: ='📊 Dashboard'!B28 | C24: ='📊 Dashboard'!C28 | D24: ='📊 Dashboard'!D28 | E24: ='📊 Dashboard'!E28 | F24: ='📊 Dashboard'!F28 | G24: ='📊 Dashboard'!G28
A25: ='📊 Dashboard'!A29 | B25: ='📊 Dashboard'!B29 | C25: ='📊 Dashboard'!C29 | D25: ='📊 Dashboard'!D29 | E25: ='📊 Dashboard'!E29 | F25: ='📊 Dashboard'!F29 | G25: ='📊 Dashboard'!G29
A27: =" 🔥 ACTIVE PIPELINE ("&(COUNTIF('🔥 Pipeline'!$D$5:$D$40,"Scheduled")+COUNTIF('🔥 Pipeline'!$D$5:$D$40,"Prospect")+COUNTIF('🔥 Pipeline'!$D$5:$D$40,"Lead")+COUNTIF('🔥 Pipeline'!$D$5:$D$40,"Hold"))&" active)" -> 🔥 ACTIVE PIPELINE (12 active)
A28: # | B28: Rep | C28: Client | D28: Status | E28: LOC | F28: Fac | G28: VOB | H28: Intake | I28: Insurance | J28: Referral
A29: =IF('🔥 Pipeline'!$C5="","",'🔥 Pipeline'!A5) -> 1 | B29: =IF('🔥 Pipeline'!$C5="","",'🔥 Pipeline'!B5) -> Amy | C29: =IF('🔥 Pipeline'!$C5="","",'🔥 Pipeline'!C5) -> Christopher Knight | D29: =IF('🔥 Pipeline'!$C5="","",'🔥 Pipeline'!D5) -> Prospect | E29: =IF('🔥 Pipeline'!$C5="","",'🔥 Pipeline'!E5) -> DTX/RTC | F29: =IF('🔥 Pipeline'!$C5="","",'🔥 Pipeline'!F5) -> HP | G29: =IF('🔥 Pipeline'!$C5="","",'🔥 Pipeline'!G5) -> ✓ | H29: =IF('🔥 Pipeline'!$C5="","",'🔥 Pipeline'!H5) -> TBD | I29: =IF('🔥 Pipeline'!$C5="","",'🔥 Pipeline'!I5) -> Anthem BC | J29: =IF('🔥 Pipeline'!$C5="","",'🔥 Pipeline'!K5) -> Web
A30: =IF('🔥 Pipeline'!$C6="","",'🔥 Pipeline'!A6) -> 2 | B30: =IF('🔥 Pipeline'!$C6="","",'🔥 Pipeline'!B6) -> Amy | C30: =IF('🔥 Pipeline'!$C6="","",'🔥 Pipeline'!C6) -> Nicolas Leuvrey | D30: =IF('🔥 Pipeline'!$C6="","",'🔥 Pipeline'!D6) -> Prospect | E30: =IF('🔥 Pipeline'!$C6="","",'🔥 Pipeline'!E6) -> DTX | F30: =IF('🔥 Pipeline'!$C6="","",'🔥 Pipeline'!F6) -> HPE | G30: =IF('🔥 Pipeline'!$C6="","",'🔥 Pipeline'!G6) -> ✓ | H30: =IF('🔥 Pipeline'!$C6="","",'🔥 Pipeline'!H6) -> TBD | I30: =IF('🔥 Pipeline'!$C6="","",'🔥 Pipeline'!I6) -> Private Pay | J30: =IF('🔥 Pipeline'!$C6="","",'🔥 Pipeline'!K6) -> Alumni
A31: =IF('🔥 Pipeline'!$C7="","",'🔥 Pipeline'!A7) -> 3 | B31: =IF('🔥 Pipeline'!$C7="","",'🔥 Pipeline'!B7) -> Amy | C31: =IF('🔥 Pipeline'!$C7="","",'🔥 Pipeline'!C7) -> Tara Shinde | D31: =IF('🔥 Pipeline'!$C7="","",'🔥 Pipeline'!D7) -> Scheduled | E31: =IF('🔥 Pipeline'!$C7="","",'🔥 Pipeline'!E7) -> DTX/RTC | F31: =IF('🔥 Pipeline'!$C7="","",'🔥 Pipeline'!F7) -> HPE | G31: =IF('🔥 Pipeline'!$C7="","",'🔥 Pipeline'!G7) -> ✓ | H31: =IF('🔥 Pipeline'!$C7="","",'🔥 Pipeline'!H7) -> 46192 | I31: =IF('🔥 Pipeline'!$C7="","",'🔥 Pipeline'!I7) -> BCBS IL | J31: =IF('🔥 Pipeline'!$C7="","",'🔥 Pipeline'!K7) -> Web
A32: =IF('🔥 Pipeline'!$C8="","",'🔥 Pipeline'!A8) -> 4 | B32: =IF('🔥 Pipeline'!$C8="","",'🔥 Pipeline'!B8) -> Amy | C32: =IF('🔥 Pipeline'!$C8="","",'🔥 Pipeline'!C8) -> Kimberly Cote | D32: =IF('🔥 Pipeline'!$C8="","",'🔥 Pipeline'!D8) -> Lead | E32: =IF('🔥 Pipeline'!$C8="","",'🔥 Pipeline'!E8) -> DTX/RTC | F32: =IF('🔥 Pipeline'!$C8="","",'🔥 Pipeline'!F8) -> HP | G32: =IF('🔥 Pipeline'!$C8="","",'🔥 Pipeline'!G8) -> ✓ | H32: =IF('🔥 Pipeline'!$C8="","",'🔥 Pipeline'!H8) -> TBD | I32: =IF('🔥 Pipeline'!$C8="","",'🔥 Pipeline'!I8) -> UMR | J32: =IF('🔥 Pipeline'!$C8="","",'🔥 Pipeline'!K8) -> Web
A33: =IF('🔥 Pipeline'!$C9="","",'🔥 Pipeline'!A9) -> 5 | B33: =IF('🔥 Pipeline'!$C9="","",'🔥 Pipeline'!B9) -> Amy | C33: =IF('🔥 Pipeline'!$C9="","",'🔥 Pipeline'!C9) -> Andrew Battley | D33: =IF('🔥 Pipeline'!$C9="","",'🔥 Pipeline'!D9) -> Lead | E33: =IF('🔥 Pipeline'!$C9="","",'🔥 Pipeline'!E9) -> DTX/RTC | F33: =IF('🔥 Pipeline'!$C9="","",'🔥 Pipeline'!F9) -> HPE | G33: =IF('🔥 Pipeline'!$C9="","",'🔥 Pipeline'!G9) -> ✓ | H33: =IF('🔥 Pipeline'!$C9="","",'🔥 Pipeline'!H9) -> TBD | I33: =IF('🔥 Pipeline'!$C9="","",'🔥 Pipeline'!I9) -> Aetna | J33: =IF('🔥 Pipeline'!$C9="","",'🔥 Pipeline'!K9) -> Web
A34: =IF('🔥 Pipeline'!$C10="","",'🔥 Pipeline'!A10) -> 6 | B34: =IF('🔥 Pipeline'!$C10="","",'🔥 Pipeline'!B10) -> Nelson | C34: =IF('🔥 Pipeline'!$C10="","",'🔥 Pipeline'!C10) -> Frederic Spieser | D34: =IF('🔥 Pipeline'!$C10="","",'🔥 Pipeline'!D10) -> Lead | E34: =IF('🔥 Pipeline'!$C10="","",'🔥 Pipeline'!E10) -> DTX/RTC | F34: =IF('🔥 Pipeline'!$C10="","",'🔥 Pipeline'!F10) -> HP | G34: =IF('🔥 Pipeline'!$C10="","",'🔥 Pipeline'!G10) -> ✓ | H34: =IF('🔥 Pipeline'!$C10="","",'🔥 Pipeline'!H10) -> TBD | I34: =IF('🔥 Pipeline'!$C10="","",'🔥 Pipeline'!I10) -> UHC | J34: =IF('🔥 Pipeline'!$C10="","",'🔥 Pipeline'!K10) -> Web
A35: =IF('🔥 Pipeline'!$C11="","",'🔥 Pipeline'!A11) -> 7 | B35: =IF('🔥 Pipeline'!$C11="","",'🔥 Pipeline'!B11) -> Nelson | C35: =IF('🔥 Pipeline'!$C11="","",'🔥 Pipeline'!C11) -> Michael Cardenas | D35: =IF('🔥 Pipeline'!$C11="","",'🔥 Pipeline'!D11) -> Prospect | E35: =IF('🔥 Pipeline'!$C11="","",'🔥 Pipeline'!E11) -> DTX/RTC | F35: =IF('🔥 Pipeline'!$C11="","",'🔥 Pipeline'!F11) -> TBD | G35: =IF('🔥 Pipeline'!$C11="","",'🔥 Pipeline'!G11) -> ✓ | H35: =IF('🔥 Pipeline'!$C11="","",'🔥 Pipeline'!H11) -> TBD | I35: =IF('🔥 Pipeline'!$C11="","",'🔥 Pipeline'!I11) -> UHC | J35: =IF('🔥 Pipeline'!$C11="","",'🔥 Pipeline'!K11) -> Web
A36: =IF('🔥 Pipeline'!$C12="","",'🔥 Pipeline'!A12) -> 8 | B36: =IF('🔥 Pipeline'!$C12="","",'🔥 Pipeline'!B12) -> Nelson | C36: =IF('🔥 Pipeline'!$C12="","",'🔥 Pipeline'!C12) -> Holly Webster | D36: =IF('🔥 Pipeline'!$C12="","",'🔥 Pipeline'!D12) -> Prospect | E36: =IF('🔥 Pipeline'!$C12="","",'🔥 Pipeline'!E12) -> DTX/RTC | F36: =IF('🔥 Pipeline'!$C12="","",'🔥 Pipeline'!F12) -> TBD | G36: =IF('🔥 Pipeline'!$C12="","",'🔥 Pipeline'!G12) -> ✓ | H36: =IF('🔥 Pipeline'!$C12="","",'🔥 Pipeline'!H12) -> 46191 | I36: =IF('🔥 Pipeline'!$C12="","",'🔥 Pipeline'!I12) -> Aetna | J36: =IF('🔥 Pipeline'!$C12="","",'🔥 Pipeline'!K12) -> Web
A37: =IF('🔥 Pipeline'!$C13="","",'🔥 Pipeline'!A13) -> 9 | B37: =IF('🔥 Pipeline'!$C13="","",'🔥 Pipeline'!B13) -> Matthew | C37: =IF('🔥 Pipeline'!$C13="","",'🔥 Pipeline'!C13) -> Samuel Lieberman | D37: =IF('🔥 Pipeline'!$C13="","",'🔥 Pipeline'!D13) -> Lead | E37: =IF('🔥 Pipeline'!$C13="","",'🔥 Pipeline'!E13) -> DTX/RTC | F37: =IF('🔥 Pipeline'!$C13="","",'🔥 Pipeline'!F13) -> TBD | G37: =IF('🔥 Pipeline'!$C13="","",'🔥 Pipeline'!G13) -> ✓ | H37: =IF('🔥 Pipeline'!$C13="","",'🔥 Pipeline'!H13) -> TBD | I37: =IF('🔥 Pipeline'!$C13="","",'🔥 Pipeline'!I13) -> Aetna | J37: =IF('🔥 Pipeline'!$C13="","",'🔥 Pipeline'!K13) -> Web
A38: =IF('🔥 Pipeline'!$C14="","",'🔥 Pipeline'!A14) | B38: =IF('🔥 Pipeline'!$C14="","",'🔥 Pipeline'!B14) | C38: =IF('🔥 Pipeline'!$C14="","",'🔥 Pipeline'!C14) | D38: =IF('🔥 Pipeline'!$C14="","",'🔥 Pipeline'!D14) | E38: =IF('🔥 Pipeline'!$C14="","",'🔥 Pipeline'!E14) | F38: =IF('🔥 Pipeline'!$C14="","",'🔥 Pipeline'!F14) | G38: =IF('🔥 Pipeline'!$C14="","",'🔥 Pipeline'!G14) | H38: =IF('🔥 Pipeline'!$C14="","",'🔥 Pipeline'!H14) | I38: =IF('🔥 Pipeline'!$C14="","",'🔥 Pipeline'!I14) | J38: =IF('🔥 Pipeline'!$C14="","",'🔥 Pipeline'!K14)
A39: =IF('🔥 Pipeline'!$C15="","",'🔥 Pipeline'!A15) | B39: =IF('🔥 Pipeline'!$C15="","",'🔥 Pipeline'!B15) | C39: =IF('🔥 Pipeline'!$C15="","",'🔥 Pipeline'!C15) | D39: =IF('🔥 Pipeline'!$C15="","",'🔥 Pipeline'!D15) | E39: =IF('🔥 Pipeline'!$C15="","",'🔥 Pipeline'!E15) | F39: =IF('🔥 Pipeline'!$C15="","",'🔥 Pipeline'!F15) | G39: =IF('🔥 Pipeline'!$C15="","",'🔥 Pipeline'!G15) | H39: =IF('🔥 Pipeline'!$C15="","",'🔥 Pipeline'!H15) | I39: =IF('🔥 Pipeline'!$C15="","",'🔥 Pipeline'!I15) | J39: =IF('🔥 Pipeline'!$C15="","",'🔥 Pipeline'!K15)
A40: =IF('🔥 Pipeline'!$C16="","",'🔥 Pipeline'!A16) -> 12 | B40: =IF('🔥 Pipeline'!$C16="","",'🔥 Pipeline'!B16) -> Ahbra | C40: =IF('🔥 Pipeline'!$C16="","",'🔥 Pipeline'!C16) -> Allison Warren | D40: =IF('🔥 Pipeline'!$C16="","",'🔥 Pipeline'!D16) -> Prospect | E40: =IF('🔥 Pipeline'!$C16="","",'🔥 Pipeline'!E16) -> DTX/RTC | F40: =IF('🔥 Pipeline'!$C16="","",'🔥 Pipeline'!F16) -> HP | G40: =IF('🔥 Pipeline'!$C16="","",'🔥 Pipeline'!G16) -> ✓ | H40: =IF('🔥 Pipeline'!$C16="","",'🔥 Pipeline'!H16) -> TBD | I40: =IF('🔥 Pipeline'!$C16="","",'🔥 Pipeline'!I16) -> UHC | J40: =IF('🔥 Pipeline'!$C16="","",'🔥 Pipeline'!K16) -> Professional Referral

Sheet 📝 Roster
A1: 📝 CENSUS ROSTER — the single place you edit
A2: Add a client and pick their CURRENT BED to place them. To move someone, just change their Current Bed — the HP / HPE boards update automatically. A bed nobody is assigned to shows Open.
A3: CLIENT NAME | B3: CURRENT BED | C3: STATUS | D3: ADMIT DATE | E3: ADMIT LOC | F3: CURRENT LOC | G3: PLAN LOS | H3: FINANCIAL | I3: REFERRAL | J3: REP | K3: CHIRO Y/N | L3: AMA RISK | M3: DC LOC | N3: DC OVERRIDE | O3: DC DATE | P3: DAYS TO DC
A4: 🏠 HP — HATTERAS (23041 / 23043) | Q4: Alumni?
B5: DTX-A | O5: =IF($A5="","",IF($N5<>"",$N5,IF(AND($D5<>"",$G5<>""),$D5+$G5,""))) | P5: =IF(O5="","",O5-TODAY()) | Q5: =IF(OR($A5="",$D5=""),"",IF((COUNTIFS('📋 May 2026'!$B$5:$B$60,$A5,'📋 May 2026'!$C$5:$C$60,"<"&$D5)+COUNTIFS('📋 Jun 2026'!$B$5:$B$60,$A5,'📋 Jun 2026'!$C$5:$C$60,"<"&$D5)+COUNTIFS('📋 Jul 2026'!$B$5:$B$60,$A5,'📋 Jul 2026'!$C$5:$C$60,"<"&$D5)+COUNTIFS('📋 Aug 2026'!$B$5:$B$60,$A5,'📋 Aug 2026'!$C$5:$C$60,"<"&$D5)+COUNTIFS('📋 Sep 2026'!$B$5:$B$60,$A5,'📋 Sep 2026'!$C$5:$C$60,"<"&$D5)+COUNTIFS('📋 Oct 2026'!$B$5:$B$60,$A5,'📋 Oct 2026'!$C$5:$C$60,"<"&$D5)+COUNTIFS('📋 Nov 2026'!$B$5:$B$60,$A5,'📋 Nov 2026'!$C$5:$C$60,"<"&$D5)+COUNTIFS('📋 Dec 2026'!$B$5:$B$60,$A5,'📋 Dec 2026'!$C$5:$C$60,"<"&$D5))+(COUNTIFS('📋 May 2026'!$B$5:$B$60,$A5,'📋 May 2026'!$AB$5:$AB$60,"Alumni")+COUNTIFS('📋 Jun 2026'!$B$5:$B$60,$A5,'📋 Jun 2026'!$AB$5:$AB$60,"Alumni")+COUNTIFS('📋 Jul 2026'!$B$5:$B$60,$A5,'📋 Jul 2026'!$AB$5:$AB$60,"Alumni")+COUNTIFS('📋 Aug 2026'!$B$5:$B$60,$A5,'📋 Aug 2026'!$AB$5:$AB$60,"Alumni")+COUNTIFS('📋 Sep 2026'!$B$5:$B$60,$A5,'📋 Sep 2026'!$AB$5:$AB$60,"Alumni")+COUNTIFS('📋 Oct 2026'!$B$5:$B$60,$A5,'📋 Oct 2026'!$AB$5:$AB$60,"Alumni")+COUNTIFS('📋 Nov 2026'!$B$5:$B$60,$A5,'📋 Nov 2026'!$AB$5:$AB$60,"Alumni")+COUNTIFS('📋 Dec 2026'!$B$5:$B$60,$A5,'📋 Dec 2026'!$AB$5:$AB$60,"Alumni"))>=1,"Alumni","New"))
B6: DTX-B | O6: =IF($A6="","",IF($N6<>"",$N6,IF(AND($D6<>"",$G6<>""),$D6+$G6,""))) | P6: =IF(O6="","",O6-TODAY()) | Q6: =IF(OR($A6="",$D6=""),"",IF((COUNTIFS('📋 May 2026'!$B$5:$B$60,$A6,'📋 May 2026'!$C$5:$C$60,"<"&$D6)+COUNTIFS('📋 Jun 2026'!$B$5:$B$60,$A6,'📋 Jun 2026'!$C$5:$C$60,"<"&$D6)+COUNTIFS('📋 Jul 2026'!$B$5:$B$60,$A6,'📋 Jul 2026'!$C$5:$C$60,"<"&$D6)+COUNTIFS('📋 Aug 2026'!$B$5:$B$60,$A6,'📋 Aug 2026'!$C$5:$C$60,"<"&$D6)+COUNTIFS('📋 Sep 2026'!$B$5:$B$60,$A6,'📋 Sep 2026'!$C$5:$C$60,"<"&$D6)+COUNTIFS('📋 Oct 2026'!$B$5:$B$60,$A6,'📋 Oct 2026'!$C$5:$C$60,"<"&$D6)+COUNTIFS('📋 Nov 2026'!$B$5:$B$60,$A6,'📋 Nov 2026'!$C$5:$C$60,"<"&$D6)+COUNTIFS('📋 Dec 2026'!$B$5:$B$60,$A6,'📋 Dec 2026'!$C$5:$C$60,"<"&$D6))+(COUNTIFS('📋 May 2026'!$B$5:$B$60,$A6,'📋 May 2026'!$AB$5:$AB$60,"Alumni")+COUNTIFS('📋 Jun 2026'!$B$5:$B$60,$A6,'📋 Jun 2026'!$AB$5:$AB$60,"Alumni")+COUNTIFS('📋 Jul 2026'!$B$5:$B$60,$A6,'📋 Jul 2026'!$AB$5:$AB$60,"Alumni")+COUNTIFS('📋 Aug 2026'!$B$5:$B$60,$A6,'📋 Aug 2026'!$AB$5:$AB$60,"Alumni")+COUNTIFS('📋 Sep 2026'!$B$5:$B$60,$A6,'📋 Sep 2026'!$AB$5:$AB$60,"Alumni")+COUNTIFS('📋 Oct 2026'!$B$5:$B$60,$A6,'📋 Oct 2026'!$AB$5:$AB$60,"Alumni")+COUNTIFS('📋 Nov 2026'!$B$5:$B$60,$A6,'📋 Nov 2026'!$AB$5:$AB$60,"Alumni")+COUNTIFS('📋 Dec 2026'!$B$5:$B$60,$A6,'📋 Dec 2026'!$AB$5:$AB$60,"Alumni"))>=1,"Alumni","New"))
A7: Kurt Guisler | B7: M1-A | C7: Occupied | D7: 46172 | E7: DTX/RTC | F7: DTX/RTC | G7: 30 | H7: Blue Shield PPO | I7: Skyline/Ahbra | J7: Amy | K7: N | N7: 46201 | O7: =IF($A7="","",IF($N7<>"",$N7,IF(AND($D7<>"",$G7<>""),$D7+$G7,""))) -> 46201 | P7: =IF(O7="","",O7-TODAY()) -> 11 | Q7: =IF(OR($A7="",$D7=""),"",IF((COUNTIFS('📋 May 2026'!$B$5:$B$60,$A7,'📋 May 2026'!$C$5:$C$60,"<"&$D7)+COUNTIFS('📋 Jun 2026'!$B$5:$B$60,$A7,'📋 Jun 2026'!$C$5:$C$60,"<"&$D7)+COUNTIFS('📋 Jul 2026'!$B$5:$B$60,$A7,'📋 Jul 2026'!$C$5:$C$60,"<"&$D7)+COUNTIFS('📋 Aug 2026'!$B$5:$B$60,$A7,'📋 Aug 2026'!$C$5:$C$60,"<"&$D7)+COUNTIFS('📋 Sep 2026'!$B$5:$B$60,$A7,'📋 Sep 2026'!$C$5:$C$60,"<"&$D7)+COUNTIFS('📋 Oct 2026'!$B$5:$B$60,$A7,'📋 Oct 2026'!$C$5:$C$60,"<"&$D7)+COUNTIFS('📋 Nov 2026'!$B$5:$B$60,$A7,'📋 Nov 2026'!$C$5:$C$60,"<"&$D7)+COUNTIFS('📋 Dec 2026'!$B$5:$B$60,$A7,'📋 Dec 2026'!$C$5:$C$60,"<"&$D7))+(COUNTIFS('📋 May 2026'!$B$5:$B$60,$A7,'📋 May 2026'!$AB$5:$AB$60,"Alumni")+COUNTIFS('📋 Jun 2026'!$B$5:$B$60,$A7,'📋 Jun 2026'!$AB$5:$AB$60,"Alumni")+COUNTIFS('📋 Jul 2026'!$B$5:$B$60,$A7,'📋 Jul 2026'!$AB$5:$AB$60,"Alumni")+COUNTIFS('📋 Aug 2026'!$B$5:$B$60,$A7,'📋 Aug 2026'!$AB$5:$AB$60,"Alumni")+COUNTIFS('📋 Sep 2026'!$B$5:$B$60,$A7,'📋 Sep 2026'!$AB$5:$AB$60,"Alumni")+COUNTIFS('📋 Oct 2026'!$B$5:$B$60,$A7,'📋 Oct 2026'!$AB$5:$AB$60,"Alumni")+COUNTIFS('📋 Nov 2026'!$B$5:$B$60,$A7,'📋 Nov 2026'!$AB$5:$AB$60,"Alumni")+COUNTIFS('📋 Dec 2026'!$B$5:$B$60,$A7,'📋 Dec 2026'!$AB$5:$AB$60,"Alumni"))>=1,"Alumni","New")) -> New
A8: Pedro Mendoza | B8: M1-B | C8: Occupied | D8: 46176 | E8: DTX/RTC | F8: DTX/RTC | G8: 30 | H8: Blue Shield CA | I8: Readmit | J8: Matthew | K8: N | N8: 46205 | O8: =IF($A8="","",IF($N8<>"",$N8,IF(AND($D8<>"",$G8<>""),$D8+$G8,""))) -> 46205 | P8: =IF(O8="","",O8-TODAY()) -> 15 | Q8: =IF(OR($A8="",$D8=""),"",IF((COUNTIFS('📋 May 2026'!$B$5:$B$60,$A8,'📋 May 2026'!$C$5:$C$60,"<"&$D8)+COUNTIFS('📋 Jun 2026'!$B$5:$B$60,$A8,'📋 Jun 2026'!$C$5:$C$60,"<"&$D8)+COUNTIFS('📋 Jul 2026'!$B$5:$B$60,$A8,'📋 Jul 2026'!$C$5:$C$60,"<"&$D8)+COUNTIFS('📋 Aug 2026'!$B$5:$B$60,$A8,'📋 Aug 2026'!$C$5:$C$60,"<"&$D8)+COUNTIFS('📋 Sep 2026'!$B$5:$B$60,$A8,'📋 Sep 2026'!$C$5:$C$60,"<"&$D8)+COUNTIFS('📋 Oct 2026'!$B$5:$B$60,$A8,'📋 Oct 2026'!$C$5:$C$60,"<"&$D8)+COUNTIFS('📋 Nov 2026'!$B$5:$B$60,$A8,'📋 Nov 2026'!$C$5:$C$60,"<"&$D8)+COUNTIFS('📋 Dec 2026'!$B$5:$B$60,$A8,'📋 Dec 2026'!$C$5:$C$60,"<"&$D8))+(COUNTIFS('📋 May 2026'!$B$5:$B$60,$A8,'📋 May 2026'!$AB$5:$AB$60,"Alumni")+COUNTIFS('📋 Jun 2026'!$B$5:$B$60,$A8,'📋 Jun 2026'!$AB$5:$AB$60,"Alumni")+COUNTIFS('📋 Jul 2026'!$B$5:$B$60,$A8,'📋 Jul 2026'!$AB$5:$AB$60,"Alumni")+COUNTIFS('📋 Aug 2026'!$B$5:$B$60,$A8,'📋 Aug 2026'!$AB$5:$AB$60,"Alumni")+COUNTIFS('📋 Sep 2026'!$B$5:$B$60,$A8,'📋 Sep 2026'!$AB$5:$AB$60,"Alumni")+COUNTIFS('📋 Oct 2026'!$B$5:$B$60,$A8,'📋 Oct 2026'!$AB$5:$AB$60,"Alumni")+COUNTIFS('📋 Nov 2026'!$B$5:$B$60,$A8,'📋 Nov 2026'!$AB$5:$AB$60,"Alumni")+COUNTIFS('📋 Dec 2026'!$B$5:$B$60,$A8,'📋 Dec 2026'!$AB$5:$AB$60,"Alumni"))>=1,"Alumni","New")) -> Alumni
B9: M2-A | O9: =IF($A9="","",IF($N9<>"",$N9,IF(AND($D9<>"",$G9<>""),$D9+$G9,""))) | P9: =IF(O9="","",O9-TODAY()) | Q9: =IF(OR($A9="",$D9=""),"",IF((COUNTIFS('📋 May 2026'!$B$5:$B$60,$A9,'📋 May 2026'!$C$5:$C$60,"<"&$D9)+COUNTIFS('📋 Jun 2026'!$B$5:$B$60,$A9,'📋 Jun 2026'!$C$5:$C$60,"<"&$D9)+COUNTIFS('📋 Jul 2026'!$B$5:$B$60,$A9,'📋 Jul 2026'!$C$5:$C$60,"<"&$D9)+COUNTIFS('📋 Aug 2026'!$B$5:$B$60,$A9,'📋 Aug 2026'!$C$5:$C$60,"<"&$D9)+COUNTIFS('📋 Sep 2026'!$B$5:$B$60,$A9,'📋 Sep 2026'!$C$5:$C$60,"<"&$D9)+COUNTIFS('📋 Oct 2026'!$B$5:$B$60,$A9,'📋 Oct 2026'!$C$5:$C$60,"<"&$D9)+COUNTIFS('📋 Nov 2026'!$B$5:$B$60,$A9,'📋 Nov 2026'!$C$5:$C$60,"<"&$D9)+COUNTIFS('📋 Dec 2026'!$B$5:$B$60,$A9,'📋 Dec 2026'!$C$5:$C$60,"<"&$D9))+(COUNTIFS('📋 May 2026'!$B$5:$B$60,$A9,'📋 May 2026'!$AB$5:$AB$60,"Alumni")+COUNTIFS('📋 Jun 2026'!$B$5:$B$60,$A9,'📋 Jun 2026'!$AB$5:$AB$60,"Alumni")+COUNTIFS('📋 Jul 2026'!$B$5:$B$60,$A9,'📋 Jul 2026'!$AB$5:$AB$60,"Alumni")+COUNTIFS('📋 Aug 2026'!$B$5:$B$60,$A9,'📋 Aug 2026'!$AB$5:$AB$60,"Alumni")+COUNTIFS('📋 Sep 2026'!$B$5:$B$60,$A9,'📋 Sep 2026'!$AB$5:$AB$60,"Alumni")+COUNTIFS('📋 Oct 2026'!$B$5:$B$60,$A9,'📋 Oct 2026'!$AB$5:$AB$60,"Alumni")+COUNTIFS('📋 Nov 2026'!$B$5:$B$60,$A9,'📋 Nov 2026'!$AB$5:$AB$60,"Alumni")+COUNTIFS('📋 Dec 2026'!$B$5:$B$60,$A9,'📋 Dec 2026'!$AB$5:$AB$60,"Alumni"))>=1,"Alumni","New"))
A10: Darian Loehner | B10: M2-B | C10: Occupied | D10: 46183 | E10: DTX | F10: DTX | G10: 10 | H10: Aetna | I10: Readmit | J10: Amy | K10: Y | O10: =IF($A10="","",IF($N10<>"",$N10,IF(AND($D10<>"",$G10<>""),$D10+$G10,""))) -> 46193 | P10: =IF(O10="","",O10-TODAY()) -> 3 | Q10: =IF(OR($A10="",$D10=""),"",IF((COUNTIFS('📋 May 2026'!$B$5:$B$60,$A10,'📋 May 2026'!$C$5:$C$60,"<"&$D10)+COUNTIFS('📋 Jun 2026'!$B$5:$B$60,$A10,'📋 Jun 2026'!$C$5:$C$60,"<"&$D10)+COUNTIFS('📋 Jul 2026'!$B$5:$B$60,$A10,'📋 Jul 2026'!$C$5:$C$60,"<"&$D10)+COUNTIFS('📋 Aug 2026'!$B$5:$B$60,$A10,'📋 Aug 2026'!$C$5:$C$60,"<"&$D10)+COUNTIFS('📋 Sep 2026'!$B$5:$B$60,$A10,'📋 Sep 2026'!$C$5:$C$60,"<"&$D10)+COUNTIFS('📋 Oct 2026'!$B$5:$B$60,$A10,'📋 Oct 2026'!$C$5:$C$60,"<"&$D10)+COUNTIFS('📋 Nov 2026'!$B$5:$B$60,$A10,'📋 Nov 2026'!$C$5:$C$60,"<"&$D10)+COUNTIFS('📋 Dec 2026'!$B$5:$B$60,$A10,'📋 Dec 2026'!$C$5:$C$60,"<"&$D10))+(COUNTIFS('📋 May 2026'!$B$5:$B$60,$A10,'📋 May 2026'!$AB$5:$AB$60,"Alumni")+COUNTIFS('📋 Jun 2026'!$B$5:$B$60,$A10,'📋 Jun 2026'!$AB$5:$AB$60,"Alumni")+COUNTIFS('📋 Jul 2026'!$B$5:$B$60,$A10,'📋 Jul 2026'!$AB$5:$AB$60,"Alumni")+COUNTIFS('📋 Aug 2026'!$B$5:$B$60,$A10,'📋 Aug 2026'!$AB$5:$AB$60,"Alumni")+COUNTIFS('📋 Sep 2026'!$B$5:$B$60,$A10,'📋 Sep 2026'!$AB$5:$AB$60,"Alumni")+COUNTIFS('📋 Oct 2026'!$B$5:$B$60,$A10,'📋 Oct 2026'!$AB$5:$AB$60,"Alumni")+COUNTIFS('📋 Nov 2026'!$B$5:$B$60,$A10,'📋 Nov 2026'!$AB$5:$AB$60,"Alumni")+COUNTIFS('📋 Dec 2026'!$B$5:$B$60,$A10,'📋 Dec 2026'!$AB$5:$AB$60,"Alumni"))>=1,"Alumni","New")) -> Alumni
A11: Jill Labate | B11: M3-A | C11: Occupied | D11: 46187 | E11: DTX/RTC | F11: DTX/RTC | G11: 21 | H11: Cigna/Evernorth | I11: Readmit/Rise | J11: Matthew | O11: =IF($A11="","",IF($N11<>"",$N11,IF(AND($D11<>"",$G11<>""),$D11+$G11,""))) -> 46208 | P11: =IF(O11="","",O11-TODAY()) -> 18 | Q11: =IF(OR($A11="",$D11=""),"",IF((COUNTIFS('📋 May 2026'!$B$5:$B$60,$A11,'📋 May 2026'!$C$5:$C$60,"<"&$D11)+COUNTIFS('📋 Jun 2026'!$B$5:$B$60,$A11,'📋 Jun 2026'!$C$5:$C$60,"<"&$D11)+COUNTIFS('📋 Jul 2026'!$B$5:$B$60,$A11,'📋 Jul 2026'!$C$5:$C$60,"<"&$D11)+COUNTIFS('📋 Aug 2026'!$B$5:$B$60,$A11,'📋 Aug 2026'!$C$5:$C$60,"<"&$D11)+COUNTIFS('📋 Sep 2026'!$B$5:$B$60,$A11,'📋 Sep 2026'!$C$5:$C$60,"<"&$D11)+COUNTIFS('📋 Oct 2026'!$B$5:$B$60,$A11,'📋 Oct 2026'!$C$5:$C$60,"<"&$D11)+COUNTIFS('📋 Nov 2026'!$B$5:$B$60,$A11,'📋 Nov 2026'!$C$5:$C$60,"<"&$D11)+COUNTIFS('📋 Dec 2026'!$B$5:$B$60,$A11,'📋 Dec 2026'!$C$5:$C$60,"<"&$D11))+(COUNTIFS('📋 May 2026'!$B$5:$B$60,$A11,'📋 May 2026'!$AB$5:$AB$60,"Alumni")+COUNTIFS('📋 Jun 2026'!$B$5:$B$60,$A11,'📋 Jun 2026'!$AB$5:$AB$60,"Alumni")+COUNTIFS('📋 Jul 2026'!$B$5:$B$60,$A11,'📋 Jul 2026'!$AB$5:$AB$60,"Alumni")+COUNTIFS('📋 Aug 2026'!$B$5:$B$60,$A11,'📋 Aug 2026'!$AB$5:$AB$60,"Alumni")+COUNTIFS('📋 Sep 2026'!$B$5:$B$60,$A11,'📋 Sep 2026'!$AB$5:$AB$60,"Alumni")+COUNTIFS('📋 Oct 2026'!$B$5:$B$60,$A11,'📋 Oct 2026'!$AB$5:$AB$60,"Alumni")+COUNTIFS('📋 Nov 2026'!$B$5:$B$60,$A11,'📋 Nov 2026'!$AB$5:$AB$60,"Alumni")+COUNTIFS('📋 Dec 2026'!$B$5:$B$60,$A11,'📋 Dec 2026'!$AB$5:$AB$60,"Alumni"))>=1,"Alumni","New")) -> Alumni
A12: Monica Gamboa | B12: M3-B | C12: Occupied | D12: 46184 | E12: DTX/RTC | F12: DTX/RTC | G12: 10 | H12: Molina CA | I12: Readmit | J12: Amy | K12: N | N12: 46194 | O12: =IF($A12="","",IF($N12<>"",$N12,IF(AND($D12<>"",$G12<>""),$D12+$G12,""))) -> 46194 | P12: =IF(O12="","",O12-TODAY()) -> 4 | Q12: =IF(OR($A12="",$D12=""),"",IF((COUNTIFS('📋 May 2026'!$B$5:$B$60,$A12,'📋 May 2026'!$C$5:$C$60,"<"&$D12)+COUNTIFS('📋 Jun 2026'!$B$5:$B$60,$A12,'📋 Jun 2026'!$C$5:$C$60,"<"&$D12)+COUNTIFS('📋 Jul 2026'!$B$5:$B$60,$A12,'📋 Jul 2026'!$C$5:$C$60,"<"&$D12)+COUNTIFS('📋 Aug 2026'!$B$5:$B$60,$A12,'📋 Aug 2026'!$C$5:$C$60,"<"&$D12)+COUNTIFS('📋 Sep 2026'!$B$5:$B$60,$A12,'📋 Sep 2026'!$C$5:$C$60,"<"&$D12)+COUNTIFS('📋 Oct 2026'!$B$5:$B$60,$A12,'📋 Oct 2026'!$C$5:$C$60,"<"&$D12)+COUNTIFS('📋 Nov 2026'!$B$5:$B$60,$A12,'📋 Nov 2026'!$C$5:$C$60,"<"&$D12)+COUNTIFS('📋 Dec 2026'!$B$5:$B$60,$A12,'📋 Dec 2026'!$C$5:$C$60,"<"&$D12))+(COUNTIFS('📋 May 2026'!$B$5:$B$60,$A12,'📋 May 2026'!$AB$5:$AB$60,"Alumni")+COUNTIFS('📋 Jun 2026'!$B$5:$B$60,$A12,'📋 Jun 2026'!$AB$5:$AB$60,"Alumni")+COUNTIFS('📋 Jul 2026'!$B$5:$B$60,$A12,'📋 Jul 2026'!$AB$5:$AB$60,"Alumni")+COUNTIFS('📋 Aug 2026'!$B$5:$B$60,$A12,'📋 Aug 2026'!$AB$5:$AB$60,"Alumni")+COUNTIFS('📋 Sep 2026'!$B$5:$B$60,$A12,'📋 Sep 2026'!$AB$5:$AB$60,"Alumni")+COUNTIFS('📋 Oct 2026'!$B$5:$B$60,$A12,'📋 Oct 2026'!$AB$5:$AB$60,"Alumni")+COUNTIFS('📋 Nov 2026'!$B$5:$B$60,$A12,'📋 Nov 2026'!$AB$5:$AB$60,"Alumni")+COUNTIFS('📋 Dec 2026'!$B$5:$B$60,$A12,'📋 Dec 2026'!$AB$5:$AB$60,"Alumni"))>=1,"Alumni","New")) -> Alumni
A13: Bradey Bauer | B13: B1-A | C13: Occupied | D13: 46186 | E13: DTX/RTC | F13: DTX/RTC | G13: 30 | H13: Anthem BC | O13: =IF($A13="","",IF($N13<>"",$N13,IF(AND($D13<>"",$G13<>""),$D13+$G13,""))) -> 46216 | P13: =IF(O13="","",O13-TODAY()) -> 26 | Q13: =IF(OR($A13="",$D13=""),"",IF((COUNTIFS('📋 May 2026'!$B$5:$B$60,$A13,'📋 May 2026'!$C$5:$C$60,"<"&$D13)+COUNTIFS('📋 Jun 2026'!$B$5:$B$60,$A13,'📋 Jun 2026'!$C$5:$C$60,"<"&$D13)+COUNTIFS('📋 Jul 2026'!$B$5:$B$60,$A13,'📋 Jul 2026'!$C$5:$C$60,"<"&$D13)+COUNTIFS('📋 Aug 2026'!$B$5:$B$60,$A13,'📋 Aug 2026'!$C$5:$C$60,"<"&$D13)+COUNTIFS('📋 Sep 2026'!$B$5:$B$60,$A13,'📋 Sep 2026'!$C$5:$C$60,"<"&$D13)+COUNTIFS('📋 Oct 2026'!$B$5:$B$60,$A13,'📋 Oct 2026'!$C$5:$C$60,"<"&$D13)+COUNTIFS('📋 Nov 2026'!$B$5:$B$60,$A13,'📋 Nov 2026'!$C$5:$C$60,"<"&$D13)+COUNTIFS('📋 Dec 2026'!$B$5:$B$60,$A13,'📋 Dec 2026'!$C$5:$C$60,"<"&$D13))+(COUNTIFS('📋 May 2026'!$B$5:$B$60,$A13,'📋 May 2026'!$AB$5:$AB$60,"Alumni")+COUNTIFS('📋 Jun 2026'!$B$5:$B$60,$A13,'📋 Jun 2026'!$AB$5:$AB$60,"Alumni")+COUNTIFS('📋 Jul 2026'!$B$5:$B$60,$A13,'📋 Jul 2026'!$AB$5:$AB$60,"Alumni")+COUNTIFS('📋 Aug 2026'!$B$5:$B$60,$A13,'📋 Aug 2026'!$AB$5:$AB$60,"Alumni")+COUNTIFS('📋 Sep 2026'!$B$5:$B$60,$A13,'📋 Sep 2026'!$AB$5:$AB$60,"Alumni")+COUNTIFS('📋 Oct 2026'!$B$5:$B$60,$A13,'📋 Oct 2026'!$AB$5:$AB$60,"Alumni")+COUNTIFS('📋 Nov 2026'!$B$5:$B$60,$A13,'📋 Nov 2026'!$AB$5:$AB$60,"Alumni")+COUNTIFS('📋 Dec 2026'!$B$5:$B$60,$A13,'📋 Dec 2026'!$AB$5:$AB$60,"Alumni"))>=1,"Alumni","New")) -> Alumni
A14: Garrett Johnson | B14: B1-B | C14: Occupied | D14: 46186 | E14: RTC | F14: RTC | G14: 30 | H14: UHC | I14: web | J14: Nelson | K14: Y | O14: =IF($A14="","",IF($N14<>"",$N14,IF(AND($D14<>"",$G14<>""),$D14+$G14,""))) -> 46216 | P14: =IF(O14="","",O14-TODAY()) -> 26 | Q14: =IF(OR($A14="",$D14=""),"",IF((COUNTIFS('📋 May 2026'!$B$5:$B$60,$A14,'📋 May 2026'!$C$5:$C$60,"<"&$D14)+COUNTIFS('📋 Jun 2026'!$B$5:$B$60,$A14,'📋 Jun 2026'!$C$5:$C$60,"<"&$D14)+COUNTIFS('📋 Jul 2026'!$B$5:$B$60,$A14,'📋 Jul 2026'!$C$5:$C$60,"<"&$D14)+COUNTIFS('📋 Aug 2026'!$B$5:$B$60,$A14,'📋 Aug 2026'!$C$5:$C$60,"<"&$D14)+COUNTIFS('📋 Sep 2026'!$B$5:$B$60,$A14,'📋 Sep 2026'!$C$5:$C$60,"<"&$D14)+COUNTIFS('📋 Oct 2026'!$B$5:$B$60,$A14,'📋 Oct 2026'!$C$5:$C$60,"<"&$D14)+COUNTIFS('📋 Nov 2026'!$B$5:$B$60,$A14,'📋 Nov 2026'!$C$5:$C$60,"<"&$D14)+COUNTIFS('📋 Dec 2026'!$B$5:$B$60,$A14,'📋 Dec 2026'!$C$5:$C$60,"<"&$D14))+(COUNTIFS('📋 May 2026'!$B$5:$B$60,$A14,'📋 May 2026'!$AB$5:$AB$60,"Alumni")+COUNTIFS('📋 Jun 2026'!$B$5:$B$60,$A14,'📋 Jun 2026'!$AB$5:$AB$60,"Alumni")+COUNTIFS('📋 Jul 2026'!$B$5:$B$60,$A14,'📋 Jul 2026'!$AB$5:$AB$60,"Alumni")+COUNTIFS('📋 Aug 2026'!$B$5:$B$60,$A14,'📋 Aug 2026'!$AB$5:$AB$60,"Alumni")+COUNTIFS('📋 Sep 2026'!$B$5:$B$60,$A14,'📋 Sep 2026'!$AB$5:$AB$60,"Alumni")+COUNTIFS('📋 Oct 2026'!$B$5:$B$60,$A14,'📋 Oct 2026'!$AB$5:$AB$60,"Alumni")+COUNTIFS('📋 Nov 2026'!$B$5:$B$60,$A14,'📋 Nov 2026'!$AB$5:$AB$60,"Alumni")+COUNTIFS('📋 Dec 2026'!$B$5:$B$60,$A14,'📋 Dec 2026'!$AB$5:$AB$60,"Alumni"))>=1,"Alumni","New")) -> New
A15: Kyle Samia | B15: B2-A | C15: Occupied | D15: 46184 | E15: DTX/RTC | F15: DTX/RTC | G15: 30 | H15: Cigna/Evernorth | I15: web | J15: Matthew | O15: =IF($A15="","",IF($N15<>"",$N15,IF(AND($D15<>"",$G15<>""),$D15+$G15,""))) -> 46214 | P15: =IF(O15="","",O15-TODAY()) -> 24 | Q15: =IF(OR($A15="",$D15=""),"",IF((COUNTIFS('📋 May 2026'!$B$5:$B$60,$A15,'📋 May 2026'!$C$5:$C$60,"<"&$D15)+COUNTIFS('📋 Jun 2026'!$B$5:$B$60,$A15,'📋 Jun 2026'!$C$5:$C$60,"<"&$D15)+COUNTIFS('📋 Jul 2026'!$B$5:$B$60,$A15,'📋 Jul 2026'!$C$5:$C$60,"<"&$D15)+COUNTIFS('📋 Aug 2026'!$B$5:$B$60,$A15,'📋 Aug 2026'!$C$5:$C$60,"<"&$D15)+COUNTIFS('📋 Sep 2026'!$B$5:$B$60,$A15,'📋 Sep 2026'!$C$5:$C$60,"<"&$D15)+COUNTIFS('📋 Oct 2026'!$B$5:$B$60,$A15,'📋 Oct 2026'!$C$5:$C$60,"<"&$D15)+COUNTIFS('📋 Nov 2026'!$B$5:$B$60,$A15,'📋 Nov 2026'!$C$5:$C$60,"<"&$D15)+COUNTIFS('📋 Dec 2026'!$B$5:$B$60,$A15,'📋 Dec 2026'!$C$5:$C$60,"<"&$D15))+(COUNTIFS('📋 May 2026'!$B$5:$B$60,$A15,'📋 May 2026'!$AB$5:$AB$60,"Alumni")+COUNTIFS('📋 Jun 2026'!$B$5:$B$60,$A15,'📋 Jun 2026'!$AB$5:$AB$60,"Alumni")+COUNTIFS('📋 Jul 2026'!$B$5:$B$60,$A15,'📋 Jul 2026'!$AB$5:$AB$60,"Alumni")+COUNTIFS('📋 Aug 2026'!$B$5:$B$60,$A15,'📋 Aug 2026'!$AB$5:$AB$60,"Alumni")+COUNTIFS('📋 Sep 2026'!$B$5:$B$60,$A15,'📋 Sep 2026'!$AB$5:$AB$60,"Alumni")+COUNTIFS('📋 Oct 2026'!$B$5:$B$60,$A15,'📋 Oct 2026'!$AB$5:$AB$60,"Alumni")+COUNTIFS('📋 Nov 2026'!$B$5:$B$60,$A15,'📋 Nov 2026'!$AB$5:$AB$60,"Alumni")+COUNTIFS('📋 Dec 2026'!$B$5:$B$60,$A15,'📋 Dec 2026'!$AB$5:$AB$60,"Alumni"))>=1,"Alumni","New")) -> New
A16: Jamal Williams | B16: B2-B | C16: Occupied | D16: 46183 | E16: DTX/RTC | F16: DTX/RTC | G16: 30 | H16: Blue Shield CA | I16: The Canyon | J16: Ahbra | O16: =IF($A16="","",IF($N16<>"",$N16,IF(AND($D16<>"",$G16<>""),$D16+$G16,""))) -> 46213 | P16: =IF(O16="","",O16-TODAY()) -> 23 | Q16: =IF(OR($A16="",$D16=""),"",IF((COUNTIFS('📋 May 2026'!$B$5:$B$60,$A16,'📋 May 2026'!$C$5:$C$60,"<"&$D16)+COUNTIFS('📋 Jun 2026'!$B$5:$B$60,$A16,'📋 Jun 2026'!$C$5:$C$60,"<"&$D16)+COUNTIFS('📋 Jul 2026'!$B$5:$B$60,$A16,'📋 Jul 2026'!$C$5:$C$60,"<"&$D16)+COUNTIFS('📋 Aug 2026'!$B$5:$B$60,$A16,'📋 Aug 2026'!$C$5:$C$60,"<"&$D16)+COUNTIFS('📋 Sep 2026'!$B$5:$B$60,$A16,'📋 Sep 2026'!$C$5:$C$60,"<"&$D16)+COUNTIFS('📋 Oct 2026'!$B$5:$B$60,$A16,'📋 Oct 2026'!$C$5:$C$60,"<"&$D16)+COUNTIFS('📋 Nov 2026'!$B$5:$B$60,$A16,'📋 Nov 2026'!$C$5:$C$60,"<"&$D16)+COUNTIFS('📋 Dec 2026'!$B$5:$B$60,$A16,'📋 Dec 2026'!$C$5:$C$60,"<"&$D16))+(COUNTIFS('📋 May 2026'!$B$5:$B$60,$A16,'📋 May 2026'!$AB$5:$AB$60,"Alumni")+COUNTIFS('📋 Jun 2026'!$B$5:$B$60,$A16,'📋 Jun 2026'!$AB$5:$AB$60,"Alumni")+COUNTIFS('📋 Jul 2026'!$B$5:$B$60,$A16,'📋 Jul 2026'!$AB$5:$AB$60,"Alumni")+COUNTIFS('📋 Aug 2026'!$B$5:$B$60,$A16,'📋 Aug 2026'!$AB$5:$AB$60,"Alumni")+COUNTIFS('📋 Sep 2026'!$B$5:$B$60,$A16,'📋 Sep 2026'!$AB$5:$AB$60,"Alumni")+COUNTIFS('📋 Oct 2026'!$B$5:$B$60,$A16,'📋 Oct 2026'!$AB$5:$AB$60,"Alumni")+COUNTIFS('📋 Nov 2026'!$B$5:$B$60,$A16,'📋 Nov 2026'!$AB$5:$AB$60,"Alumni")+COUNTIFS('📋 Dec 2026'!$B$5:$B$60,$A16,'📋 Dec 2026'!$AB$5:$AB$60,"Alumni"))>=1,"Alumni","New")) -> New
A17: Christopher Avolio | B17: B3-A | C17: Occupied | D17: 46169 | E17: DTX/RTC | F17: DTX/RTC | G17: 30 | H17: Blue Shield PPO | I17: Montare | J17: Amy | K17: N | N17: 46205 | O17: =IF($A17="","",IF($N17<>"",$N17,IF(AND($D17<>"",$G17<>""),$D17+$G17,""))) -> 46205 | P17: =IF(O17="","",O17-TODAY()) -> 15 | Q17: =IF(OR($A17="",$D17=""),"",IF((COUNTIFS('📋 May 2026'!$B$5:$B$60,$A17,'📋 May 2026'!$C$5:$C$60,"<"&$D17)+COUNTIFS('📋 Jun 2026'!$B$5:$B$60,$A17,'📋 Jun 2026'!$C$5:$C$60,"<"&$D17)+COUNTIFS('📋 Jul 2026'!$B$5:$B$60,$A17,'📋 Jul 2026'!$C$5:$C$60,"<"&$D17)+COUNTIFS('📋 Aug 2026'!$B$5:$B$60,$A17,'📋 Aug 2026'!$C$5:$C$60,"<"&$D17)+COUNTIFS('📋 Sep 2026'!$B$5:$B$60,$A17,'📋 Sep 2026'!$C$5:$C$60,"<"&$D17)+COUNTIFS('📋 Oct 2026'!$B$5:$B$60,$A17,'📋 Oct 2026'!$C$5:$C$60,"<"&$D17)+COUNTIFS('📋 Nov 2026'!$B$5:$B$60,$A17,'📋 Nov 2026'!$C$5:$C$60,"<"&$D17)+COUNTIFS('📋 Dec 2026'!$B$5:$B$60,$A17,'📋 Dec 2026'!$C$5:$C$60,"<"&$D17))+(COUNTIFS('📋 May 2026'!$B$5:$B$60,$A17,'📋 May 2026'!$AB$5:$AB$60,"Alumni")+COUNTIFS('📋 Jun 2026'!$B$5:$B$60,$A17,'📋 Jun 2026'!$AB$5:$AB$60,"Alumni")+COUNTIFS('📋 Jul 2026'!$B$5:$B$60,$A17,'📋 Jul 2026'!$AB$5:$AB$60,"Alumni")+COUNTIFS('📋 Aug 2026'!$B$5:$B$60,$A17,'📋 Aug 2026'!$AB$5:$AB$60,"Alumni")+COUNTIFS('📋 Sep 2026'!$B$5:$B$60,$A17,'📋 Sep 2026'!$AB$5:$AB$60,"Alumni")+COUNTIFS('📋 Oct 2026'!$B$5:$B$60,$A17,'📋 Oct 2026'!$AB$5:$AB$60,"Alumni")+COUNTIFS('📋 Nov 2026'!$B$5:$B$60,$A17,'📋 Nov 2026'!$AB$5:$AB$60,"Alumni")+COUNTIFS('📋 Dec 2026'!$B$5:$B$60,$A17,'📋 Dec 2026'!$AB$5:$AB$60,"Alumni"))>=1,"Alumni","New")) -> New
A18: Jason Schnell | B18: B3-B | C18: Occupied | D18: 46164 | E18: DTX/RTC | F18: DTX/RTC | G18: 30 | H18: Blue Shield CA | I18: Readmit | J18: Amy | K18: N | N18: 46203 | O18: =IF($A18="","",IF($N18<>"",$N18,IF(AND($D18<>"",$G18<>""),$D18+$G18,""))) -> 46203 | P18: =IF(O18="","",O18-TODAY()) -> 13 | Q18: =IF(OR($A18="",$D18=""),"",IF((COUNTIFS('📋 May 2026'!$B$5:$B$60,$A18,'📋 May 2026'!$C$5:$C$60,"<"&$D18)+COUNTIFS('📋 Jun 2026'!$B$5:$B$60,$A18,'📋 Jun 2026'!$C$5:$C$60,"<"&$D18)+COUNTIFS('📋 Jul 2026'!$B$5:$B$60,$A18,'📋 Jul 2026'!$C$5:$C$60,"<"&$D18)+COUNTIFS('📋 Aug 2026'!$B$5:$B$60,$A18,'📋 Aug 2026'!$C$5:$C$60,"<"&$D18)+COUNTIFS('📋 Sep 2026'!$B$5:$B$60,$A18,'📋 Sep 2026'!$C$5:$C$60,"<"&$D18)+COUNTIFS('📋 Oct 2026'!$B$5:$B$60,$A18,'📋 Oct 2026'!$C$5:$C$60,"<"&$D18)+COUNTIFS('📋 Nov 2026'!$B$5:$B$60,$A18,'📋 Nov 2026'!$C$5:$C$60,"<"&$D18)+COUNTIFS('📋 Dec 2026'!$B$5:$B$60,$A18,'📋 Dec 2026'!$C$5:$C$60,"<"&$D18))+(COUNTIFS('📋 May 2026'!$B$5:$B$60,$A18,'📋 May 2026'!$AB$5:$AB$60,"Alumni")+COUNTIFS('📋 Jun 2026'!$B$5:$B$60,$A18,'📋 Jun 2026'!$AB$5:$AB$60,"Alumni")+COUNTIFS('📋 Jul 2026'!$B$5:$B$60,$A18,'📋 Jul 2026'!$AB$5:$AB$60,"Alumni")+COUNTIFS('📋 Aug 2026'!$B$5:$B$60,$A18,'📋 Aug 2026'!$AB$5:$AB$60,"Alumni")+COUNTIFS('📋 Sep 2026'!$B$5:$B$60,$A18,'📋 Sep 2026'!$AB$5:$AB$60,"Alumni")+COUNTIFS('📋 Oct 2026'!$B$5:$B$60,$A18,'📋 Oct 2026'!$AB$5:$AB$60,"Alumni")+COUNTIFS('📋 Nov 2026'!$B$5:$B$60,$A18,'📋 Nov 2026'!$AB$5:$AB$60,"Alumni")+COUNTIFS('📋 Dec 2026'!$B$5:$B$60,$A18,'📋 Dec 2026'!$AB$5:$AB$60,"Alumni"))>=1,"Alumni","New")) -> Alumni
A20: 🏢 HPE — BURBANK · HOUSE 1 (22913)
A21: Allisa Leuvrey | B21: H1-1A | C21: Occupied | D21: 46185 | E21: DTX | F21: DTX | G21: 7 | H21: Blue Shield CA | I21: web | J21: Amy | K21: N | O21: =IF($A21="","",IF($N21<>"",$N21,IF(AND($D21<>"",$G21<>""),$D21+$G21,""))) -> 46192 | P21: =IF(O21="","",O21-TODAY()) -> 2 | Q21: =IF(OR($A21="",$D21=""),"",IF((COUNTIFS('📋 May 2026'!$B$5:$B$60,$A21,'📋 May 2026'!$C$5:$C$60,"<"&$D21)+COUNTIFS('📋 Jun 2026'!$B$5:$B$60,$A21,'📋 Jun 2026'!$C$5:$C$60,"<"&$D21)+COUNTIFS('📋 Jul 2026'!$B$5:$B$60,$A21,'📋 Jul 2026'!$C$5:$C$60,"<"&$D21)+COUNTIFS('📋 Aug 2026'!$B$5:$B$60,$A21,'📋 Aug 2026'!$C$5:$C$60,"<"&$D21)+COUNTIFS('📋 Sep 2026'!$B$5:$B$60,$A21,'📋 Sep 2026'!$C$5:$C$60,"<"&$D21)+COUNTIFS('📋 Oct 2026'!$B$5:$B$60,$A21,'📋 Oct 2026'!$C$5:$C$60,"<"&$D21)+COUNTIFS('📋 Nov 2026'!$B$5:$B$60,$A21,'📋 Nov 2026'!$C$5:$C$60,"<"&$D21)+COUNTIFS('📋 Dec 2026'!$B$5:$B$60,$A21,'📋 Dec 2026'!$C$5:$C$60,"<"&$D21))+(COUNTIFS('📋 May 2026'!$B$5:$B$60,$A21,'📋 May 2026'!$AB$5:$AB$60,"Alumni")+COUNTIFS('📋 Jun 2026'!$B$5:$B$60,$A21,'📋 Jun 2026'!$AB$5:$AB$60,"Alumni")+COUNTIFS('📋 Jul 2026'!$B$5:$B$60,$A21,'📋 Jul 2026'!$AB$5:$AB$60,"Alumni")+COUNTIFS('📋 Aug 2026'!$B$5:$B$60,$A21,'📋 Aug 2026'!$AB$5:$AB$60,"Alumni")+COUNTIFS('📋 Sep 2026'!$B$5:$B$60,$A21,'📋 Sep 2026'!$AB$5:$AB$60,"Alumni")+COUNTIFS('📋 Oct 2026'!$B$5:$B$60,$A21,'📋 Oct 2026'!$AB$5:$AB$60,"Alumni")+COUNTIFS('📋 Nov 2026'!$B$5:$B$60,$A21,'📋 Nov 2026'!$AB$5:$AB$60,"Alumni")+COUNTIFS('📋 Dec 2026'!$B$5:$B$60,$A21,'📋 Dec 2026'!$AB$5:$AB$60,"Alumni"))>=1,"Alumni","New")) -> New
A22: Cree Lamere | B22: H1-1B | C22: Occupied | D22: 46170 | E22: DTX/RTC | F22: DTX/RTC | G22: 30 | H22: Blue Shield CA | I22: Ahbra/Profound | J22: Amy | K22: N | N22: 46202 | O22: =IF($A22="","",IF($N22<>"",$N22,IF(AND($D22<>"",$G22<>""),$D22+$G22,""))) -> 46202 | P22: =IF(O22="","",O22-TODAY()) -> 12 | Q22: =IF(OR($A22="",$D22=""),"",IF((COUNTIFS('📋 May 2026'!$B$5:$B$60,$A22,'📋 May 2026'!$C$5:$C$60,"<"&$D22)+COUNTIFS('📋 Jun 2026'!$B$5:$B$60,$A22,'📋 Jun 2026'!$C$5:$C$60,"<"&$D22)+COUNTIFS('📋 Jul 2026'!$B$5:$B$60,$A22,'📋 Jul 2026'!$C$5:$C$60,"<"&$D22)+COUNTIFS('📋 Aug 2026'!$B$5:$B$60,$A22,'📋 Aug 2026'!$C$5:$C$60,"<"&$D22)+COUNTIFS('📋 Sep 2026'!$B$5:$B$60,$A22,'📋 Sep 2026'!$C$5:$C$60,"<"&$D22)+COUNTIFS('📋 Oct 2026'!$B$5:$B$60,$A22,'📋 Oct 2026'!$C$5:$C$60,"<"&$D22)+COUNTIFS('📋 Nov 2026'!$B$5:$B$60,$A22,'📋 Nov 2026'!$C$5:$C$60,"<"&$D22)+COUNTIFS('📋 Dec 2026'!$B$5:$B$60,$A22,'📋 Dec 2026'!$C$5:$C$60,"<"&$D22))+(COUNTIFS('📋 May 2026'!$B$5:$B$60,$A22,'📋 May 2026'!$AB$5:$AB$60,"Alumni")+COUNTIFS('📋 Jun 2026'!$B$5:$B$60,$A22,'📋 Jun 2026'!$AB$5:$AB$60,"Alumni")+COUNTIFS('📋 Jul 2026'!$B$5:$B$60,$A22,'📋 Jul 2026'!$AB$5:$AB$60,"Alumni")+COUNTIFS('📋 Aug 2026'!$B$5:$B$60,$A22,'📋 Aug 2026'!$AB$5:$AB$60,"Alumni")+COUNTIFS('📋 Sep 2026'!$B$5:$B$60,$A22,'📋 Sep 2026'!$AB$5:$AB$60,"Alumni")+COUNTIFS('📋 Oct 2026'!$B$5:$B$60,$A22,'📋 Oct 2026'!$AB$5:$AB$60,"Alumni")+COUNTIFS('📋 Nov 2026'!$B$5:$B$60,$A22,'📋 Nov 2026'!$AB$5:$AB$60,"Alumni")+COUNTIFS('📋 Dec 2026'!$B$5:$B$60,$A22,'📋 Dec 2026'!$AB$5:$AB$60,"Alumni"))>=1,"Alumni","New")) -> New
A23: Rhonda Baim | B23: H1-2A | C23: Occupied | D23: 46166 | E23: DTX | F23: DTX | G23: 30 | H23: Anthem BC | I23: Web | J23: Nelson | K23: N | O23: =IF($A23="","",IF($N23<>"",$N23,IF(AND($D23<>"",$G23<>""),$D23+$G23,""))) -> 46196 | P23: =IF(O23="","",O23-TODAY()) -> 6 | Q23: =IF(OR($A23="",$D23=""),"",IF((COUNTIFS('📋 May 2026'!$B$5:$B$60,$A23,'📋 May 2026'!$C$5:$C$60,"<"&$D23)+COUNTIFS('📋 Jun 2026'!$B$5:$B$60,$A23,'📋 Jun 2026'!$C$5:$C$60,"<"&$D23)+COUNTIFS('📋 Jul 2026'!$B$5:$B$60,$A23,'📋 Jul 2026'!$C$5:$C$60,"<"&$D23)+COUNTIFS('📋 Aug 2026'!$B$5:$B$60,$A23,'📋 Aug 2026'!$C$5:$C$60,"<"&$D23)+COUNTIFS('📋 Sep 2026'!$B$5:$B$60,$A23,'📋 Sep 2026'!$C$5:$C$60,"<"&$D23)+COUNTIFS('📋 Oct 2026'!$B$5:$B$60,$A23,'📋 Oct 2026'!$C$5:$C$60,"<"&$D23)+COUNTIFS('📋 Nov 2026'!$B$5:$B$60,$A23,'📋 Nov 2026'!$C$5:$C$60,"<"&$D23)+COUNTIFS('📋 Dec 2026'!$B$5:$B$60,$A23,'📋 Dec 2026'!$C$5:$C$60,"<"&$D23))+(COUNTIFS('📋 May 2026'!$B$5:$B$60,$A23,'📋 May 2026'!$AB$5:$AB$60,"Alumni")+COUNTIFS('📋 Jun 2026'!$B$5:$B$60,$A23,'📋 Jun 2026'!$AB$5:$AB$60,"Alumni")+COUNTIFS('📋 Jul 2026'!$B$5:$B$60,$A23,'📋 Jul 2026'!$AB$5:$AB$60,"Alumni")+COUNTIFS('📋 Aug 2026'!$B$5:$B$60,$A23,'📋 Aug 2026'!$AB$5:$AB$60,"Alumni")+COUNTIFS('📋 Sep 2026'!$B$5:$B$60,$A23,'📋 Sep 2026'!$AB$5:$AB$60,"Alumni")+COUNTIFS('📋 Oct 2026'!$B$5:$B$60,$A23,'📋 Oct 2026'!$AB$5:$AB$60,"Alumni")+COUNTIFS('📋 Nov 2026'!$B$5:$B$60,$A23,'📋 Nov 2026'!$AB$5:$AB$60,"Alumni")+COUNTIFS('📋 Dec 2026'!$B$5:$B$60,$A23,'📋 Dec 2026'!$AB$5:$AB$60,"Alumni"))>=1,"Alumni","New")) -> New
A24: Aaron Dufresne | B24: H1-3A | C24: Occupied | D24: 46171 | E24: DTX | F24: DTX | G24: 30 | H24: UMR/UHC | I24: Ahbra/Action IOP | J24: Nelson | K24: N | O24: =IF($A24="","",IF($N24<>"",$N24,IF(AND($D24<>"",$G24<>""),$D24+$G24,""))) -> 46201 | P24: =IF(O24="","",O24-TODAY()) -> 11 | Q24: =IF(OR($A24="",$D24=""),"",IF((COUNTIFS('📋 May 2026'!$B$5:$B$60,$A24,'📋 May 2026'!$C$5:$C$60,"<"&$D24)+COUNTIFS('📋 Jun 2026'!$B$5:$B$60,$A24,'📋 Jun 2026'!$C$5:$C$60,"<"&$D24)+COUNTIFS('📋 Jul 2026'!$B$5:$B$60,$A24,'📋 Jul 2026'!$C$5:$C$60,"<"&$D24)+COUNTIFS('📋 Aug 2026'!$B$5:$B$60,$A24,'📋 Aug 2026'!$C$5:$C$60,"<"&$D24)+COUNTIFS('📋 Sep 2026'!$B$5:$B$60,$A24,'📋 Sep 2026'!$C$5:$C$60,"<"&$D24)+COUNTIFS('📋 Oct 2026'!$B$5:$B$60,$A24,'📋 Oct 2026'!$C$5:$C$60,"<"&$D24)+COUNTIFS('📋 Nov 2026'!$B$5:$B$60,$A24,'📋 Nov 2026'!$C$5:$C$60,"<"&$D24)+COUNTIFS('📋 Dec 2026'!$B$5:$B$60,$A24,'📋 Dec 2026'!$C$5:$C$60,"<"&$D24))+(COUNTIFS('📋 May 2026'!$B$5:$B$60,$A24,'📋 May 2026'!$AB$5:$AB$60,"Alumni")+COUNTIFS('📋 Jun 2026'!$B$5:$B$60,$A24,'📋 Jun 2026'!$AB$5:$AB$60,"Alumni")+COUNTIFS('📋 Jul 2026'!$B$5:$B$60,$A24,'📋 Jul 2026'!$AB$5:$AB$60,"Alumni")+COUNTIFS('📋 Aug 2026'!$B$5:$B$60,$A24,'📋 Aug 2026'!$AB$5:$AB$60,"Alumni")+COUNTIFS('📋 Sep 2026'!$B$5:$B$60,$A24,'📋 Sep 2026'!$AB$5:$AB$60,"Alumni")+COUNTIFS('📋 Oct 2026'!$B$5:$B$60,$A24,'📋 Oct 2026'!$AB$5:$AB$60,"Alumni")+COUNTIFS('📋 Nov 2026'!$B$5:$B$60,$A24,'📋 Nov 2026'!$AB$5:$AB$60,"Alumni")+COUNTIFS('📋 Dec 2026'!$B$5:$B$60,$A24,'📋 Dec 2026'!$AB$5:$AB$60,"Alumni"))>=1,"Alumni","New")) -> New
B25: H1-3B | O25: =IF($A25="","",IF($N25<>"",$N25,IF(AND($D25<>"",$G25<>""),$D25+$G25,""))) | P25: =IF(O25="","",O25-TODAY()) | Q25: =IF(OR($A25="",$D25=""),"",IF((COUNTIFS('📋 May 2026'!$B$5:$B$60,$A25,'📋 May 2026'!$C$5:$C$60,"<"&$D25)+COUNTIFS('📋 Jun 2026'!$B$5:$B$60,$A25,'📋 Jun 2026'!$C$5:$C$60,"<"&$D25)+COUNTIFS('📋 Jul 2026'!$B$5:$B$60,$A25,'📋 Jul 2026'!$C$5:$C$60,"<"&$D25)+COUNTIFS('📋 Aug 2026'!$B$5:$B$60,$A25,'📋 Aug 2026'!$C$5:$C$60,"<"&$D25)+COUNTIFS('📋 Sep 2026'!$B$5:$B$60,$A25,'📋 Sep 2026'!$C$5:$C$60,"<"&$D25)+COUNTIFS('📋 Oct 2026'!$B$5:$B$60,$A25,'📋 Oct 2026'!$C$5:$C$60,"<"&$D25)+COUNTIFS('📋 Nov 2026'!$B$5:$B$60,$A25,'📋 Nov 2026'!$C$5:$C$60,"<"&$D25)+COUNTIFS('📋 Dec 2026'!$B$5:$B$60,$A25,'📋 Dec 2026'!$C$5:$C$60,"<"&$D25))+(COUNTIFS('📋 May 2026'!$B$5:$B$60,$A25,'📋 May 2026'!$AB$5:$AB$60,"Alumni")+COUNTIFS('📋 Jun 2026'!$B$5:$B$60,$A25,'📋 Jun 2026'!$AB$5:$AB$60,"Alumni")+COUNTIFS('📋 Jul 2026'!$B$5:$B$60,$A25,'📋 Jul 2026'!$AB$5:$AB$60,"Alumni")+COUNTIFS('📋 Aug 2026'!$B$5:$B$60,$A25,'📋 Aug 2026'!$AB$5:$AB$60,"Alumni")+COUNTIFS('📋 Sep 2026'!$B$5:$B$60,$A25,'📋 Sep 2026'!$AB$5:$AB$60,"Alumni")+COUNTIFS('📋 Oct 2026'!$B$5:$B$60,$A25,'📋 Oct 2026'!$AB$5:$AB$60,"Alumni")+COUNTIFS('📋 Nov 2026'!$B$5:$B$60,$A25,'📋 Nov 2026'!$AB$5:$AB$60,"Alumni")+COUNTIFS('📋 Dec 2026'!$B$5:$B$60,$A25,'📋 Dec 2026'!$AB$5:$AB$60,"Alumni"))>=1,"Alumni","New"))
A26: Jared Hamilton | B26: H1-4 | C26: Occupied | D26: 46175 | E26: DTX/RTC | F26: DTX/RTC | G26: 30 | H26: Blue Shield PPO | I26: Rise | J26: Amy | K26: N | O26: =IF($A26="","",IF($N26<>"",$N26,IF(AND($D26<>"",$G26<>""),$D26+$G26,""))) -> 46205 | P26: =IF(O26="","",O26-TODAY()) -> 15 | Q26: =IF(OR($A26="",$D26=""),"",IF((COUNTIFS('📋 May 2026'!$B$5:$B$60,$A26,'📋 May 2026'!$C$5:$C$60,"<"&$D26)+COUNTIFS('📋 Jun 2026'!$B$5:$B$60,$A26,'📋 Jun 2026'!$C$5:$C$60,"<"&$D26)+COUNTIFS('📋 Jul 2026'!$B$5:$B$60,$A26,'📋 Jul 2026'!$C$5:$C$60,"<"&$D26)+COUNTIFS('📋 Aug 2026'!$B$5:$B$60,$A26,'📋 Aug 2026'!$C$5:$C$60,"<"&$D26)+COUNTIFS('📋 Sep 2026'!$B$5:$B$60,$A26,'📋 Sep 2026'!$C$5:$C$60,"<"&$D26)+COUNTIFS('📋 Oct 2026'!$B$5:$B$60,$A26,'📋 Oct 2026'!$C$5:$C$60,"<"&$D26)+COUNTIFS('📋 Nov 2026'!$B$5:$B$60,$A26,'📋 Nov 2026'!$C$5:$C$60,"<"&$D26)+COUNTIFS('📋 Dec 2026'!$B$5:$B$60,$A26,'📋 Dec 2026'!$C$5:$C$60,"<"&$D26))+(COUNTIFS('📋 May 2026'!$B$5:$B$60,$A26,'📋 May 2026'!$AB$5:$AB$60,"Alumni")+COUNTIFS('📋 Jun 2026'!$B$5:$B$60,$A26,'📋 Jun 2026'!$AB$5:$AB$60,"Alumni")+COUNTIFS('📋 Jul 2026'!$B$5:$B$60,$A26,'📋 Jul 2026'!$AB$5:$AB$60,"Alumni")+COUNTIFS('📋 Aug 2026'!$B$5:$B$60,$A26,'📋 Aug 2026'!$AB$5:$AB$60,"Alumni")+COUNTIFS('📋 Sep 2026'!$B$5:$B$60,$A26,'📋 Sep 2026'!$AB$5:$AB$60,"Alumni")+COUNTIFS('📋 Oct 2026'!$B$5:$B$60,$A26,'📋 Oct 2026'!$AB$5:$AB$60,"Alumni")+COUNTIFS('📋 Nov 2026'!$B$5:$B$60,$A26,'📋 Nov 2026'!$AB$5:$AB$60,"Alumni")+COUNTIFS('📋 Dec 2026'!$B$5:$B$60,$A26,'📋 Dec 2026'!$AB$5:$AB$60,"Alumni"))>=1,"Alumni","New")) -> New
A27: 🏢 HPE — BURBANK · HOUSE 2 (22915)
A28: Tara Shinde | B28: H2-2A | C28: Reserved | D28: 46192 | E28: DTX/RTC | G28: 30 | H28: BCBS IL | I28: web | J28: Amy | O28: =IF($A28="","",IF($N28<>"",$N28,IF(AND($D28<>"",$G28<>""),$D28+$G28,""))) -> 46222 | P28: =IF(O28="","",O28-TODAY()) -> 32 | Q28: =IF(OR($A28="",$D28=""),"",IF((COUNTIFS('📋 May 2026'!$B$5:$B$60,$A28,'📋 May 2026'!$C$5:$C$60,"<"&$D28)+COUNTIFS('📋 Jun 2026'!$B$5:$B$60,$A28,'📋 Jun 2026'!$C$5:$C$60,"<"&$D28)+COUNTIFS('📋 Jul 2026'!$B$5:$B$60,$A28,'📋 Jul 2026'!$C$5:$C$60,"<"&$D28)+COUNTIFS('📋 Aug 2026'!$B$5:$B$60,$A28,'📋 Aug 2026'!$C$5:$C$60,"<"&$D28)+COUNTIFS('📋 Sep 2026'!$B$5:$B$60,$A28,'📋 Sep 2026'!$C$5:$C$60,"<"&$D28)+COUNTIFS('📋 Oct 2026'!$B$5:$B$60,$A28,'📋 Oct 2026'!$C$5:$C$60,"<"&$D28)+COUNTIFS('📋 Nov 2026'!$B$5:$B$60,$A28,'📋 Nov 2026'!$C$5:$C$60,"<"&$D28)+COUNTIFS('📋 Dec 2026'!$B$5:$B$60,$A28,'📋 Dec 2026'!$C$5:$C$60,"<"&$D28))+(COUNTIFS('📋 May 2026'!$B$5:$B$60,$A28,'📋 May 2026'!$AB$5:$AB$60,"Alumni")+COUNTIFS('📋 Jun 2026'!$B$5:$B$60,$A28,'📋 Jun 2026'!$AB$5:$AB$60,"Alumni")+COUNTIFS('📋 Jul 2026'!$B$5:$B$60,$A28,'📋 Jul 2026'!$AB$5:$AB$60,"Alumni")+COUNTIFS('📋 Aug 2026'!$B$5:$B$60,$A28,'📋 Aug 2026'!$AB$5:$AB$60,"Alumni")+COUNTIFS('📋 Sep 2026'!$B$5:$B$60,$A28,'📋 Sep 2026'!$AB$5:$AB$60,"Alumni")+COUNTIFS('📋 Oct 2026'!$B$5:$B$60,$A28,'📋 Oct 2026'!$AB$5:$AB$60,"Alumni")+COUNTIFS('📋 Nov 2026'!$B$5:$B$60,$A28,'📋 Nov 2026'!$AB$5:$AB$60,"Alumni")+COUNTIFS('📋 Dec 2026'!$B$5:$B$60,$A28,'📋 Dec 2026'!$AB$5:$AB$60,"Alumni"))>=1,"Alumni","New")) -> New
B29: H2-2B | O29: =IF($A29="","",IF($N29<>"",$N29,IF(AND($D29<>"",$G29<>""),$D29+$G29,""))) | P29: =IF(O29="","",O29-TODAY()) | Q29: =IF(OR($A29="",$D29=""),"",IF((COUNTIFS('📋 May 2026'!$B$5:$B$60,$A29,'📋 May 2026'!$C$5:$C$60,"<"&$D29)+COUNTIFS('📋 Jun 2026'!$B$5:$B$60,$A29,'📋 Jun 2026'!$C$5:$C$60,"<"&$D29)+COUNTIFS('📋 Jul 2026'!$B$5:$B$60,$A29,'📋 Jul 2026'!$C$5:$C$60,"<"&$D29)+COUNTIFS('📋 Aug 2026'!$B$5:$B$60,$A29,'📋 Aug 2026'!$C$5:$C$60,"<"&$D29)+COUNTIFS('📋 Sep 2026'!$B$5:$B$60,$A29,'📋 Sep 2026'!$C$5:$C$60,"<"&$D29)+COUNTIFS('📋 Oct 2026'!$B$5:$B$60,$A29,'📋 Oct 2026'!$C$5:$C$60,"<"&$D29)+COUNTIFS('📋 Nov 2026'!$B$5:$B$60,$A29,'📋 Nov 2026'!$C$5:$C$60,"<"&$D29)+COUNTIFS('📋 Dec 2026'!$B$5:$B$60,$A29,'📋 Dec 2026'!$C$5:$C$60,"<"&$D29))+(COUNTIFS('📋 May 2026'!$B$5:$B$60,$A29,'📋 May 2026'!$AB$5:$AB$60,"Alumni")+COUNTIFS('📋 Jun 2026'!$B$5:$B$60,$A29,'📋 Jun 2026'!$AB$5:$AB$60,"Alumni")+COUNTIFS('📋 Jul 2026'!$B$5:$B$60,$A29,'📋 Jul 2026'!$AB$5:$AB$60,"Alumni")+COUNTIFS('📋 Aug 2026'!$B$5:$B$60,$A29,'📋 Aug 2026'!$AB$5:$AB$60,"Alumni")+COUNTIFS('📋 Sep 2026'!$B$5:$B$60,$A29,'📋 Sep 2026'!$AB$5:$AB$60,"Alumni")+COUNTIFS('📋 Oct 2026'!$B$5:$B$60,$A29,'📋 Oct 2026'!$AB$5:$AB$60,"Alumni")+COUNTIFS('📋 Nov 2026'!$B$5:$B$60,$A29,'📋 Nov 2026'!$AB$5:$AB$60,"Alumni")+COUNTIFS('📋 Dec 2026'!$B$5:$B$60,$A29,'📋 Dec 2026'!$AB$5:$AB$60,"Alumni"))>=1,"Alumni","New"))
A30: Daniel Armiger | B30: H2-3A | C30: Occupied | D30: 46182 | E30: DTX/RTC | F30: RTC | G30: 30 | H30: Blue Shield CA | I30: Readmit | J30: Matthew | O30: =IF($A30="","",IF($N30<>"",$N30,IF(AND($D30<>"",$G30<>""),$D30+$G30,""))) -> 46212 | P30: =IF(O30="","",O30-TODAY()) -> 22 | Q30: =IF(OR($A30="",$D30=""),"",IF((COUNTIFS('📋 May 2026'!$B$5:$B$60,$A30,'📋 May 2026'!$C$5:$C$60,"<"&$D30)+COUNTIFS('📋 Jun 2026'!$B$5:$B$60,$A30,'📋 Jun 2026'!$C$5:$C$60,"<"&$D30)+COUNTIFS('📋 Jul 2026'!$B$5:$B$60,$A30,'📋 Jul 2026'!$C$5:$C$60,"<"&$D30)+COUNTIFS('📋 Aug 2026'!$B$5:$B$60,$A30,'📋 Aug 2026'!$C$5:$C$60,"<"&$D30)+COUNTIFS('📋 Sep 2026'!$B$5:$B$60,$A30,'📋 Sep 2026'!$C$5:$C$60,"<"&$D30)+COUNTIFS('📋 Oct 2026'!$B$5:$B$60,$A30,'📋 Oct 2026'!$C$5:$C$60,"<"&$D30)+COUNTIFS('📋 Nov 2026'!$B$5:$B$60,$A30,'📋 Nov 2026'!$C$5:$C$60,"<"&$D30)+COUNTIFS('📋 Dec 2026'!$B$5:$B$60,$A30,'📋 Dec 2026'!$C$5:$C$60,"<"&$D30))+(COUNTIFS('📋 May 2026'!$B$5:$B$60,$A30,'📋 May 2026'!$AB$5:$AB$60,"Alumni")+COUNTIFS('📋 Jun 2026'!$B$5:$B$60,$A30,'📋 Jun 2026'!$AB$5:$AB$60,"Alumni")+COUNTIFS('📋 Jul 2026'!$B$5:$B$60,$A30,'📋 Jul 2026'!$AB$5:$AB$60,"Alumni")+COUNTIFS('📋 Aug 2026'!$B$5:$B$60,$A30,'📋 Aug 2026'!$AB$5:$AB$60,"Alumni")+COUNTIFS('📋 Sep 2026'!$B$5:$B$60,$A30,'📋 Sep 2026'!$AB$5:$AB$60,"Alumni")+COUNTIFS('📋 Oct 2026'!$B$5:$B$60,$A30,'📋 Oct 2026'!$AB$5:$AB$60,"Alumni")+COUNTIFS('📋 Nov 2026'!$B$5:$B$60,$A30,'📋 Nov 2026'!$AB$5:$AB$60,"Alumni")+COUNTIFS('📋 Dec 2026'!$B$5:$B$60,$A30,'📋 Dec 2026'!$AB$5:$AB$60,"Alumni"))>=1,"Alumni","New")) -> New
A31: Blayne Olivier | B31: H2-3B | C31: Occupied | D31: 46186 | E31: DTX/RTC | G31: 30 | H31: Molina | I31: Readmit | J31: Amy | K31: N | O31: =IF($A31="","",IF($N31<>"",$N31,IF(AND($D31<>"",$G31<>""),$D31+$G31,""))) -> 46216 | P31: =IF(O31="","",O31-TODAY()) -> 26 | Q31: =IF(OR($A31="",$D31=""),"",IF((COUNTIFS('📋 May 2026'!$B$5:$B$60,$A31,'📋 May 2026'!$C$5:$C$60,"<"&$D31)+COUNTIFS('📋 Jun 2026'!$B$5:$B$60,$A31,'📋 Jun 2026'!$C$5:$C$60,"<"&$D31)+COUNTIFS('📋 Jul 2026'!$B$5:$B$60,$A31,'📋 Jul 2026'!$C$5:$C$60,"<"&$D31)+COUNTIFS('📋 Aug 2026'!$B$5:$B$60,$A31,'📋 Aug 2026'!$C$5:$C$60,"<"&$D31)+COUNTIFS('📋 Sep 2026'!$B$5:$B$60,$A31,'📋 Sep 2026'!$C$5:$C$60,"<"&$D31)+COUNTIFS('📋 Oct 2026'!$B$5:$B$60,$A31,'📋 Oct 2026'!$C$5:$C$60,"<"&$D31)+COUNTIFS('📋 Nov 2026'!$B$5:$B$60,$A31,'📋 Nov 2026'!$C$5:$C$60,"<"&$D31)+COUNTIFS('📋 Dec 2026'!$B$5:$B$60,$A31,'📋 Dec 2026'!$C$5:$C$60,"<"&$D31))+(COUNTIFS('📋 May 2026'!$B$5:$B$60,$A31,'📋 May 2026'!$AB$5:$AB$60,"Alumni")+COUNTIFS('📋 Jun 2026'!$B$5:$B$60,$A31,'📋 Jun 2026'!$AB$5:$AB$60,"Alumni")+COUNTIFS('📋 Jul 2026'!$B$5:$B$60,$A31,'📋 Jul 2026'!$AB$5:$AB$60,"Alumni")+COUNTIFS('📋 Aug 2026'!$B$5:$B$60,$A31,'📋 Aug 2026'!$AB$5:$AB$60,"Alumni")+COUNTIFS('📋 Sep 2026'!$B$5:$B$60,$A31,'📋 Sep 2026'!$AB$5:$AB$60,"Alumni")+COUNTIFS('📋 Oct 2026'!$B$5:$B$60,$A31,'📋 Oct 2026'!$AB$5:$AB$60,"Alumni")+COUNTIFS('📋 Nov 2026'!$B$5:$B$60,$A31,'📋 Nov 2026'!$AB$5:$AB$60,"Alumni")+COUNTIFS('📋 Dec 2026'!$B$5:$B$60,$A31,'📋 Dec 2026'!$AB$5:$AB$60,"Alumni"))>=1,"Alumni","New")) -> Alumni
A32: Bradey Bauer | B32: H2-3C | C32: Occupied | D32: 46186 | E32: DTX/RTC | G32: 30 | H32: Anthem BC | I32: Readmit/Rise | J32: Matthew | K32: y | O32: =IF($A32="","",IF($N32<>"",$N32,IF(AND($D32<>"",$G32<>""),$D32+$G32,""))) -> 46216 | P32: =IF(O32="","",O32-TODAY()) -> 26 | Q32: =IF(OR($A32="",$D32=""),"",IF((COUNTIFS('📋 May 2026'!$B$5:$B$60,$A32,'📋 May 2026'!$C$5:$C$60,"<"&$D32)+COUNTIFS('📋 Jun 2026'!$B$5:$B$60,$A32,'📋 Jun 2026'!$C$5:$C$60,"<"&$D32)+COUNTIFS('📋 Jul 2026'!$B$5:$B$60,$A32,'📋 Jul 2026'!$C$5:$C$60,"<"&$D32)+COUNTIFS('📋 Aug 2026'!$B$5:$B$60,$A32,'📋 Aug 2026'!$C$5:$C$60,"<"&$D32)+COUNTIFS('📋 Sep 2026'!$B$5:$B$60,$A32,'📋 Sep 2026'!$C$5:$C$60,"<"&$D32)+COUNTIFS('📋 Oct 2026'!$B$5:$B$60,$A32,'📋 Oct 2026'!$C$5:$C$60,"<"&$D32)+COUNTIFS('📋 Nov 2026'!$B$5:$B$60,$A32,'📋 Nov 2026'!$C$5:$C$60,"<"&$D32)+COUNTIFS('📋 Dec 2026'!$B$5:$B$60,$A32,'📋 Dec 2026'!$C$5:$C$60,"<"&$D32))+(COUNTIFS('📋 May 2026'!$B$5:$B$60,$A32,'📋 May 2026'!$AB$5:$AB$60,"Alumni")+COUNTIFS('📋 Jun 2026'!$B$5:$B$60,$A32,'📋 Jun 2026'!$AB$5:$AB$60,"Alumni")+COUNTIFS('📋 Jul 2026'!$B$5:$B$60,$A32,'📋 Jul 2026'!$AB$5:$AB$60,"Alumni")+COUNTIFS('📋 Aug 2026'!$B$5:$B$60,$A32,'📋 Aug 2026'!$AB$5:$AB$60,"Alumni")+COUNTIFS('📋 Sep 2026'!$B$5:$B$60,$A32,'📋 Sep 2026'!$AB$5:$AB$60,"Alumni")+COUNTIFS('📋 Oct 2026'!$B$5:$B$60,$A32,'📋 Oct 2026'!$AB$5:$AB$60,"Alumni")+COUNTIFS('📋 Nov 2026'!$B$5:$B$60,$A32,'📋 Nov 2026'!$AB$5:$AB$60,"Alumni")+COUNTIFS('📋 Dec 2026'!$B$5:$B$60,$A32,'📋 Dec 2026'!$AB$5:$AB$60,"Alumni"))>=1,"Alumni","New")) -> Alumni
A33: Jeongwoon Lee | B33: H2-4 | C33: Occupied | D33: 46167 | E33: RTC | F33: RTC | G33: 30 | H33: Aetna | I33: Web | J33: Nelson | K33: Y | N33: 46199 | O33: =IF($A33="","",IF($N33<>"",$N33,IF(AND($D33<>"",$G33<>""),$D33+$G33,""))) -> 46199 | P33: =IF(O33="","",O33-TODAY()) -> 9 | Q33: =IF(OR($A33="",$D33=""),"",IF((COUNTIFS('📋 May 2026'!$B$5:$B$60,$A33,'📋 May 2026'!$C$5:$C$60,"<"&$D33)+COUNTIFS('📋 Jun 2026'!$B$5:$B$60,$A33,'📋 Jun 2026'!$C$5:$C$60,"<"&$D33)+COUNTIFS('📋 Jul 2026'!$B$5:$B$60,$A33,'📋 Jul 2026'!$C$5:$C$60,"<"&$D33)+COUNTIFS('📋 Aug 2026'!$B$5:$B$60,$A33,'📋 Aug 2026'!$C$5:$C$60,"<"&$D33)+COUNTIFS('📋 Sep 2026'!$B$5:$B$60,$A33,'📋 Sep 2026'!$C$5:$C$60,"<"&$D33)+COUNTIFS('📋 Oct 2026'!$B$5:$B$60,$A33,'📋 Oct 2026'!$C$5:$C$60,"<"&$D33)+COUNTIFS('📋 Nov 2026'!$B$5:$B$60,$A33,'📋 Nov 2026'!$C$5:$C$60,"<"&$D33)+COUNTIFS('📋 Dec 2026'!$B$5:$B$60,$A33,'📋 Dec 2026'!$C$5:$C$60,"<"&$D33))+(COUNTIFS('📋 May 2026'!$B$5:$B$60,$A33,'📋 May 2026'!$AB$5:$AB$60,"Alumni")+COUNTIFS('📋 Jun 2026'!$B$5:$B$60,$A33,'📋 Jun 2026'!$AB$5:$AB$60,"Alumni")+COUNTIFS('📋 Jul 2026'!$B$5:$B$60,$A33,'📋 Jul 2026'!$AB$5:$AB$60,"Alumni")+COUNTIFS('📋 Aug 2026'!$B$5:$B$60,$A33,'📋 Aug 2026'!$AB$5:$AB$60,"Alumni")+COUNTIFS('📋 Sep 2026'!$B$5:$B$60,$A33,'📋 Sep 2026'!$AB$5:$AB$60,"Alumni")+COUNTIFS('📋 Oct 2026'!$B$5:$B$60,$A33,'📋 Oct 2026'!$AB$5:$AB$60,"Alumni")+COUNTIFS('📋 Nov 2026'!$B$5:$B$60,$A33,'📋 Nov 2026'!$AB$5:$AB$60,"Alumni")+COUNTIFS('📋 Dec 2026'!$B$5:$B$60,$A33,'📋 Dec 2026'!$AB$5:$AB$60,"Alumni"))>=1,"Alumni","New")) -> New

Sheet 🛏 HP Bed Board
A1: 🛏 HP Bed Board | 23041/23043 Hatteras St (14 beds)
A2: ="Census: "&COUNTIF(B10:B23,"Occupied")&"/14" -> Census: 11/14 | C2: ="Reserved: "&COUNTIF(B10:B23,"Reserved") -> Reserved: 0 | E2: ="Open: "&COUNTIF(B10:B23,"Open") -> Open: 3 | G2: =TEXT(COUNTIF(B10:B23,"Occupied")/14,"0%")&" capacity" -> 79% capacity | I2: =IFERROR(COUNTIFS(B10:B23,"Occupied",H10:H23,">="&TODAY(),H10:H23,"<="&TODAY()+7)&" DC within 7 days","0 DC within 7 days") -> 2 DC within 7 days
A4: 📝 ALL EDITS HAPPEN ON THE ROSTER TAB — this board updates automatically. 🔎 FILTER: click the ▼ buttons on the header row (e.g. STATUS = Open to find vacancies, or REP to see one rep's beds).
A6: OPEN — available | D6: RESERVED | G6: OCCUPIED | J6: ⚠ FLAGGED — verify
A9: ROOM | B9: STATUS | C9: CLIENT NAME | D9: ADMIT DATE | E9: ADMIT LOC | F9: CURRENT LOC | G9: PLAN LOS | H9: DC DATE | I9: TO DC | J9: FINANCIAL | K9: REFERRAL | L9: CHIRO Y/N | M9: REP | N9: AMA RISK | O9: DC LOC | P9: SORT# | Q9: DC OVERRIDE
A10: DTX-A | B10: =IF($A10="","",IF(COUNTIF('📝 Roster'!$B:$B,$A10)=0,"Open",IF(IFERROR(INDEX('📝 Roster'!$C:$C,MATCH($A10,'📝 Roster'!$B:$B,0)),"")="","Open",INDEX('📝 Roster'!$C:$C,MATCH($A10,'📝 Roster'!$B:$B,0))))) -> Open | C10: =IF($B10="Open","",IFERROR(INDEX('📝 Roster'!$A:$A,MATCH($A10,'📝 Roster'!$B:$B,0)),"")) | D10: =IF($B10="Open","",IFERROR(INDEX('📝 Roster'!$D:$D,MATCH($A10,'📝 Roster'!$B:$B,0)),"")) | E10: =IF($B10="Open","",IFERROR(INDEX('📝 Roster'!$E:$E,MATCH($A10,'📝 Roster'!$B:$B,0)),"")) | F10: =IF($B10="Open","",IFERROR(INDEX('📝 Roster'!$F:$F,MATCH($A10,'📝 Roster'!$B:$B,0)),"")) | G10: =IF($B10="Open","",IFERROR(INDEX('📝 Roster'!$G:$G,MATCH($A10,'📝 Roster'!$B:$B,0)),"")) | H10: =IF($Q10<>"",$Q10,IF(AND($D10<>"",$G10<>""),INT($D10)+$G10,"")) | I10: =IF(H10="","",IF(H10<TODAY(),"PAST ("&INT(TODAY()-H10)&"d ago)",IF(H10=TODAY(),"TODAY",INT(H10-TODAY())))) | J10: =IF($B10="Open","",IFERROR(INDEX('📝 Roster'!$H:$H,MATCH($A10,'📝 Roster'!$B:$B,0)),"")) | K10: =IF($B10="Open","",IFERROR(INDEX('📝 Roster'!$I:$I,MATCH($A10,'📝 Roster'!$B:$B,0)),"")) | L10: =IF($B10="Open","",IFERROR(INDEX('📝 Roster'!$K:$K,MATCH($A10,'📝 Roster'!$B:$B,0)),"")) | M10: =IF($B10="Open","",IFERROR(INDEX('📝 Roster'!$J:$J,MATCH($A10,'📝 Roster'!$B:$B,0)),"")) | N10: =IF($B10="Open","",IFERROR(INDEX('📝 Roster'!$L:$L,MATCH($A10,'📝 Roster'!$B:$B,0)),"")) | O10: =IF($B10="Open","",IFERROR(INDEX('📝 Roster'!$M:$M,MATCH($A10,'📝 Roster'!$B:$B,0)),"")) | P10: =IFERROR(MATCH($A10,HP_ROOMS,0),99) -> 1 | Q10: =IFERROR(IF(INDEX('📝 Roster'!$N:$N,MATCH($A10,'📝 Roster'!$B:$B,0))=0,"",INDEX('📝 Roster'!$N:$N,MATCH($A10,'📝 Roster'!$B:$B,0))),"")
A11: DTX-B | B11: =IF($A11="","",IF(COUNTIF('📝 Roster'!$B:$B,$A11)=0,"Open",IF(IFERROR(INDEX('📝 Roster'!$C:$C,MATCH($A11,'📝 Roster'!$B:$B,0)),"")="","Open",INDEX('📝 Roster'!$C:$C,MATCH($A11,'📝 Roster'!$B:$B,0))))) -> Open | C11: =IF($B11="Open","",IFERROR(INDEX('📝 Roster'!$A:$A,MATCH($A11,'📝 Roster'!$B:$B,0)),"")) | D11: =IF($B11="Open","",IFERROR(INDEX('📝 Roster'!$D:$D,MATCH($A11,'📝 Roster'!$B:$B,0)),"")) | E11: =IF($B11="Open","",IFERROR(INDEX('📝 Roster'!$E:$E,MATCH($A11,'📝 Roster'!$B:$B,0)),"")) | F11: =IF($B11="Open","",IFERROR(INDEX('📝 Roster'!$F:$F,MATCH($A11,'📝 Roster'!$B:$B,0)),"")) | G11: =IF($B11="Open","",IFERROR(INDEX('📝 Roster'!$G:$G,MATCH($A11,'📝 Roster'!$B:$B,0)),"")) | H11: =IF($Q11<>"",$Q11,IF(AND($D11<>"",$G11<>""),INT($D11)+$G11,"")) | I11: =IF(H11="","",IF(H11<TODAY(),"PAST ("&INT(TODAY()-H11)&"d ago)",IF(H11=TODAY(),"TODAY",INT(H11-TODAY())))) | J11: =IF($B11="Open","",IFERROR(INDEX('📝 Roster'!$H:$H,MATCH($A11,'📝 Roster'!$B:$B,0)),"")) | K11: =IF($B11="Open","",IFERROR(INDEX('📝 Roster'!$I:$I,MATCH($A11,'📝 Roster'!$B:$B,0)),"")) | L11: =IF($B11="Open","",IFERROR(INDEX('📝 Roster'!$K:$K,MATCH($A11,'📝 Roster'!$B:$B,0)),"")) | M11: =IF($B11="Open","",IFERROR(INDEX('📝 Roster'!$J:$J,MATCH($A11,'📝 Roster'!$B:$B,0)),"")) | N11: =IF($B11="Open","",IFERROR(INDEX('📝 Roster'!$L:$L,MATCH($A11,'📝 Roster'!$B:$B,0)),"")) | O11: =IF($B11="Open","",IFERROR(INDEX('📝 Roster'!$M:$M,MATCH($A11,'📝 Roster'!$B:$B,0)),"")) | P11: =IFERROR(MATCH($A11,HP_ROOMS,0),99) -> 2 | Q11: =IFERROR(IF(INDEX('📝 Roster'!$N:$N,MATCH($A11,'📝 Roster'!$B:$B,0))=0,"",INDEX('📝 Roster'!$N:$N,MATCH($A11,'📝 Roster'!$B:$B,0))),"")
A12: M1-A | B12: =IF($A12="","",IF(COUNTIF('📝 Roster'!$B:$B,$A12)=0,"Open",IF(IFERROR(INDEX('📝 Roster'!$C:$C,MATCH($A12,'📝 Roster'!$B:$B,0)),"")="","Open",INDEX('📝 Roster'!$C:$C,MATCH($A12,'📝 Roster'!$B:$B,0))))) -> Occupied | C12: =IF($B12="Open","",IFERROR(INDEX('📝 Roster'!$A:$A,MATCH($A12,'📝 Roster'!$B:$B,0)),"")) -> Kurt Guisler | D12: =IF($B12="Open","",IFERROR(INDEX('📝 Roster'!$D:$D,MATCH($A12,'📝 Roster'!$B:$B,0)),"")) -> 46172 | E12: =IF($B12="Open","",IFERROR(INDEX('📝 Roster'!$E:$E,MATCH($A12,'📝 Roster'!$B:$B,0)),"")) -> DTX/RTC | F12: =IF($B12="Open","",IFERROR(INDEX('📝 Roster'!$F:$F,MATCH($A12,'📝 Roster'!$B:$B,0)),"")) -> DTX/RTC | G12: =IF($B12="Open","",IFERROR(INDEX('📝 Roster'!$G:$G,MATCH($A12,'📝 Roster'!$B:$B,0)),"")) -> 30 | H12: =IF($Q12<>"",$Q12,IF(AND($D12<>"",$G12<>""),INT($D12)+$G12,"")) -> 46201 | I12: =IF(H12="","",IF(H12<TODAY(),"PAST ("&INT(TODAY()-H12)&"d ago)",IF(H12=TODAY(),"TODAY",INT(H12-TODAY())))) -> 11 | J12: =IF($B12="Open","",IFERROR(INDEX('📝 Roster'!$H:$H,MATCH($A12,'📝 Roster'!$B:$B,0)),"")) -> Blue Shield PPO | K12: =IF($B12="Open","",IFERROR(INDEX('📝 Roster'!$I:$I,MATCH($A12,'📝 Roster'!$B:$B,0)),"")) -> Skyline/Ahbra | L12: =IF($B12="Open","",IFERROR(INDEX('📝 Roster'!$K:$K,MATCH($A12,'📝 Roster'!$B:$B,0)),"")) -> N | M12: =IF($B12="Open","",IFERROR(INDEX('📝 Roster'!$J:$J,MATCH($A12,'📝 Roster'!$B:$B,0)),"")) -> Amy | N12: =IF($B12="Open","",IFERROR(INDEX('📝 Roster'!$L:$L,MATCH($A12,'📝 Roster'!$B:$B,0)),"")) -> 0 | O12: =IF($B12="Open","",IFERROR(INDEX('📝 Roster'!$M:$M,MATCH($A12,'📝 Roster'!$B:$B,0)),"")) -> 0 | P12: =IFERROR(MATCH($A12,HP_ROOMS,0),99) -> 3 | Q12: =IFERROR(IF(INDEX('📝 Roster'!$N:$N,MATCH($A12,'📝 Roster'!$B:$B,0))=0,"",INDEX('📝 Roster'!$N:$N,MATCH($A12,'📝 Roster'!$B:$B,0))),"") -> 46201
A13: M1-B | B13: =IF($A13="","",IF(COUNTIF('📝 Roster'!$B:$B,$A13)=0,"Open",IF(IFERROR(INDEX('📝 Roster'!$C:$C,MATCH($A13,'📝 Roster'!$B:$B,0)),"")="","Open",INDEX('📝 Roster'!$C:$C,MATCH($A13,'📝 Roster'!$B:$B,0))))) -> Occupied | C13: =IF($B13="Open","",IFERROR(INDEX('📝 Roster'!$A:$A,MATCH($A13,'📝 Roster'!$B:$B,0)),"")) -> Pedro Mendoza | D13: =IF($B13="Open","",IFERROR(INDEX('📝 Roster'!$D:$D,MATCH($A13,'📝 Roster'!$B:$B,0)),"")) -> 46176 | E13: =IF($B13="Open","",IFERROR(INDEX('📝 Roster'!$E:$E,MATCH($A13,'📝 Roster'!$B:$B,0)),"")) -> DTX/RTC | F13: =IF($B13="Open","",IFERROR(INDEX('📝 Roster'!$F:$F,MATCH($A13,'📝 Roster'!$B:$B,0)),"")) -> DTX/RTC | G13: =IF($B13="Open","",IFERROR(INDEX('📝 Roster'!$G:$G,MATCH($A13,'📝 Roster'!$B:$B,0)),"")) -> 30 | H13: =IF($Q13<>"",$Q13,IF(AND($D13<>"",$G13<>""),INT($D13)+$G13,"")) -> 46205 | I13: =IF(H13="","",IF(H13<TODAY(),"PAST ("&INT(TODAY()-H13)&"d ago)",IF(H13=TODAY(),"TODAY",INT(H13-TODAY())))) -> 15 | J13: =IF($B13="Open","",IFERROR(INDEX('📝 Roster'!$H:$H,MATCH($A13,'📝 Roster'!$B:$B,0)),"")) -> Blue Shield CA | K13: =IF($B13="Open","",IFERROR(INDEX('📝 Roster'!$I:$I,MATCH($A13,'📝 Roster'!$B:$B,0)),"")) -> Readmit | L13: =IF($B13="Open","",IFERROR(INDEX('📝 Roster'!$K:$K,MATCH($A13,'📝 Roster'!$B:$B,0)),"")) -> N | M13: =IF($B13="Open","",IFERROR(INDEX('📝 Roster'!$J:$J,MATCH($A13,'📝 Roster'!$B:$B,0)),"")) -> Matthew | N13: =IF($B13="Open","",IFERROR(INDEX('📝 Roster'!$L:$L,MATCH($A13,'📝 Roster'!$B:$B,0)),"")) -> 0 | O13: =IF($B13="Open","",IFERROR(INDEX('📝 Roster'!$M:$M,MATCH($A13,'📝 Roster'!$B:$B,0)),"")) -> 0 | P13: =IFERROR(MATCH($A13,HP_ROOMS,0),99) -> 4 | Q13: =IFERROR(IF(INDEX('📝 Roster'!$N:$N,MATCH($A13,'📝 Roster'!$B:$B,0))=0,"",INDEX('📝 Roster'!$N:$N,MATCH($A13,'📝 Roster'!$B:$B,0))),"") -> 46205
A14: M2-A | B14: =IF($A14="","",IF(COUNTIF('📝 Roster'!$B:$B,$A14)=0,"Open",IF(IFERROR(INDEX('📝 Roster'!$C:$C,MATCH($A14,'📝 Roster'!$B:$B,0)),"")="","Open",INDEX('📝 Roster'!$C:$C,MATCH($A14,'📝 Roster'!$B:$B,0))))) -> Open | C14: =IF($B14="Open","",IFERROR(INDEX('📝 Roster'!$A:$A,MATCH($A14,'📝 Roster'!$B:$B,0)),"")) | D14: =IF($B14="Open","",IFERROR(INDEX('📝 Roster'!$D:$D,MATCH($A14,'📝 Roster'!$B:$B,0)),"")) | E14: =IF($B14="Open","",IFERROR(INDEX('📝 Roster'!$E:$E,MATCH($A14,'📝 Roster'!$B:$B,0)),"")) | F14: =IF($B14="Open","",IFERROR(INDEX('📝 Roster'!$F:$F,MATCH($A14,'📝 Roster'!$B:$B,0)),"")) | G14: =IF($B14="Open","",IFERROR(INDEX('📝 Roster'!$G:$G,MATCH($A14,'📝 Roster'!$B:$B,0)),"")) | H14: =IF($Q14<>"",$Q14,IF(AND($D14<>"",$G14<>""),INT($D14)+$G14,"")) | I14: =IF(H14="","",IF(H14<TODAY(),"PAST ("&INT(TODAY()-H14)&"d ago)",IF(H14=TODAY(),"TODAY",INT(H14-TODAY())))) | J14: =IF($B14="Open","",IFERROR(INDEX('📝 Roster'!$H:$H,MATCH($A14,'📝 Roster'!$B:$B,0)),"")) | K14: =IF($B14="Open","",IFERROR(INDEX('📝 Roster'!$I:$I,MATCH($A14,'📝 Roster'!$B:$B,0)),"")) | L14: =IF($B14="Open","",IFERROR(INDEX('📝 Roster'!$K:$K,MATCH($A14,'📝 Roster'!$B:$B,0)),"")) | M14: =IF($B14="Open","",IFERROR(INDEX('📝 Roster'!$J:$J,MATCH($A14,'📝 Roster'!$B:$B,0)),"")) | N14: =IF($B14="Open","",IFERROR(INDEX('📝 Roster'!$L:$L,MATCH($A14,'📝 Roster'!$B:$B,0)),"")) | O14: =IF($B14="Open","",IFERROR(INDEX('📝 Roster'!$M:$M,MATCH($A14,'📝 Roster'!$B:$B,0)),"")) | P14: =IFERROR(MATCH($A14,HP_ROOMS,0),99) -> 5 | Q14: =IFERROR(IF(INDEX('📝 Roster'!$N:$N,MATCH($A14,'📝 Roster'!$B:$B,0))=0,"",INDEX('📝 Roster'!$N:$N,MATCH($A14,'📝 Roster'!$B:$B,0))),"")
A15: M2-B | B15: =IF($A15="","",IF(COUNTIF('📝 Roster'!$B:$B,$A15)=0,"Open",IF(IFERROR(INDEX('📝 Roster'!$C:$C,MATCH($A15,'📝 Roster'!$B:$B,0)),"")="","Open",INDEX('📝 Roster'!$C:$C,MATCH($A15,'📝 Roster'!$B:$B,0))))) -> Occupied | C15: =IF($B15="Open","",IFERROR(INDEX('📝 Roster'!$A:$A,MATCH($A15,'📝 Roster'!$B:$B,0)),"")) -> Darian Loehner | D15: =IF($B15="Open","",IFERROR(INDEX('📝 Roster'!$D:$D,MATCH($A15,'📝 Roster'!$B:$B,0)),"")) -> 46183 | E15: =IF($B15="Open","",IFERROR(INDEX('📝 Roster'!$E:$E,MATCH($A15,'📝 Roster'!$B:$B,0)),"")) -> DTX | F15: =IF($B15="Open","",IFERROR(INDEX('📝 Roster'!$F:$F,MATCH($A15,'📝 Roster'!$B:$B,0)),"")) -> DTX | G15: =IF($B15="Open","",IFERROR(INDEX('📝 Roster'!$G:$G,MATCH($A15,'📝 Roster'!$B:$B,0)),"")) -> 10 | H15: =IF($Q15<>"",$Q15,IF(AND($D15<>"",$G15<>""),INT($D15)+$G15,"")) -> 46193 | I15: =IF(H15="","",IF(H15<TODAY(),"PAST ("&INT(TODAY()-H15)&"d ago)",IF(H15=TODAY(),"TODAY",INT(H15-TODAY())))) -> 3 | J15: =IF($B15="Open","",IFERROR(INDEX('📝 Roster'!$H:$H,MATCH($A15,'📝 Roster'!$B:$B,0)),"")) -> Aetna | K15: =IF($B15="Open","",IFERROR(INDEX('📝 Roster'!$I:$I,MATCH($A15,'📝 Roster'!$B:$B,0)),"")) -> Readmit | L15: =IF($B15="Open","",IFERROR(INDEX('📝 Roster'!$K:$K,MATCH($A15,'📝 Roster'!$B:$B,0)),"")) -> Y | M15: =IF($B15="Open","",IFERROR(INDEX('📝 Roster'!$J:$J,MATCH($A15,'📝 Roster'!$B:$B,0)),"")) -> Amy | N15: =IF($B15="Open","",IFERROR(INDEX('📝 Roster'!$L:$L,MATCH($A15,'📝 Roster'!$B:$B,0)),"")) -> 0 | O15: =IF($B15="Open","",IFERROR(INDEX('📝 Roster'!$M:$M,MATCH($A15,'📝 Roster'!$B:$B,0)),"")) -> 0 | P15: =IFERROR(MATCH($A15,HP_ROOMS,0),99) -> 6 | Q15: =IFERROR(IF(INDEX('📝 Roster'!$N:$N,MATCH($A15,'📝 Roster'!$B:$B,0))=0,"",INDEX('📝 Roster'!$N:$N,MATCH($A15,'📝 Roster'!$B:$B,0))),"")
A16: M3-A | B16: =IF($A16="","",IF(COUNTIF('📝 Roster'!$B:$B,$A16)=0,"Open",IF(IFERROR(INDEX('📝 Roster'!$C:$C,MATCH($A16,'📝 Roster'!$B:$B,0)),"")="","Open",INDEX('📝 Roster'!$C:$C,MATCH($A16,'📝 Roster'!$B:$B,0))))) -> Occupied | C16: =IF($B16="Open","",IFERROR(INDEX('📝 Roster'!$A:$A,MATCH($A16,'📝 Roster'!$B:$B,0)),"")) -> Jill Labate | D16: =IF($B16="Open","",IFERROR(INDEX('📝 Roster'!$D:$D,MATCH($A16,'📝 Roster'!$B:$B,0)),"")) -> 46187 | E16: =IF($B16="Open","",IFERROR(INDEX('📝 Roster'!$E:$E,MATCH($A16,'📝 Roster'!$B:$B,0)),"")) -> DTX/RTC | F16: =IF($B16="Open","",IFERROR(INDEX('📝 Roster'!$F:$F,MATCH($A16,'📝 Roster'!$B:$B,0)),"")) -> DTX/RTC | G16: =IF($B16="Open","",IFERROR(INDEX('📝 Roster'!$G:$G,MATCH($A16,'📝 Roster'!$B:$B,0)),"")) -> 21 | H16: =IF($Q16<>"",$Q16,IF(AND($D16<>"",$G16<>""),INT($D16)+$G16,"")) -> 46208 | I16: =IF(H16="","",IF(H16<TODAY(),"PAST ("&INT(TODAY()-H16)&"d ago)",IF(H16=TODAY(),"TODAY",INT(H16-TODAY())))) -> 18 | J16: =IF($B16="Open","",IFERROR(INDEX('📝 Roster'!$H:$H,MATCH($A16,'📝 Roster'!$B:$B,0)),"")) -> Cigna/Evernorth | K16: =IF($B16="Open","",IFERROR(INDEX('📝 Roster'!$I:$I,MATCH($A16,'📝 Roster'!$B:$B,0)),"")) -> Readmit/Rise | L16: =IF($B16="Open","",IFERROR(INDEX('📝 Roster'!$K:$K,MATCH($A16,'📝 Roster'!$B:$B,0)),"")) -> 0 | M16: =IF($B16="Open","",IFERROR(INDEX('📝 Roster'!$J:$J,MATCH($A16,'📝 Roster'!$B:$B,0)),"")) -> Matthew | N16: =IF($B16="Open","",IFERROR(INDEX('📝 Roster'!$L:$L,MATCH($A16,'📝 Roster'!$B:$B,0)),"")) -> 0 | O16: =IF($B16="Open","",IFERROR(INDEX('📝 Roster'!$M:$M,MATCH($A16,'📝 Roster'!$B:$B,0)),"")) -> 0 | P16: =IFERROR(MATCH($A16,HP_ROOMS,0),99) -> 7 | Q16: =IFERROR(IF(INDEX('📝 Roster'!$N:$N,MATCH($A16,'📝 Roster'!$B:$B,0))=0,"",INDEX('📝 Roster'!$N:$N,MATCH($A16,'📝 Roster'!$B:$B,0))),"")
A17: M3-B | B17: =IF($A17="","",IF(COUNTIF('📝 Roster'!$B:$B,$A17)=0,"Open",IF(IFERROR(INDEX('📝 Roster'!$C:$C,MATCH($A17,'📝 Roster'!$B:$B,0)),"")="","Open",INDEX('📝 Roster'!$C:$C,MATCH($A17,'📝 Roster'!$B:$B,0))))) -> Occupied | C17: =IF($B17="Open","",IFERROR(INDEX('📝 Roster'!$A:$A,MATCH($A17,'📝 Roster'!$B:$B,0)),"")) -> Monica Gamboa | D17: =IF($B17="Open","",IFERROR(INDEX('📝 Roster'!$D:$D,MATCH($A17,'📝 Roster'!$B:$B,0)),"")) -> 46184 | E17: =IF($B17="Open","",IFERROR(INDEX('📝 Roster'!$E:$E,MATCH($A17,'📝 Roster'!$B:$B,0)),"")) -> DTX/RTC | F17: =IF($B17="Open","",IFERROR(INDEX('📝 Roster'!$F:$F,MATCH($A17,'📝 Roster'!$B:$B,0)),"")) -> DTX/RTC | G17: =IF($B17="Open","",IFERROR(INDEX('📝 Roster'!$G:$G,MATCH($A17,'📝 Roster'!$B:$B,0)),"")) -> 10 | H17: =IF($Q17<>"",$Q17,IF(AND($D17<>"",$G17<>""),INT($D17)+$G17,"")) -> 46194 | I17: =IF(H17="","",IF(H17<TODAY(),"PAST ("&INT(TODAY()-H17)&"d ago)",IF(H17=TODAY(),"TODAY",INT(H17-TODAY())))) -> 4 | J17: =IF($B17="Open","",IFERROR(INDEX('📝 Roster'!$H:$H,MATCH($A17,'📝 Roster'!$B:$B,0)),"")) -> Molina CA | K17: =IF($B17="Open","",IFERROR(INDEX('📝 Roster'!$I:$I,MATCH($A17,'📝 Roster'!$B:$B,0)),"")) -> Readmit | L17: =IF($B17="Open","",IFERROR(INDEX('📝 Roster'!$K:$K,MATCH($A17,'📝 Roster'!$B:$B,0)),"")) -> N | M17: =IF($B17="Open","",IFERROR(INDEX('📝 Roster'!$J:$J,MATCH($A17,'📝 Roster'!$B:$B,0)),"")) -> Amy | N17: =IF($B17="Open","",IFERROR(INDEX('📝 Roster'!$L:$L,MATCH($A17,'📝 Roster'!$B:$B,0)),"")) -> 0 | O17: =IF($B17="Open","",IFERROR(INDEX('📝 Roster'!$M:$M,MATCH($A17,'📝 Roster'!$B:$B,0)),"")) -> 0 | P17: =IFERROR(MATCH($A17,HP_ROOMS,0),99) -> 8 | Q17: =IFERROR(IF(INDEX('📝 Roster'!$N:$N,MATCH($A17,'📝 Roster'!$B:$B,0))=0,"",INDEX('📝 Roster'!$N:$N,MATCH($A17,'📝 Roster'!$B:$B,0))),"") -> 46194
A18: B1-A | B18: =IF($A18="","",IF(COUNTIF('📝 Roster'!$B:$B,$A18)=0,"Open",IF(IFERROR(INDEX('📝 Roster'!$C:$C,MATCH($A18,'📝 Roster'!$B:$B,0)),"")="","Open",INDEX('📝 Roster'!$C:$C,MATCH($A18,'📝 Roster'!$B:$B,0))))) -> Occupied | C18: =IF($B18="Open","",IFERROR(INDEX('📝 Roster'!$A:$A,MATCH($A18,'📝 Roster'!$B:$B,0)),"")) -> Bradey Bauer | D18: =IF($B18="Open","",IFERROR(INDEX('📝 Roster'!$D:$D,MATCH($A18,'📝 Roster'!$B:$B,0)),"")) -> 46186 | E18: =IF($B18="Open","",IFERROR(INDEX('📝 Roster'!$E:$E,MATCH($A18,'📝 Roster'!$B:$B,0)),"")) -> DTX/RTC | F18: =IF($B18="Open","",IFERROR(INDEX('📝 Roster'!$F:$F,MATCH($A18,'📝 Roster'!$B:$B,0)),"")) -> DTX/RTC | G18: =IF($B18="Open","",IFERROR(INDEX('📝 Roster'!$G:$G,MATCH($A18,'📝 Roster'!$B:$B,0)),"")) -> 30 | H18: =IF($Q18<>"",$Q18,IF(AND($D18<>"",$G18<>""),INT($D18)+$G18,"")) -> 46216 | I18: =IF(H18="","",IF(H18<TODAY(),"PAST ("&INT(TODAY()-H18)&"d ago)",IF(H18=TODAY(),"TODAY",INT(H18-TODAY())))) -> 26 | J18: =IF($B18="Open","",IFERROR(INDEX('📝 Roster'!$H:$H,MATCH($A18,'📝 Roster'!$B:$B,0)),"")) -> Anthem BC | K18: =IF($B18="Open","",IFERROR(INDEX('📝 Roster'!$I:$I,MATCH($A18,'📝 Roster'!$B:$B,0)),"")) -> 0 | L18: =IF($B18="Open","",IFERROR(INDEX('📝 Roster'!$K:$K,MATCH($A18,'📝 Roster'!$B:$B,0)),"")) -> 0 | M18: =IF($B18="Open","",IFERROR(INDEX('📝 Roster'!$J:$J,MATCH($A18,'📝 Roster'!$B:$B,0)),"")) -> 0 | N18: =IF($B18="Open","",IFERROR(INDEX('📝 Roster'!$L:$L,MATCH($A18,'📝 Roster'!$B:$B,0)),"")) -> 0 | O18: =IF($B18="Open","",IFERROR(INDEX('📝 Roster'!$M:$M,MATCH($A18,'📝 Roster'!$B:$B,0)),"")) -> 0 | P18: =IFERROR(MATCH($A18,HP_ROOMS,0),99) -> 9 | Q18: =IFERROR(IF(INDEX('📝 Roster'!$N:$N,MATCH($A18,'📝 Roster'!$B:$B,0))=0,"",INDEX('📝 Roster'!$N:$N,MATCH($A18,'📝 Roster'!$B:$B,0))),"")
A19: B1-B | B19: =IF($A19="","",IF(COUNTIF('📝 Roster'!$B:$B,$A19)=0,"Open",IF(IFERROR(INDEX('📝 Roster'!$C:$C,MATCH($A19,'📝 Roster'!$B:$B,0)),"")="","Open",INDEX('📝 Roster'!$C:$C,MATCH($A19,'📝 Roster'!$B:$B,0))))) -> Occupied | C19: =IF($B19="Open","",IFERROR(INDEX('📝 Roster'!$A:$A,MATCH($A19,'📝 Roster'!$B:$B,0)),"")) -> Garrett Johnson | D19: =IF($B19="Open","",IFERROR(INDEX('📝 Roster'!$D:$D,MATCH($A19,'📝 Roster'!$B:$B,0)),"")) -> 46186 | E19: =IF($B19="Open","",IFERROR(INDEX('📝 Roster'!$E:$E,MATCH($A19,'📝 Roster'!$B:$B,0)),"")) -> RTC | F19: =IF($B19="Open","",IFERROR(INDEX('📝 Roster'!$F:$F,MATCH($A19,'📝 Roster'!$B:$B,0)),"")) -> RTC | G19: =IF($B19="Open","",IFERROR(INDEX('📝 Roster'!$G:$G,MATCH($A19,'📝 Roster'!$B:$B,0)),"")) -> 30 | H19: =IF($Q19<>"",$Q19,IF(AND($D19<>"",$G19<>""),INT($D19)+$G19,"")) -> 46216 | I19: =IF(H19="","",IF(H19<TODAY(),"PAST ("&INT(TODAY()-H19)&"d ago)",IF(H19=TODAY(),"TODAY",INT(H19-TODAY())))) -> 26 | J19: =IF($B19="Open","",IFERROR(INDEX('📝 Roster'!$H:$H,MATCH($A19,'📝 Roster'!$B:$B,0)),"")) -> UHC | K19: =IF($B19="Open","",IFERROR(INDEX('📝 Roster'!$I:$I,MATCH($A19,'📝 Roster'!$B:$B,0)),"")) -> web | L19: =IF($B19="Open","",IFERROR(INDEX('📝 Roster'!$K:$K,MATCH($A19,'📝 Roster'!$B:$B,0)),"")) -> Y | M19: =IF($B19="Open","",IFERROR(INDEX('📝 Roster'!$J:$J,MATCH($A19,'📝 Roster'!$B:$B,0)),"")) -> Nelson | N19: =IF($B19="Open","",IFERROR(INDEX('📝 Roster'!$L:$L,MATCH($A19,'📝 Roster'!$B:$B,0)),"")) -> 0 | O19: =IF($B19="Open","",IFERROR(INDEX('📝 Roster'!$M:$M,MATCH($A19,'📝 Roster'!$B:$B,0)),"")) -> 0 | P19: =IFERROR(MATCH($A19,HP_ROOMS,0),99) -> 10 | Q19: =IFERROR(IF(INDEX('📝 Roster'!$N:$N,MATCH($A19,'📝 Roster'!$B:$B,0))=0,"",INDEX('📝 Roster'!$N:$N,MATCH($A19,'📝 Roster'!$B:$B,0))),"")
A20: B2-A | B20: =IF($A20="","",IF(COUNTIF('📝 Roster'!$B:$B,$A20)=0,"Open",IF(IFERROR(INDEX('📝 Roster'!$C:$C,MATCH($A20,'📝 Roster'!$B:$B,0)),"")="","Open",INDEX('📝 Roster'!$C:$C,MATCH($A20,'📝 Roster'!$B:$B,0))))) -> Occupied | C20: =IF($B20="Open","",IFERROR(INDEX('📝 Roster'!$A:$A,MATCH($A20,'📝 Roster'!$B:$B,0)),"")) -> Kyle Samia | D20: =IF($B20="Open","",IFERROR(INDEX('📝 Roster'!$D:$D,MATCH($A20,'📝 Roster'!$B:$B,0)),"")) -> 46184 | E20: =IF($B20="Open","",IFERROR(INDEX('📝 Roster'!$E:$E,MATCH($A20,'📝 Roster'!$B:$B,0)),"")) -> DTX/RTC | F20: =IF($B20="Open","",IFERROR(INDEX('📝 Roster'!$F:$F,MATCH($A20,'📝 Roster'!$B:$B,0)),"")) -> DTX/RTC | G20: =IF($B20="Open","",IFERROR(INDEX('📝 Roster'!$G:$G,MATCH($A20,'📝 Roster'!$B:$B,0)),"")) -> 30 | H20: =IF($Q20<>"",$Q20,IF(AND($D20<>"",$G20<>""),INT($D20)+$G20,"")) -> 46214 | I20: =IF(H20="","",IF(H20<TODAY(),"PAST ("&INT(TODAY()-H20)&"d ago)",IF(H20=TODAY(),"TODAY",INT(H20-TODAY())))) -> 24 | J20: =IF($B20="Open","",IFERROR(INDEX('📝 Roster'!$H:$H,MATCH($A20,'📝 Roster'!$B:$B,0)),"")) -> Cigna/Evernorth | K20: =IF($B20="Open","",IFERROR(INDEX('📝 Roster'!$I:$I,MATCH($A20,'📝 Roster'!$B:$B,0)),"")) -> web | L20: =IF($B20="Open","",IFERROR(INDEX('📝 Roster'!$K:$K,MATCH($A20,'📝 Roster'!$B:$B,0)),"")) -> 0 | M20: =IF($B20="Open","",IFERROR(INDEX('📝 Roster'!$J:$J,MATCH($A20,'📝 Roster'!$B:$B,0)),"")) -> Matthew | N20: =IF($B20="Open","",IFERROR(INDEX('📝 Roster'!$L:$L,MATCH($A20,'📝 Roster'!$B:$B,0)),"")) -> 0 | O20: =IF($B20="Open","",IFERROR(INDEX('📝 Roster'!$M:$M,MATCH($A20,'📝 Roster'!$B:$B,0)),"")) -> 0 | P20: =IFERROR(MATCH($A20,HP_ROOMS,0),99) -> 11 | Q20: =IFERROR(IF(INDEX('📝 Roster'!$N:$N,MATCH($A20,'📝 Roster'!$B:$B,0))=0,"",INDEX('📝 Roster'!$N:$N,MATCH($A20,'📝 Roster'!$B:$B,0))),"")
A21: B2-B | B21: =IF($A21="","",IF(COUNTIF('📝 Roster'!$B:$B,$A21)=0,"Open",IF(IFERROR(INDEX('📝 Roster'!$C:$C,MATCH($A21,'📝 Roster'!$B:$B,0)),"")="","Open",INDEX('📝 Roster'!$C:$C,MATCH($A21,'📝 Roster'!$B:$B,0))))) -> Occupied | C21: =IF($B21="Open","",IFERROR(INDEX('📝 Roster'!$A:$A,MATCH($A21,'📝 Roster'!$B:$B,0)),"")) -> Jamal Williams | D21: =IF($B21="Open","",IFERROR(INDEX('📝 Roster'!$D:$D,MATCH($A21,'📝 Roster'!$B:$B,0)),"")) -> 46183 | E21: =IF($B21="Open","",IFERROR(INDEX('📝 Roster'!$E:$E,MATCH($A21,'📝 Roster'!$B:$B,0)),"")) -> DTX/RTC | F21: =IF($B21="Open","",IFERROR(INDEX('📝 Roster'!$F:$F,MATCH($A21,'📝 Roster'!$B:$B,0)),"")) -> DTX/RTC | G21: =IF($B21="Open","",IFERROR(INDEX('📝 Roster'!$G:$G,MATCH($A21,'📝 Roster'!$B:$B,0)),"")) -> 30 | H21: =IF($Q21<>"",$Q21,IF(AND($D21<>"",$G21<>""),INT($D21)+$G21,"")) -> 46213 | I21: =IF(H21="","",IF(H21<TODAY(),"PAST ("&INT(TODAY()-H21)&"d ago)",IF(H21=TODAY(),"TODAY",INT(H21-TODAY())))) -> 23 | J21: =IF($B21="Open","",IFERROR(INDEX('📝 Roster'!$H:$H,MATCH($A21,'📝 Roster'!$B:$B,0)),"")) -> Blue Shield CA | K21: =IF($B21="Open","",IFERROR(INDEX('📝 Roster'!$I:$I,MATCH($A21,'📝 Roster'!$B:$B,0)),"")) -> The Canyon | L21: =IF($B21="Open","",IFERROR(INDEX('📝 Roster'!$K:$K,MATCH($A21,'📝 Roster'!$B:$B,0)),"")) -> 0 | M21: =IF($B21="Open","",IFERROR(INDEX('📝 Roster'!$J:$J,MATCH($A21,'📝 Roster'!$B:$B,0)),"")) -> Ahbra | N21: =IF($B21="Open","",IFERROR(INDEX('📝 Roster'!$L:$L,MATCH($A21,'📝 Roster'!$B:$B,0)),"")) -> 0 | O21: =IF($B21="Open","",IFERROR(INDEX('📝 Roster'!$M:$M,MATCH($A21,'📝 Roster'!$B:$B,0)),"")) -> 0 | P21: =IFERROR(MATCH($A21,HP_ROOMS,0),99) -> 12 | Q21: =IFERROR(IF(INDEX('📝 Roster'!$N:$N,MATCH($A21,'📝 Roster'!$B:$B,0))=0,"",INDEX('📝 Roster'!$N:$N,MATCH($A21,'📝 Roster'!$B:$B,0))),"")
... A23: B3-B | B23: =IF($A23="","",IF(COUNTIF('📝 Roster'!$B:$B,$A23)=0,"Open",IF(IFERROR(INDEX('📝 Roster'!$C:$C,MATCH($A23,'📝 Roster'!$B:$B,0)),"")="","Open",INDEX('📝 Roster'!$C:$C,MATCH($A23,'📝 Roster'!$B:$B,0))))) -> Occupied | C23: =IF($B23="Open","",IFERROR(INDEX('📝 Roster'!$A:$A,MATCH($A23,'📝 Roster'!$B:$B,0)),"")) -> Jason Schnell | D23: =IF($B23="Open","",IFERROR(INDEX('📝 Roster'!$D:$D,MATCH($A23,'📝 Roster'!$B:$B,0)),"")) -> 46164 | E23: =IF($B23="Open","",IFERROR(INDEX('📝 Roster'!$E:$E,MATCH($A23,'📝 Roster'!$B:$B,0)),"")) -> DTX/RTC | F23: =IF($B23="Open","",IFERROR(INDEX('📝 Roster'!$F:$F,MATCH($A23,'📝 Roster'!$B:$B,0)),"")) -> DTX/RTC | G23: =IF($B23="Open","",IFERROR(INDEX('📝 Roster'!$G:$G,MATCH($A23,'📝 Roster'!$B:$B,0)),"")) -> 30 | H23: =IF($Q23<>"",$Q23,IF(AND($D23<>"",$G23<>""),INT($D23)+$G23,"")) -> 46203 | I23: =IF(H23="","",IF(H23<TODAY(),"PAST ("&INT(TODAY()-H23)&"d ago)",IF(H23=TODAY(),"TODAY",INT(H23-TODAY())))) -> 13 | J23: =IF($B23="Open","",IFERROR(INDEX('📝 Roster'!$H:$H,MATCH($A23,'📝 Roster'!$B:$B,0)),"")) -> Blue Shield CA | K23: =IF($B23="Open","",IFERROR(INDEX('📝 Roster'!$I:$I,MATCH($A23,'📝 Roster'!$B:$B,0)),"")) -> Readmit | L23: =IF($B23="Open","",IFERROR(INDEX('📝 Roster'!$K:$K,MATCH($A23,'📝 Roster'!$B:$B,0)),"")) -> N | M23: =IF($B23="Open","",IFERROR(INDEX('📝 Roster'!$J:$J,MATCH($A23,'📝 Roster'!$B:$B,0)),"")) -> Amy | N23: =IF($B23="Open","",IFERROR(INDEX('📝 Roster'!$L:$L,MATCH($A23,'📝 Roster'!$B:$B,0)),"")) -> 0 | O23: =IF($B23="Open","",IFERROR(INDEX('📝 Roster'!$M:$M,MATCH($A23,'📝 Roster'!$B:$B,0)),"")) -> 0 | P23: =IFERROR(MATCH($A23,HP_ROOMS,0),99) -> 14 | Q23: =IFERROR(IF(INDEX('📝 Roster'!$N:$N,MATCH($A23,'📝 Roster'!$B:$B,0))=0,"",INDEX('📝 Roster'!$N:$N,MATCH($A23,'📝 Roster'!$B:$B,0))),"") -> 46203
A26: 📥 SCHEDULED INTAKES
A27: Auto-pulled from Pipeline where Status = Scheduled & Facility = HP
A28: CLIENT | B28: REP | C28: LOC | D28: INSURANCE | E28: INTAKE | F28: VOB
A29: =IFERROR(INDEX('🔥 Pipeline'!$C:$C,MATCH(1,'⚙ Pipeline Engine'!$AC:$AC,0)),"") | B29: =IFERROR(INDEX('🔥 Pipeline'!$B:$B,MATCH(1,'⚙ Pipeline Engine'!$AC:$AC,0)),"") | C29: =IFERROR(INDEX('🔥 Pipeline'!$E:$E,MATCH(1,'⚙ Pipeline Engine'!$AC:$AC,0)),"") | D29: =IFERROR(INDEX('🔥 Pipeline'!$I:$I,MATCH(1,'⚙ Pipeline Engine'!$AC:$AC,0)),"") | E29: =IFERROR(INDEX('🔥 Pipeline'!$H:$H,MATCH(1,'⚙ Pipeline Engine'!$AC:$AC,0)),"") | F29: =IFERROR(INDEX('🔥 Pipeline'!$G:$G,MATCH(1,'⚙ Pipeline Engine'!$AC:$AC,0)),"")
A30: =IFERROR(INDEX('🔥 Pipeline'!$C:$C,MATCH(2,'⚙ Pipeline Engine'!$AC:$AC,0)),"") | B30: =IFERROR(INDEX('🔥 Pipeline'!$B:$B,MATCH(2,'⚙ Pipeline Engine'!$AC:$AC,0)),"") | C30: =IFERROR(INDEX('🔥 Pipeline'!$E:$E,MATCH(2,'⚙ Pipeline Engine'!$AC:$AC,0)),"") | D30: =IFERROR(INDEX('🔥 Pipeline'!$I:$I,MATCH(2,'⚙ Pipeline Engine'!$AC:$AC,0)),"") | E30: =IFERROR(INDEX('🔥 Pipeline'!$H:$H,MATCH(2,'⚙ Pipeline Engine'!$AC:$AC,0)),"") | F30: =IFERROR(INDEX('🔥 Pipeline'!$G:$G,MATCH(2,'⚙ Pipeline Engine'!$AC:$AC,0)),"")
A31: =IFERROR(INDEX('🔥 Pipeline'!$C:$C,MATCH(3,'⚙ Pipeline Engine'!$AC:$AC,0)),"") | B31: =IFERROR(INDEX('🔥 Pipeline'!$B:$B,MATCH(3,'⚙ Pipeline Engine'!$AC:$AC,0)),"") | C31: =IFERROR(INDEX('🔥 Pipeline'!$E:$E,MATCH(3,'⚙ Pipeline Engine'!$AC:$AC,0)),"") | D31: =IFERROR(INDEX('🔥 Pipeline'!$I:$I,MATCH(3,'⚙ Pipeline Engine'!$AC:$AC,0)),"") | E31: =IFERROR(INDEX('🔥 Pipeline'!$H:$H,MATCH(3,'⚙ Pipeline Engine'!$AC:$AC,0)),"") | F31: =IFERROR(INDEX('🔥 Pipeline'!$G:$G,MATCH(3,'⚙ Pipeline Engine'!$AC:$AC,0)),"")
A32: =IFERROR(INDEX('🔥 Pipeline'!$C:$C,MATCH(4,'⚙ Pipeline Engine'!$AC:$AC,0)),"") | B32: =IFERROR(INDEX('🔥 Pipeline'!$B:$B,MATCH(4,'⚙ Pipeline Engine'!$AC:$AC,0)),"") | C32: =IFERROR(INDEX('🔥 Pipeline'!$E:$E,MATCH(4,'⚙ Pipeline Engine'!$AC:$AC,0)),"") | D32: =IFERROR(INDEX('🔥 Pipeline'!$I:$I,MATCH(4,'⚙ Pipeline Engine'!$AC:$AC,0)),"") | E32: =IFERROR(INDEX('🔥 Pipeline'!$H:$H,MATCH(4,'⚙ Pipeline Engine'!$AC:$AC,0)),"") | F32: =IFERROR(INDEX('🔥 Pipeline'!$G:$G,MATCH(4,'⚙ Pipeline Engine'!$AC:$AC,0)),"")
A33: =IFERROR(INDEX('🔥 Pipeline'!$C:$C,MATCH(5,'⚙ Pipeline Engine'!$AC:$AC,0)),"") | B33: =IFERROR(INDEX('🔥 Pipeline'!$B:$B,MATCH(5,'⚙ Pipeline Engine'!$AC:$AC,0)),"") | C33: =IFERROR(INDEX('🔥 Pipeline'!$E:$E,MATCH(5,'⚙ Pipeline Engine'!$AC:$AC,0)),"") | D33: =IFERROR(INDEX('🔥 Pipeline'!$I:$I,MATCH(5,'⚙ Pipeline Engine'!$AC:$AC,0)),"") | E33: =IFERROR(INDEX('🔥 Pipeline'!$H:$H,MATCH(5,'⚙ Pipeline Engine'!$AC:$AC,0)),"") | F33: =IFERROR(INDEX('🔥 Pipeline'!$G:$G,MATCH(5,'⚙ Pipeline Engine'!$AC:$AC,0)),"")
A34: =IFERROR(INDEX('🔥 Pipeline'!$C:$C,MATCH(6,'⚙ Pipeline Engine'!$AC:$AC,0)),"") | B34: =IFERROR(INDEX('🔥 Pipeline'!$B:$B,MATCH(6,'⚙ Pipeline Engine'!$AC:$AC,0)),"") | C34: =IFERROR(INDEX('🔥 Pipeline'!$E:$E,MATCH(6,'⚙ Pipeline Engine'!$AC:$AC,0)),"") | D34: =IFERROR(INDEX('🔥 Pipeline'!$I:$I,MATCH(6,'⚙ Pipeline Engine'!$AC:$AC,0)),"") | E34: =IFERROR(INDEX('🔥 Pipeline'!$H:$H,MATCH(6,'⚙ Pipeline Engine'!$AC:$AC,0)),"") | F34: =IFERROR(INDEX('🔥 Pipeline'!$G:$G,MATCH(6,'⚙ Pipeline Engine'!$AC:$AC,0)),"")

Sheet 🛏 HPE Bed Board
A1: 🛏 HPE Bed Board | 22913/22915 Burbank Blvd (12 beds)
A2: ="Census: "&(COUNTIF(B11:B16,"Occupied")+COUNTIF(B18:B23,"Occupied"))&"/12" -> Census: 9/12 | C2: ="Reserved: "&(COUNTIF(B11:B16,"Reserved")+COUNTIF(B18:B23,"Reserved")) -> Reserved: 1 | E2: ="Open: "&(COUNTIF(B11:B16,"Open")+COUNTIF(B18:B23,"Open")) -> Open: 2 | G2: =TEXT((COUNTIF(B11:B16,"Occupied")+COUNTIF(B18:B23,"Occupied"))/12,"0%")&" capacity" -> 75% capacity | I2: =IFERROR(COUNTIFS(B11:B16,"Occupied",H11:H16,">="&TODAY(),H11:H16,"<="&TODAY()+7)&" DC within 7 days","0 DC within 7 days") -> 2 DC within 7 days
A4: 📝 ALL EDITS HAPPEN ON THE ROSTER TAB — this board updates automatically. 🔎 FILTER: click the ▼ buttons on the header row (e.g. STATUS = Open to find vacancies, or REP to see one rep's beds).
A6: OPEN — available | D6: RESERVED | G6: OCCUPIED | J6: ⚠ FLAGGED — verify
A9: ROOM | B9: STATUS | C9: CLIENT NAME | D9: ADMIT DATE | E9: ADMIT LOC | F9: CURRENT LOC | G9: PLAN LOS | H9: DC DATE | I9: TO DC | J9: FINANCIAL | K9: REFERRAL | L9: CHIRO Y/N | M9: REP | N9: AMA RISK | O9: DC LOC | P9: SORT# | Q9: DC OVERRIDE
A10: ="— HOUSE 1 · 22913 — "&COUNTIF(B11:B16,"Occupied")&"/6 occupied" -> — HOUSE 1 · 22913 — 5/6 occupied
A11: H1-1A | B11: =IF($A11="","",IF(COUNTIF('📝 Roster'!$B:$B,$A11)=0,"Open",IF(IFERROR(INDEX('📝 Roster'!$C:$C,MATCH($A11,'📝 Roster'!$B:$B,0)),"")="","Open",INDEX('📝 Roster'!$C:$C,MATCH($A11,'📝 Roster'!$B:$B,0))))) -> Occupied | C11: =IF($B11="Open","",IFERROR(INDEX('📝 Roster'!$A:$A,MATCH($A11,'📝 Roster'!$B:$B,0)),"")) -> Allisa Leuvrey | D11: =IF($B11="Open","",IFERROR(INDEX('📝 Roster'!$D:$D,MATCH($A11,'📝 Roster'!$B:$B,0)),"")) -> 46185 | E11: =IF($B11="Open","",IFERROR(INDEX('📝 Roster'!$E:$E,MATCH($A11,'📝 Roster'!$B:$B,0)),"")) -> DTX | F11: =IF($B11="Open","",IFERROR(INDEX('📝 Roster'!$F:$F,MATCH($A11,'📝 Roster'!$B:$B,0)),"")) -> DTX | G11: =IF($B11="Open","",IFERROR(INDEX('📝 Roster'!$G:$G,MATCH($A11,'📝 Roster'!$B:$B,0)),"")) -> 7 | H11: =IF($Q11<>"",$Q11,IF(AND($D11<>"",$G11<>""),INT($D11)+$G11,"")) -> 46192 | I11: =IF(H11="","",IF(H11<TODAY(),"PAST ("&INT(TODAY()-H11)&"d ago)",IF(H11=TODAY(),"TODAY",INT(H11-TODAY())))) -> 2 | J11: =IF($B11="Open","",IFERROR(INDEX('📝 Roster'!$H:$H,MATCH($A11,'📝 Roster'!$B:$B,0)),"")) -> Blue Shield CA | K11: =IF($B11="Open","",IFERROR(INDEX('📝 Roster'!$I:$I,MATCH($A11,'📝 Roster'!$B:$B,0)),"")) -> web | L11: =IF($B11="Open","",IFERROR(INDEX('📝 Roster'!$K:$K,MATCH($A11,'📝 Roster'!$B:$B,0)),"")) -> N | M11: =IF($B11="Open","",IFERROR(INDEX('📝 Roster'!$J:$J,MATCH($A11,'📝 Roster'!$B:$B,0)),"")) -> Amy | N11: =IF($B11="Open","",IFERROR(INDEX('📝 Roster'!$L:$L,MATCH($A11,'📝 Roster'!$B:$B,0)),"")) -> 0 | O11: =IF($B11="Open","",IFERROR(INDEX('📝 Roster'!$M:$M,MATCH($A11,'📝 Roster'!$B:$B,0)),"")) -> 0 | P11: =IFERROR(MATCH($A11,HPE_ROOMS,0),99) -> 1 | Q11: =IFERROR(IF(INDEX('📝 Roster'!$N:$N,MATCH($A11,'📝 Roster'!$B:$B,0))=0,"",INDEX('📝 Roster'!$N:$N,MATCH($A11,'📝 Roster'!$B:$B,0))),"")
A12: H1-1B | B12: =IF($A12="","",IF(COUNTIF('📝 Roster'!$B:$B,$A12)=0,"Open",IF(IFERROR(INDEX('📝 Roster'!$C:$C,MATCH($A12,'📝 Roster'!$B:$B,0)),"")="","Open",INDEX('📝 Roster'!$C:$C,MATCH($A12,'📝 Roster'!$B:$B,0))))) -> Occupied | C12: =IF($B12="Open","",IFERROR(INDEX('📝 Roster'!$A:$A,MATCH($A12,'📝 Roster'!$B:$B,0)),"")) -> Cree Lamere | D12: =IF($B12="Open","",IFERROR(INDEX('📝 Roster'!$D:$D,MATCH($A12,'📝 Roster'!$B:$B,0)),"")) -> 46170 | E12: =IF($B12="Open","",IFERROR(INDEX('📝 Roster'!$E:$E,MATCH($A12,'📝 Roster'!$B:$B,0)),"")) -> DTX/RTC | F12: =IF($B12="Open","",IFERROR(INDEX('📝 Roster'!$F:$F,MATCH($A12,'📝 Roster'!$B:$B,0)),"")) -> DTX/RTC | G12: =IF($B12="Open","",IFERROR(INDEX('📝 Roster'!$G:$G,MATCH($A12,'📝 Roster'!$B:$B,0)),"")) -> 30 | H12: =IF($Q12<>"",$Q12,IF(AND($D12<>"",$G12<>""),INT($D12)+$G12,"")) -> 46202 | I12: =IF(H12="","",IF(H12<TODAY(),"PAST ("&INT(TODAY()-H12)&"d ago)",IF(H12=TODAY(),"TODAY",INT(H12-TODAY())))) -> 12 | J12: =IF($B12="Open","",IFERROR(INDEX('📝 Roster'!$H:$H,MATCH($A12,'📝 Roster'!$B:$B,0)),"")) -> Blue Shield CA | K12: =IF($B12="Open","",IFERROR(INDEX('📝 Roster'!$I:$I,MATCH($A12,'📝 Roster'!$B:$B,0)),"")) -> Ahbra/Profound | L12: =IF($B12="Open","",IFERROR(INDEX('📝 Roster'!$K:$K,MATCH($A12,'📝 Roster'!$B:$B,0)),"")) -> N | M12: =IF($B12="Open","",IFERROR(INDEX('📝 Roster'!$J:$J,MATCH($A12,'📝 Roster'!$B:$B,0)),"")) -> Amy | N12: =IF($B12="Open","",IFERROR(INDEX('📝 Roster'!$L:$L,MATCH($A12,'📝 Roster'!$B:$B,0)),"")) -> 0 | O12: =IF($B12="Open","",IFERROR(INDEX('📝 Roster'!$M:$M,MATCH($A12,'📝 Roster'!$B:$B,0)),"")) -> 0 | P12: =IFERROR(MATCH($A12,HPE_ROOMS,0),99) -> 2 | Q12: =IFERROR(IF(INDEX('📝 Roster'!$N:$N,MATCH($A12,'📝 Roster'!$B:$B,0))=0,"",INDEX('📝 Roster'!$N:$N,MATCH($A12,'📝 Roster'!$B:$B,0))),"") -> 46202
A13: H1-2A | B13: =IF($A13="","",IF(COUNTIF('📝 Roster'!$B:$B,$A13)=0,"Open",IF(IFERROR(INDEX('📝 Roster'!$C:$C,MATCH($A13,'📝 Roster'!$B:$B,0)),"")="","Open",INDEX('📝 Roster'!$C:$C,MATCH($A13,'📝 Roster'!$B:$B,0))))) -> Occupied | C13: =IF($B13="Open","",IFERROR(INDEX('📝 Roster'!$A:$A,MATCH($A13,'📝 Roster'!$B:$B,0)),"")) -> Rhonda Baim | D13: =IF($B13="Open","",IFERROR(INDEX('📝 Roster'!$D:$D,MATCH($A13,'📝 Roster'!$B:$B,0)),"")) -> 46166 | E13: =IF($B13="Open","",IFERROR(INDEX('📝 Roster'!$E:$E,MATCH($A13,'📝 Roster'!$B:$B,0)),"")) -> DTX | F13: =IF($B13="Open","",IFERROR(INDEX('📝 Roster'!$F:$F,MATCH($A13,'📝 Roster'!$B:$B,0)),"")) -> DTX | G13: =IF($B13="Open","",IFERROR(INDEX('📝 Roster'!$G:$G,MATCH($A13,'📝 Roster'!$B:$B,0)),"")) -> 30 | H13: =IF($Q13<>"",$Q13,IF(AND($D13<>"",$G13<>""),INT($D13)+$G13,"")) -> 46196 | I13: =IF(H13="","",IF(H13<TODAY(),"PAST ("&INT(TODAY()-H13)&"d ago)",IF(H13=TODAY(),"TODAY",INT(H13-TODAY())))) -> 6 | J13: =IF($B13="Open","",IFERROR(INDEX('📝 Roster'!$H:$H,MATCH($A13,'📝 Roster'!$B:$B,0)),"")) -> Anthem BC | K13: =IF($B13="Open","",IFERROR(INDEX('📝 Roster'!$I:$I,MATCH($A13,'📝 Roster'!$B:$B,0)),"")) -> Web | L13: =IF($B13="Open","",IFERROR(INDEX('📝 Roster'!$K:$K,MATCH($A13,'📝 Roster'!$B:$B,0)),"")) -> N | M13: =IF($B13="Open","",IFERROR(INDEX('📝 Roster'!$J:$J,MATCH($A13,'📝 Roster'!$B:$B,0)),"")) -> Nelson | N13: =IF($B13="Open","",IFERROR(INDEX('📝 Roster'!$L:$L,MATCH($A13,'📝 Roster'!$B:$B,0)),"")) -> 0 | O13: =IF($B13="Open","",IFERROR(INDEX('📝 Roster'!$M:$M,MATCH($A13,'📝 Roster'!$B:$B,0)),"")) -> 0 | P13: =IFERROR(MATCH($A13,HPE_ROOMS,0),99) -> 3 | Q13: =IFERROR(IF(INDEX('📝 Roster'!$N:$N,MATCH($A13,'📝 Roster'!$B:$B,0))=0,"",INDEX('📝 Roster'!$N:$N,MATCH($A13,'📝 Roster'!$B:$B,0))),"")
A14: H1-3A | B14: =IF($A14="","",IF(COUNTIF('📝 Roster'!$B:$B,$A14)=0,"Open",IF(IFERROR(INDEX('📝 Roster'!$C:$C,MATCH($A14,'📝 Roster'!$B:$B,0)),"")="","Open",INDEX('📝 Roster'!$C:$C,MATCH($A14,'📝 Roster'!$B:$B,0))))) -> Occupied | C14: =IF($B14="Open","",IFERROR(INDEX('📝 Roster'!$A:$A,MATCH($A14,'📝 Roster'!$B:$B,0)),"")) -> Aaron Dufresne | D14: =IF($B14="Open","",IFERROR(INDEX('📝 Roster'!$D:$D,MATCH($A14,'📝 Roster'!$B:$B,0)),"")) -> 46171 | E14: =IF($B14="Open","",IFERROR(INDEX('📝 Roster'!$E:$E,MATCH($A14,'📝 Roster'!$B:$B,0)),"")) -> DTX | F14: =IF($B14="Open","",IFERROR(INDEX('📝 Roster'!$F:$F,MATCH($A14,'📝 Roster'!$B:$B,0)),"")) -> DTX | G14: =IF($B14="Open","",IFERROR(INDEX('📝 Roster'!$G:$G,MATCH($A14,'📝 Roster'!$B:$B,0)),"")) -> 30 | H14: =IF($Q14<>"",$Q14,IF(AND($D14<>"",$G14<>""),INT($D14)+$G14,"")) -> 46201 | I14: =IF(H14="","",IF(H14<TODAY(),"PAST ("&INT(TODAY()-H14)&"d ago)",IF(H14=TODAY(),"TODAY",INT(H14-TODAY())))) -> 11 | J14: =IF($B14="Open","",IFERROR(INDEX('📝 Roster'!$H:$H,MATCH($A14,'📝 Roster'!$B:$B,0)),"")) -> UMR/UHC | K14: =IF($B14="Open","",IFERROR(INDEX('📝 Roster'!$I:$I,MATCH($A14,'📝 Roster'!$B:$B,0)),"")) -> Ahbra/Action IOP | L14: =IF($B14="Open","",IFERROR(INDEX('📝 Roster'!$K:$K,MATCH($A14,'📝 Roster'!$B:$B,0)),"")) -> N | M14: =IF($B14="Open","",IFERROR(INDEX('📝 Roster'!$J:$J,MATCH($A14,'📝 Roster'!$B:$B,0)),"")) -> Nelson | N14: =IF($B14="Open","",IFERROR(INDEX('📝 Roster'!$L:$L,MATCH($A14,'📝 Roster'!$B:$B,0)),"")) -> 0 | O14: =IF($B14="Open","",IFERROR(INDEX('📝 Roster'!$M:$M,MATCH($A14,'📝 Roster'!$B:$B,0)),"")) -> 0 | P14: =IFERROR(MATCH($A14,HPE_ROOMS,0),99) -> 4 | Q14: =IFERROR(IF(INDEX('📝 Roster'!$N:$N,MATCH($A14,'📝 Roster'!$B:$B,0))=0,"",INDEX('📝 Roster'!$N:$N,MATCH($A14,'📝 Roster'!$B:$B,0))),"")
A15: H1-3B | B15: =IF($A15="","",IF(COUNTIF('📝 Roster'!$B:$B,$A15)=0,"Open",IF(IFERROR(INDEX('📝 Roster'!$C:$C,MATCH($A15,'📝 Roster'!$B:$B,0)),"")="","Open",INDEX('📝 Roster'!$C:$C,MATCH($A15,'📝 Roster'!$B:$B,0))))) -> Open | C15: =IF($B15="Open","",IFERROR(INDEX('📝 Roster'!$A:$A,MATCH($A15,'📝 Roster'!$B:$B,0)),"")) | D15: =IF($B15="Open","",IFERROR(INDEX('📝 Roster'!$D:$D,MATCH($A15,'📝 Roster'!$B:$B,0)),"")) | E15: =IF($B15="Open","",IFERROR(INDEX('📝 Roster'!$E:$E,MATCH($A15,'📝 Roster'!$B:$B,0)),"")) | F15: =IF($B15="Open","",IFERROR(INDEX('📝 Roster'!$F:$F,MATCH($A15,'📝 Roster'!$B:$B,0)),"")) | G15: =IF($B15="Open","",IFERROR(INDEX('📝 Roster'!$G:$G,MATCH($A15,'📝 Roster'!$B:$B,0)),"")) | H15: =IF($Q15<>"",$Q15,IF(AND($D15<>"",$G15<>""),INT($D15)+$G15,"")) | I15: =IF(H15="","",IF(H15<TODAY(),"PAST ("&INT(TODAY()-H15)&"d ago)",IF(H15=TODAY(),"TODAY",INT(H15-TODAY())))) | J15: =IF($B15="Open","",IFERROR(INDEX('📝 Roster'!$H:$H,MATCH($A15,'📝 Roster'!$B:$B,0)),"")) | K15: =IF($B15="Open","",IFERROR(INDEX('📝 Roster'!$I:$I,MATCH($A15,'📝 Roster'!$B:$B,0)),"")) | L15: =IF($B15="Open","",IFERROR(INDEX('📝 Roster'!$K:$K,MATCH($A15,'📝 Roster'!$B:$B,0)),"")) | M15: =IF($B15="Open","",IFERROR(INDEX('📝 Roster'!$J:$J,MATCH($A15,'📝 Roster'!$B:$B,0)),"")) | N15: =IF($B15="Open","",IFERROR(INDEX('📝 Roster'!$L:$L,MATCH($A15,'📝 Roster'!$B:$B,0)),"")) | O15: =IF($B15="Open","",IFERROR(INDEX('📝 Roster'!$M:$M,MATCH($A15,'📝 Roster'!$B:$B,0)),"")) | P15: =IFERROR(MATCH($A15,HPE_ROOMS,0),99) -> 5 | Q15: =IFERROR(IF(INDEX('📝 Roster'!$N:$N,MATCH($A15,'📝 Roster'!$B:$B,0))=0,"",INDEX('📝 Roster'!$N:$N,MATCH($A15,'📝 Roster'!$B:$B,0))),"")
A16: H1-4 | B16: =IF($A16="","",IF(COUNTIF('📝 Roster'!$B:$B,$A16)=0,"Open",IF(IFERROR(INDEX('📝 Roster'!$C:$C,MATCH($A16,'📝 Roster'!$B:$B,0)),"")="","Open",INDEX('📝 Roster'!$C:$C,MATCH($A16,'📝 Roster'!$B:$B,0))))) -> Occupied | C16: =IF($B16="Open","",IFERROR(INDEX('📝 Roster'!$A:$A,MATCH($A16,'📝 Roster'!$B:$B,0)),"")) -> Jared Hamilton | D16: =IF($B16="Open","",IFERROR(INDEX('📝 Roster'!$D:$D,MATCH($A16,'📝 Roster'!$B:$B,0)),"")) -> 46175 | E16: =IF($B16="Open","",IFERROR(INDEX('📝 Roster'!$E:$E,MATCH($A16,'📝 Roster'!$B:$B,0)),"")) -> DTX/RTC | F16: =IF($B16="Open","",IFERROR(INDEX('📝 Roster'!$F:$F,MATCH($A16,'📝 Roster'!$B:$B,0)),"")) -> DTX/RTC | G16: =IF($B16="Open","",IFERROR(INDEX('📝 Roster'!$G:$G,MATCH($A16,'📝 Roster'!$B:$B,0)),"")) -> 30 | H16: =IF($Q16<>"",$Q16,IF(AND($D16<>"",$G16<>""),INT($D16)+$G16,"")) -> 46205 | I16: =IF(H16="","",IF(H16<TODAY(),"PAST ("&INT(TODAY()-H16)&"d ago)",IF(H16=TODAY(),"TODAY",INT(H16-TODAY())))) -> 15 | J16: =IF($B16="Open","",IFERROR(INDEX('📝 Roster'!$H:$H,MATCH($A16,'📝 Roster'!$B:$B,0)),"")) -> Blue Shield PPO | K16: =IF($B16="Open","",IFERROR(INDEX('📝 Roster'!$I:$I,MATCH($A16,'📝 Roster'!$B:$B,0)),"")) -> Rise | L16: =IF($B16="Open","",IFERROR(INDEX('📝 Roster'!$K:$K,MATCH($A16,'📝 Roster'!$B:$B,0)),"")) -> N | M16: =IF($B16="Open","",IFERROR(INDEX('📝 Roster'!$J:$J,MATCH($A16,'📝 Roster'!$B:$B,0)),"")) -> Amy | N16: =IF($B16="Open","",IFERROR(INDEX('📝 Roster'!$L:$L,MATCH($A16,'📝 Roster'!$B:$B,0)),"")) -> 0 | O16: =IF($B16="Open","",IFERROR(INDEX('📝 Roster'!$M:$M,MATCH($A16,'📝 Roster'!$B:$B,0)),"")) -> 0 | P16: =IFERROR(MATCH($A16,HPE_ROOMS,0),99) -> 6 | Q16: =IFERROR(IF(INDEX('📝 Roster'!$N:$N,MATCH($A16,'📝 Roster'!$B:$B,0))=0,"",INDEX('📝 Roster'!$N:$N,MATCH($A16,'📝 Roster'!$B:$B,0))),"")
A17: ="— HOUSE 2 · 22915 — "&COUNTIF(B18:B23,"Occupied")&"/6 occupied" -> — HOUSE 2 · 22915 — 4/6 occupied
A18: H2-2A | B18: =IF($A18="","",IF(COUNTIF('📝 Roster'!$B:$B,$A18)=0,"Open",IF(IFERROR(INDEX('📝 Roster'!$C:$C,MATCH($A18,'📝 Roster'!$B:$B,0)),"")="","Open",INDEX('📝 Roster'!$C:$C,MATCH($A18,'📝 Roster'!$B:$B,0))))) -> Reserved | C18: =IF($B18="Open","",IFERROR(INDEX('📝 Roster'!$A:$A,MATCH($A18,'📝 Roster'!$B:$B,0)),"")) -> Tara Shinde | D18: =IF($B18="Open","",IFERROR(INDEX('📝 Roster'!$D:$D,MATCH($A18,'📝 Roster'!$B:$B,0)),"")) -> 46192 | E18: =IF($B18="Open","",IFERROR(INDEX('📝 Roster'!$E:$E,MATCH($A18,'📝 Roster'!$B:$B,0)),"")) -> DTX/RTC | F18: =IF($B18="Open","",IFERROR(INDEX('📝 Roster'!$F:$F,MATCH($A18,'📝 Roster'!$B:$B,0)),"")) -> 0 | G18: =IF($B18="Open","",IFERROR(INDEX('📝 Roster'!$G:$G,MATCH($A18,'📝 Roster'!$B:$B,0)),"")) -> 30 | H18: =IF($Q18<>"",$Q18,IF(AND($D18<>"",$G18<>""),INT($D18)+$G18,"")) -> 46222 | I18: =IF(H18="","",IF(H18<TODAY(),"PAST ("&INT(TODAY()-H18)&"d ago)",IF(H18=TODAY(),"TODAY",INT(H18-TODAY())))) -> 32 | J18: =IF($B18="Open","",IFERROR(INDEX('📝 Roster'!$H:$H,MATCH($A18,'📝 Roster'!$B:$B,0)),"")) -> BCBS IL | K18: =IF($B18="Open","",IFERROR(INDEX('📝 Roster'!$I:$I,MATCH($A18,'📝 Roster'!$B:$B,0)),"")) -> web | L18: =IF($B18="Open","",IFERROR(INDEX('📝 Roster'!$K:$K,MATCH($A18,'📝 Roster'!$B:$B,0)),"")) -> 0 | M18: =IF($B18="Open","",IFERROR(INDEX('📝 Roster'!$J:$J,MATCH($A18,'📝 Roster'!$B:$B,0)),"")) -> Amy | N18: =IF($B18="Open","",IFERROR(INDEX('📝 Roster'!$L:$L,MATCH($A18,'📝 Roster'!$B:$B,0)),"")) -> 0 | O18: =IF($B18="Open","",IFERROR(INDEX('📝 Roster'!$M:$M,MATCH($A18,'📝 Roster'!$B:$B,0)),"")) -> 0 | P18: =IFERROR(MATCH($A18,HPE_ROOMS,0),99) -> 7 | Q18: =IFERROR(IF(INDEX('📝 Roster'!$N:$N,MATCH($A18,'📝 Roster'!$B:$B,0))=0,"",INDEX('📝 Roster'!$N:$N,MATCH($A18,'📝 Roster'!$B:$B,0))),"")
A19: H2-2B | B19: =IF($A19="","",IF(COUNTIF('📝 Roster'!$B:$B,$A19)=0,"Open",IF(IFERROR(INDEX('📝 Roster'!$C:$C,MATCH($A19,'📝 Roster'!$B:$B,0)),"")="","Open",INDEX('📝 Roster'!$C:$C,MATCH($A19,'📝 Roster'!$B:$B,0))))) -> Open | C19: =IF($B19="Open","",IFERROR(INDEX('📝 Roster'!$A:$A,MATCH($A19,'📝 Roster'!$B:$B,0)),"")) | D19: =IF($B19="Open","",IFERROR(INDEX('📝 Roster'!$D:$D,MATCH($A19,'📝 Roster'!$B:$B,0)),"")) | E19: =IF($B19="Open","",IFERROR(INDEX('📝 Roster'!$E:$E,MATCH($A19,'📝 Roster'!$B:$B,0)),"")) | F19: =IF($B19="Open","",IFERROR(INDEX('📝 Roster'!$F:$F,MATCH($A19,'📝 Roster'!$B:$B,0)),"")) | G19: =IF($B19="Open","",IFERROR(INDEX('📝 Roster'!$G:$G,MATCH($A19,'📝 Roster'!$B:$B,0)),"")) | H19: =IF($Q19<>"",$Q19,IF(AND($D19<>"",$G19<>""),INT($D19)+$G19,"")) | I19: =IF(H19="","",IF(H19<TODAY(),"PAST ("&INT(TODAY()-H19)&"d ago)",IF(H19=TODAY(),"TODAY",INT(H19-TODAY())))) | J19: =IF($B19="Open","",IFERROR(INDEX('📝 Roster'!$H:$H,MATCH($A19,'📝 Roster'!$B:$B,0)),"")) | K19: =IF($B19="Open","",IFERROR(INDEX('📝 Roster'!$I:$I,MATCH($A19,'📝 Roster'!$B:$B,0)),"")) | L19: =IF($B19="Open","",IFERROR(INDEX('📝 Roster'!$K:$K,MATCH($A19,'📝 Roster'!$B:$B,0)),"")) | M19: =IF($B19="Open","",IFERROR(INDEX('📝 Roster'!$J:$J,MATCH($A19,'📝 Roster'!$B:$B,0)),"")) | N19: =IF($B19="Open","",IFERROR(INDEX('📝 Roster'!$L:$L,MATCH($A19,'📝 Roster'!$B:$B,0)),"")) | O19: =IF($B19="Open","",IFERROR(INDEX('📝 Roster'!$M:$M,MATCH($A19,'📝 Roster'!$B:$B,0)),"")) | P19: =IFERROR(MATCH($A19,HPE_ROOMS,0),99) -> 8 | Q19: =IFERROR(IF(INDEX('📝 Roster'!$N:$N,MATCH($A19,'📝 Roster'!$B:$B,0))=0,"",INDEX('📝 Roster'!$N:$N,MATCH($A19,'📝 Roster'!$B:$B,0))),"")
A20: H2-3A | B20: =IF($A20="","",IF(COUNTIF('📝 Roster'!$B:$B,$A20)=0,"Open",IF(IFERROR(INDEX('📝 Roster'!$C:$C,MATCH($A20,'📝 Roster'!$B:$B,0)),"")="","Open",INDEX('📝 Roster'!$C:$C,MATCH($A20,'📝 Roster'!$B:$B,0))))) -> Occupied | C20: =IF($B20="Open","",IFERROR(INDEX('📝 Roster'!$A:$A,MATCH($A20,'📝 Roster'!$B:$B,0)),"")) -> Daniel Armiger | D20: =IF($B20="Open","",IFERROR(INDEX('📝 Roster'!$D:$D,MATCH($A20,'📝 Roster'!$B:$B,0)),"")) -> 46182 | E20: =IF($B20="Open","",IFERROR(INDEX('📝 Roster'!$E:$E,MATCH($A20,'📝 Roster'!$B:$B,0)),"")) -> DTX/RTC | F20: =IF($B20="Open","",IFERROR(INDEX('📝 Roster'!$F:$F,MATCH($A20,'📝 Roster'!$B:$B,0)),"")) -> RTC | G20: =IF($B20="Open","",IFERROR(INDEX('📝 Roster'!$G:$G,MATCH($A20,'📝 Roster'!$B:$B,0)),"")) -> 30 | H20: =IF($Q20<>"",$Q20,IF(AND($D20<>"",$G20<>""),INT($D20)+$G20,"")) -> 46212 | I20: =IF(H20="","",IF(H20<TODAY(),"PAST ("&INT(TODAY()-H20)&"d ago)",IF(H20=TODAY(),"TODAY",INT(H20-TODAY())))) -> 22 | J20: =IF($B20="Open","",IFERROR(INDEX('📝 Roster'!$H:$H,MATCH($A20,'📝 Roster'!$B:$B,0)),"")) -> Blue Shield CA | K20: =IF($B20="Open","",IFERROR(INDEX('📝 Roster'!$I:$I,MATCH($A20,'📝 Roster'!$B:$B,0)),"")) -> Readmit | L20: =IF($B20="Open","",IFERROR(INDEX('📝 Roster'!$K:$K,MATCH($A20,'📝 Roster'!$B:$B,0)),"")) -> 0 | M20: =IF($B20="Open","",IFERROR(INDEX('📝 Roster'!$J:$J,MATCH($A20,'📝 Roster'!$B:$B,0)),"")) -> Matthew | N20: =IF($B20="Open","",IFERROR(INDEX('📝 Roster'!$L:$L,MATCH($A20,'📝 Roster'!$B:$B,0)),"")) -> 0 | O20: =IF($B20="Open","",IFERROR(INDEX('📝 Roster'!$M:$M,MATCH($A20,'📝 Roster'!$B:$B,0)),"")) -> 0 | P20: =IFERROR(MATCH($A20,HPE_ROOMS,0),99) -> 9 | Q20: =IFERROR(IF(INDEX('📝 Roster'!$N:$N,MATCH($A20,'📝 Roster'!$B:$B,0))=0,"",INDEX('📝 Roster'!$N:$N,MATCH($A20,'📝 Roster'!$B:$B,0))),"")
A21: H2-3B | B21: =IF($A21="","",IF(COUNTIF('📝 Roster'!$B:$B,$A21)=0,"Open",IF(IFERROR(INDEX('📝 Roster'!$C:$C,MATCH($A21,'📝 Roster'!$B:$B,0)),"")="","Open",INDEX('📝 Roster'!$C:$C,MATCH($A21,'📝 Roster'!$B:$B,0))))) -> Occupied | C21: =IF($B21="Open","",IFERROR(INDEX('📝 Roster'!$A:$A,MATCH($A21,'📝 Roster'!$B:$B,0)),"")) -> Blayne Olivier | D21: =IF($B21="Open","",IFERROR(INDEX('📝 Roster'!$D:$D,MATCH($A21,'📝 Roster'!$B:$B,0)),"")) -> 46186 | E21: =IF($B21="Open","",IFERROR(INDEX('📝 Roster'!$E:$E,MATCH($A21,'📝 Roster'!$B:$B,0)),"")) -> DTX/RTC | F21: =IF($B21="Open","",IFERROR(INDEX('📝 Roster'!$F:$F,MATCH($A21,'📝 Roster'!$B:$B,0)),"")) -> 0 | G21: =IF($B21="Open","",IFERROR(INDEX('📝 Roster'!$G:$G,MATCH($A21,'📝 Roster'!$B:$B,0)),"")) -> 30 | H21: =IF($Q21<>"",$Q21,IF(AND($D21<>"",$G21<>""),INT($D21)+$G21,"")) -> 46216 | I21: =IF(H21="","",IF(H21<TODAY(),"PAST ("&INT(TODAY()-H21)&"d ago)",IF(H21=TODAY(),"TODAY",INT(H21-TODAY())))) -> 26 | J21: =IF($B21="Open","",IFERROR(INDEX('📝 Roster'!$H:$H,MATCH($A21,'📝 Roster'!$B:$B,0)),"")) -> Molina | K21: =IF($B21="Open","",IFERROR(INDEX('📝 Roster'!$I:$I,MATCH($A21,'📝 Roster'!$B:$B,0)),"")) -> Readmit | L21: =IF($B21="Open","",IFERROR(INDEX('📝 Roster'!$K:$K,MATCH($A21,'📝 Roster'!$B:$B,0)),"")) -> N | M21: =IF($B21="Open","",IFERROR(INDEX('📝 Roster'!$J:$J,MATCH($A21,'📝 Roster'!$B:$B,0)),"")) -> Amy | N21: =IF($B21="Open","",IFERROR(INDEX('📝 Roster'!$L:$L,MATCH($A21,'📝 Roster'!$B:$B,0)),"")) -> 0 | O21: =IF($B21="Open","",IFERROR(INDEX('📝 Roster'!$M:$M,MATCH($A21,'📝 Roster'!$B:$B,0)),"")) -> 0 | P21: =IFERROR(MATCH($A21,HPE_ROOMS,0),99) -> 10 | Q21: =IFERROR(IF(INDEX('📝 Roster'!$N:$N,MATCH($A21,'📝 Roster'!$B:$B,0))=0,"",INDEX('📝 Roster'!$N:$N,MATCH($A21,'📝 Roster'!$B:$B,0))),"")
A22: H2-3C | B22: =IF($A22="","",IF(COUNTIF('📝 Roster'!$B:$B,$A22)=0,"Open",IF(IFERROR(INDEX('📝 Roster'!$C:$C,MATCH($A22,'📝 Roster'!$B:$B,0)),"")="","Open",INDEX('📝 Roster'!$C:$C,MATCH($A22,'📝 Roster'!$B:$B,0))))) -> Occupied | C22: =IF($B22="Open","",IFERROR(INDEX('📝 Roster'!$A:$A,MATCH($A22,'📝 Roster'!$B:$B,0)),"")) -> Bradey Bauer | D22: =IF($B22="Open","",IFERROR(INDEX('📝 Roster'!$D:$D,MATCH($A22,'📝 Roster'!$B:$B,0)),"")) -> 46186 | E22: =IF($B22="Open","",IFERROR(INDEX('📝 Roster'!$E:$E,MATCH($A22,'📝 Roster'!$B:$B,0)),"")) -> DTX/RTC | F22: =IF($B22="Open","",IFERROR(INDEX('📝 Roster'!$F:$F,MATCH($A22,'📝 Roster'!$B:$B,0)),"")) -> 0 | G22: =IF($B22="Open","",IFERROR(INDEX('📝 Roster'!$G:$G,MATCH($A22,'📝 Roster'!$B:$B,0)),"")) -> 30 | H22: =IF($Q22<>"",$Q22,IF(AND($D22<>"",$G22<>""),INT($D22)+$G22,"")) -> 46216 | I22: =IF(H22="","",IF(H22<TODAY(),"PAST ("&INT(TODAY()-H22)&"d ago)",IF(H22=TODAY(),"TODAY",INT(H22-TODAY())))) -> 26 | J22: =IF($B22="Open","",IFERROR(INDEX('📝 Roster'!$H:$H,MATCH($A22,'📝 Roster'!$B:$B,0)),"")) -> Anthem BC | K22: =IF($B22="Open","",IFERROR(INDEX('📝 Roster'!$I:$I,MATCH($A22,'📝 Roster'!$B:$B,0)),"")) -> Readmit/Rise | L22: =IF($B22="Open","",IFERROR(INDEX('📝 Roster'!$K:$K,MATCH($A22,'📝 Roster'!$B:$B,0)),"")) -> y | M22: =IF($B22="Open","",IFERROR(INDEX('📝 Roster'!$J:$J,MATCH($A22,'📝 Roster'!$B:$B,0)),"")) -> Matthew | N22: =IF($B22="Open","",IFERROR(INDEX('📝 Roster'!$L:$L,MATCH($A22,'📝 Roster'!$B:$B,0)),"")) -> 0 | O22: =IF($B22="Open","",IFERROR(INDEX('📝 Roster'!$M:$M,MATCH($A22,'📝 Roster'!$B:$B,0)),"")) -> 0 | P22: =IFERROR(MATCH($A22,HPE_ROOMS,0),99) -> 11 | Q22: =IFERROR(IF(INDEX('📝 Roster'!$N:$N,MATCH($A22,'📝 Roster'!$B:$B,0))=0,"",INDEX('📝 Roster'!$N:$N,MATCH($A22,'📝 Roster'!$B:$B,0))),"")
A23: H2-4 | B23: =IF($A23="","",IF(COUNTIF('📝 Roster'!$B:$B,$A23)=0,"Open",IF(IFERROR(INDEX('📝 Roster'!$C:$C,MATCH($A23,'📝 Roster'!$B:$B,0)),"")="","Open",INDEX('📝 Roster'!$C:$C,MATCH($A23,'📝 Roster'!$B:$B,0))))) -> Occupied | C23: =IF($B23="Open","",IFERROR(INDEX('📝 Roster'!$A:$A,MATCH($A23,'📝 Roster'!$B:$B,0)),"")) -> Jeongwoon Lee | D23: =IF($B23="Open","",IFERROR(INDEX('📝 Roster'!$D:$D,MATCH($A23,'📝 Roster'!$B:$B,0)),"")) -> 46167 | E23: =IF($B23="Open","",IFERROR(INDEX('📝 Roster'!$E:$E,MATCH($A23,'📝 Roster'!$B:$B,0)),"")) -> RTC | F23: =IF($B23="Open","",IFERROR(INDEX('📝 Roster'!$F:$F,MATCH($A23,'📝 Roster'!$B:$B,0)),"")) -> RTC | G23: =IF($B23="Open","",IFERROR(INDEX('📝 Roster'!$G:$G,MATCH($A23,'📝 Roster'!$B:$B,0)),"")) -> 30 | H23: =IF($Q23<>"",$Q23,IF(AND($D23<>"",$G23<>""),INT($D23)+$G23,"")) -> 46199 | I23: =IF(H23="","",IF(H23<TODAY(),"PAST ("&INT(TODAY()-H23)&"d ago)",IF(H23=TODAY(),"TODAY",INT(H23-TODAY())))) -> 9 | J23: =IF($B23="Open","",IFERROR(INDEX('📝 Roster'!$H:$H,MATCH($A23,'📝 Roster'!$B:$B,0)),"")) -> Aetna | K23: =IF($B23="Open","",IFERROR(INDEX('📝 Roster'!$I:$I,MATCH($A23,'📝 Roster'!$B:$B,0)),"")) -> Web | L23: =IF($B23="Open","",IFERROR(INDEX('📝 Roster'!$K:$K,MATCH($A23,'📝 Roster'!$B:$B,0)),"")) -> Y | M23: =IF($B23="Open","",IFERROR(INDEX('📝 Roster'!$J:$J,MATCH($A23,'📝 Roster'!$B:$B,0)),"")) -> Nelson | N23: =IF($B23="Open","",IFERROR(INDEX('📝 Roster'!$L:$L,MATCH($A23,'📝 Roster'!$B:$B,0)),"")) -> 0 | O23: =IF($B23="Open","",IFERROR(INDEX('📝 Roster'!$M:$M,MATCH($A23,'📝 Roster'!$B:$B,0)),"")) -> 0 | P23: =IFERROR(MATCH($A23,HPE_ROOMS,0),99) -> 12 | Q23: =IFERROR(IF(INDEX('📝 Roster'!$N:$N,MATCH($A23,'📝 Roster'!$B:$B,0))=0,"",INDEX('📝 Roster'!$N:$N,MATCH($A23,'📝 Roster'!$B:$B,0))),"") -> 46199
A26: 📥 SCHEDULED INTAKES
A27: Auto-pulled from Pipeline where Status = Scheduled & Facility = HPE
A28: CLIENT | B28: REP | C28: LOC | D28: INSURANCE | E28: INTAKE | F28: VOB
A29: =IFERROR(INDEX('🔥 Pipeline'!$C:$C,MATCH(1,'⚙ Pipeline Engine'!$AD:$AD,0)),"") -> Tara Shinde | B29: =IFERROR(INDEX('🔥 Pipeline'!$B:$B,MATCH(1,'⚙ Pipeline Engine'!$AD:$AD,0)),"") -> Amy | C29: =IFERROR(INDEX('🔥 Pipeline'!$E:$E,MATCH(1,'⚙ Pipeline Engine'!$AD:$AD,0)),"") -> DTX/RTC | D29: =IFERROR(INDEX('🔥 Pipeline'!$I:$I,MATCH(1,'⚙ Pipeline Engine'!$AD:$AD,0)),"") -> BCBS IL | E29: =IFERROR(INDEX('🔥 Pipeline'!$H:$H,MATCH(1,'⚙ Pipeline Engine'!$AD:$AD,0)),"") -> 46192 | F29: =IFERROR(INDEX('🔥 Pipeline'!$G:$G,MATCH(1,'⚙ Pipeline Engine'!$AD:$AD,0)),"") -> ✓
A30: =IFERROR(INDEX('🔥 Pipeline'!$C:$C,MATCH(2,'⚙ Pipeline Engine'!$AD:$AD,0)),"") | B30: =IFERROR(INDEX('🔥 Pipeline'!$B:$B,MATCH(2,'⚙ Pipeline Engine'!$AD:$AD,0)),"") | C30: =IFERROR(INDEX('🔥 Pipeline'!$E:$E,MATCH(2,'⚙ Pipeline Engine'!$AD:$AD,0)),"") | D30: =IFERROR(INDEX('🔥 Pipeline'!$I:$I,MATCH(2,'⚙ Pipeline Engine'!$AD:$AD,0)),"") | E30: =IFERROR(INDEX('🔥 Pipeline'!$H:$H,MATCH(2,'⚙ Pipeline Engine'!$AD:$AD,0)),"") | F30: =IFERROR(INDEX('🔥 Pipeline'!$G:$G,MATCH(2,'⚙ Pipeline Engine'!$AD:$AD,0)),"")
A31: =IFERROR(INDEX('🔥 Pipeline'!$C:$C,MATCH(3,'⚙ Pipeline Engine'!$AD:$AD,0)),"") | B31: =IFERROR(INDEX('🔥 Pipeline'!$B:$B,MATCH(3,'⚙ Pipeline Engine'!$AD:$AD,0)),"") | C31: =IFERROR(INDEX('🔥 Pipeline'!$E:$E,MATCH(3,'⚙ Pipeline Engine'!$AD:$AD,0)),"") | D31: =IFERROR(INDEX('🔥 Pipeline'!$I:$I,MATCH(3,'⚙ Pipeline Engine'!$AD:$AD,0)),"") | E31: =IFERROR(INDEX('🔥 Pipeline'!$H:$H,MATCH(3,'⚙ Pipeline Engine'!$AD:$AD,0)),"") | F31: =IFERROR(INDEX('🔥 Pipeline'!$G:$G,MATCH(3,'⚙ Pipeline Engine'!$AD:$AD,0)),"")
A32: =IFERROR(INDEX('🔥 Pipeline'!$C:$C,MATCH(4,'⚙ Pipeline Engine'!$AD:$AD,0)),"") | B32: =IFERROR(INDEX('🔥 Pipeline'!$B:$B,MATCH(4,'⚙ Pipeline Engine'!$AD:$AD,0)),"") | C32: =IFERROR(INDEX('🔥 Pipeline'!$E:$E,MATCH(4,'⚙ Pipeline Engine'!$AD:$AD,0)),"") | D32: =IFERROR(INDEX('🔥 Pipeline'!$I:$I,MATCH(4,'⚙ Pipeline Engine'!$AD:$AD,0)),"") | E32: =IFERROR(INDEX('🔥 Pipeline'!$H:$H,MATCH(4,'⚙ Pipeline Engine'!$AD:$AD,0)),"") | F32: =IFERROR(INDEX('🔥 Pipeline'!$G:$G,MATCH(4,'⚙ Pipeline Engine'!$AD:$AD,0)),"")
A33: =IFERROR(INDEX('🔥 Pipeline'!$C:$C,MATCH(5,'⚙ Pipeline Engine'!$AD:$AD,0)),"") | B33: =IFERROR(INDEX('🔥 Pipeline'!$B:$B,MATCH(5,'⚙ Pipeline Engine'!$AD:$AD,0)),"") | C33: =IFERROR(INDEX('🔥 Pipeline'!$E:$E,MATCH(5,'⚙ Pipeline Engine'!$AD:$AD,0)),"") | D33: =IFERROR(INDEX('🔥 Pipeline'!$I:$I,MATCH(5,'⚙ Pipeline Engine'!$AD:$AD,0)),"") | E33: =IFERROR(INDEX('🔥 Pipeline'!$H:$H,MATCH(5,'⚙ Pipeline Engine'!$AD:$AD,0)),"") | F33: =IFERROR(INDEX('🔥 Pipeline'!$G:$G,MATCH(5,'⚙ Pipeline Engine'!$AD:$AD,0)),"")
A34: =IFERROR(INDEX('🔥 Pipeline'!$C:$C,MATCH(6,'⚙ Pipeline Engine'!$AD:$AD,0)),"") | B34: =IFERROR(INDEX('🔥 Pipeline'!$B:$B,MATCH(6,'⚙ Pipeline Engine'!$AD:$AD,0)),"") | C34: =IFERROR(INDEX('🔥 Pipeline'!$E:$E,MATCH(6,'⚙ Pipeline Engine'!$AD:$AD,0)),"") | D34: =IFERROR(INDEX('🔥 Pipeline'!$I:$I,MATCH(6,'⚙ Pipeline Engine'!$AD:$AD,0)),"") | E34: =IFERROR(INDEX('🔥 Pipeline'!$H:$H,MATCH(6,'⚙ Pipeline Engine'!$AD:$AD,0)),"") | F34: =IFERROR(INDEX('🔥 Pipeline'!$G:$G,MATCH(6,'⚙ Pipeline Engine'!$AD:$AD,0)),"")

Sheet 🔥 Pipeline
A1: 🔥 HARMONY PLACE — ADMISSIONS PIPELINE
A2: ="SCHEDULED: "&COUNTIF(D5:D100,"Scheduled")&" PROSPECT: "&COUNTIF(D5:D100,"Prospect")&" LEAD: "&COUNTIF(D5:D100,"Lead")&" HOLD: "&COUNTIF(D5:D100,"Hold")&" TOTAL: "&(COUNTIF(D5:D100,"Scheduled")+COUNTIF(D5:D100,"Prospect")+COUNTIF(D5:D100,"Lead")+COUNTIF(D5:D100,"Hold")) -> SCHEDULED: 1 PROSPECT: 6 LEAD: 5 HOLD: 0 TOTAL: 12
A3: Coverage: Amy & Nelson — weekdays · Ahbra — evenings · Matthew — weekends (as of pull date)
A4: # | B4: REP | C4: CLIENT NAME | D4: STATUS ▼ | E4: LOC | F4: FACILITY | G4: VOB | H4: INTAKE | I4: INSURANCE | J4: NOTES / NEXT ACTION | K4: REFERRAL SOURCE ▼ | L4: REFERRAL SOURCE DETAIL | M4: INSURANCE DETAIL | N4: ASSESSMENT STATUS ▼ | O4: PRIORITY SCORE | P4: OUTCOME ▼ | Q4: PERSONAL REFERRAL ▼ | R4: GREETED ≤24H ▼ | S4: DATE ADDED | U4: ▣ PIPELINE SUMMARY (auto-updates)
A5: 1 | B5: Amy | C5: Christopher Knight | D5: Prospect | E5: DTX/RTC | F5: HP | G5: ✓ | H5: TBD | I5: Anthem BC | J5: $300 admit copay then covered at 100%. Only wants to go to HP. Meeting with employer on Wednesday for medical leave of absence. | K5: Web | L5: Google Organice SEO | M5: EPO | N5: Not Yet Scheduled | Q5: No | S5: 45586 | T5: =IF($C5<>"",$B5&"#"&COUNTIF($B$5:$B5,$B5),"") -> Amy#1 | U5: By Stage
A6: 2 | B6: Amy | C6: Nicolas Leuvrey | D6: Prospect | E6: DTX | F6: HPE | G6: ✓ | H6: TBD | I6: Private Pay | J6: $1,000/day for 10 day detox. 31 yo male struggling with 7oh for the last year. | K6: Alumni | L6: Allisa Leuvrey | M6: n/a | N6: Scheduled | S6: 46188 | T6: =IF($C6<>"",$B6&"#"&COUNTIF($B$5:$B6,$B6),"") -> Amy#2 | U6: Scheduled | V6: =COUNTIF($D$5:$D$100,"Scheduled") -> 1
A7: 3 | B7: Amy | C7: Tara Shinde | D7: Scheduled | E7: DTX/RTC | F7: HPE | G7: ✓ | H7: 46192 | I7: BCBS IL | J7: 1759.82 remaining of OPM. Can pay this. 24 y/o female. DOC: ADHD medications/cocaine | K7: Web | L7: Google Organic SEO | M7: PPO | N7: Completed | Q7: No | S7: 46178 | T7: =IF($C7<>"",$B7&"#"&COUNTIF($B$5:$B7,$B7),"") -> Amy#3 | U7: Prospect | V7: =COUNTIF($D$5:$D$100,"Prospect") -> 6
A8: 4 | B8: Amy | C8: Kimberly Cote | D8: Lead | E8: DTX/RTC | F8: HP | G8: ✓ | H8: TBD | I8: UMR | J8: employer policy. Sent for VOB after hours. Have a follow up call scheduled with her today to go over benefits. 43 y/o abusing xanax prescription and struggling with depression and anxiety. Located in Texas. | K8: Web | L8: Website Direct- Form Fill | M8: EPO | N8: Not Yet Scheduled | T8: =IF($C8<>"",$B8&"#"&COUNTIF($B$5:$B8,$B8),"") -> Amy#4 | U8: Lead | V8: =COUNTIF($D$5:$D$100,"Lead") -> 5
A9: 5 | B9: Amy | C9: Andrew Battley | D9: Lead | E9: DTX/RTC | F9: HPE | G9: ✓ | H9: TBD | I9: Aetna | J9: Employer policy through his wife. His wife called in and said he is struggling with cocaine, adderal, xanax and weed. They are located in MS. Looking to admit at the end of the week. Sent for VOB. | K9: Web | L9: Google Organice SEO | M9: POS | N9: Not Yet Scheduled | T9: =IF($C9<>"",$B9&"#"&COUNTIF($B$5:$B9,$B9),"") -> Amy#5 | U9: Hold | V9: =COUNTIF($D$5:$D$100,"Hold") -> 0
A10: 6 | B10: Nelson | C10: Frederic Spieser | D10: Lead | E10: DTX/RTC | F10: HP | G10: ✓ | H10: TBD | I10: UHC | J10: 51M alcohol; SMART + IOP but still drinking; tour Thursday 10am | K10: Web | L10: Web | M10: POS | N10: Not Yet Scheduled | O10: 2 | Q10: No | S10: 46177 | T10: =IF($C10<>"",$B10&"#"&COUNTIF($B$5:$B10,$B10),"") -> Nelson#1 | U10: TOTAL | V10: =COUNTA($C$5:$C$100) -> 12
A11: 7 | B11: Nelson | C11: Michael Cardenas | D11: Prospect | E11: DTX/RTC | F11: TBD | G11: ✓ | H11: TBD | I11: UHC | J11: 54M Army vet (Lt. Commander), PTSD, daily drinking; needs own room; in Colorado | K11: Web | L11: Web | M11: EPO | N11: Not Yet Scheduled | O11: 2 | Q11: No | S11: 46175 | T11: =IF($C11<>"",$B11&"#"&COUNTIF($B$5:$B11,$B11),"") -> Nelson#2
A12: 8 | B12: Nelson | C12: Holly Webster | D12: Prospect | E12: DTX/RTC | F12: TBD | G12: ✓ | H12: 46191 | I12: Aetna | J12: 34 yo Female, In Maryland, DOC: alcohol. Scheduled assessement 6/17 | K12: Web | N12: Scheduled | Q12: No | S12: 46189 | T12: =IF($C12<>"",$B12&"#"&COUNTIF($B$5:$B12,$B12),"") -> Nelson#3 | U12: By Rep
A13: 9 | B13: Matthew | C13: Samuel Lieberman | D13: Lead | E13: DTX/RTC | F13: TBD | G13: ✓ | H13: TBD | I13: Aetna | J13: Daily use of Ketamine for 2 years. Hx of initiating and not committing to tx. Currently in Brooklyn. | K13: Web | L13: Web | M13: PPPO | N13: Not Yet Scheduled | O13: 2 | Q13: No | S13: 46187 | T13: =IF($C13<>"",$B13&"#"&COUNTIF($B$5:$B13,$B13),"") -> Matthew#1 | U13: Amy | V13: =COUNTIF($B$5:$B$100,"Amy") -> 5
A14: 10 | T14: =IF($C14<>"",$B14&"#"&COUNTIF($B$5:$B14,$B14),"") | U14: Nelson | V14: =COUNTIF($B$5:$B$100,"Nelson") -> 3
A15: 11 | T15: =IF($C15<>"",$B15&"#"&COUNTIF($B$5:$B15,$B15),"") | U15: Matthew | V15: =COUNTIF($B$5:$B$100,"Matthew") -> 1
A16: 12 | B16: Ahbra | C16: Allison Warren | D16: Prospect | E16: DTX/RTC | F16: HP | G16: ✓ | H16: TBD | I16: UHC | J16: 0 ded; $1,500 OPM; covered 100%. 28F alcohol; stabilized after HLOC, ready to focus on SUD | K16: Professional Referral | L16: Iris / Ahbra | M16: HMO | N16: Complete | O16: 2 | Q16: No | S16: 46103 | T16: =IF($C16<>"",$B16&"#"&COUNTIF($B$5:$B16,$B16),"") -> Ahbra#1 | U16: Amos | V16: =COUNTIF($B$5:$B$100,"Amos") -> 0
B17: Ahbra | C17: Lisa Alden | D17: Prospect | E17: DTX/RTC | F17: HP | H17: TBD | I17: Cigna/Evernorth | J17: tour HPE Wed. at 3pm | K17: Personal/BD | L17: Personal/friend | M17: PPO | N17: Not Yet Scheduled | Q17: Yes | S17: 46189 | T17: =IF($C17<>"",$B17&"#"&COUNTIF($B$5:$B17,$B17),"") -> Ahbra#2 | U17: Ahbra | V17: =COUNTIF($B$5:$B$100,"Ahbra") -> 3
B18: Ahbra | C18: Teri Kahana | D18: Lead | E18: DTX/RTC | F18: TBD | H18: TBD | I18: HMSA | K18: Professional Referral | L18: Scotty/Monarch | N18: Not Yet Scheduled | S18: 46189 | T18: =IF($C18<>"",$B18&"#"&COUNTIF($B$5:$B18,$B18),"") -> Ahbra#3
T19: =IF($C19<>"",$B19&"#"&COUNTIF($B$5:$B19,$B19),"") | U19: By Facility
T20: =IF($C20<>"",$B20&"#"&COUNTIF($B$5:$B20,$B20),"") | U20: HP | V20: =COUNTIF($F$5:$F$100,"HP") -> 5
T21: =IF($C21<>"",$B21&"#"&COUNTIF($B$5:$B21,$B21),"") | U21: HPE | V21: =COUNTIF($F$5:$F$100,"HPE") -> 3
T22: =IF($C22<>"",$B22&"#"&COUNTIF($B$5:$B22,$B22),"") | U22: VRC | V22: =COUNTIF($F$5:$F$100,"VRC") -> 0
T23: =IF($C23<>"",$B23&"#"&COUNTIF($B$5:$B23,$B23),"")
T24: =IF($C24<>"",$B24&"#"&COUNTIF($B$5:$B24,$B24),"")
T25: =IF($C25<>"",$B25&"#"&COUNTIF($B$5:$B25,$B25),"")
T26: =IF($C26<>"",$B26&"#"&COUNTIF($B$5:$B26,$B26),"")
T27: =IF($C27<>"",$B27&"#"&COUNTIF($B$5:$B27,$B27),"")
T28: =IF($C28<>"",$B28&"#"&COUNTIF($B$5:$B28,$B28),"")
T29: =IF($C29<>"",$B29&"#"&COUNTIF($B$5:$B29,$B29),"")
T30: =IF($C30<>"",$B30&"#"&COUNTIF($B$5:$B30,$B30),"")
T31: =IF($C31<>"",$B31&"#"&COUNTIF($B$5:$B31,$B31),"")
T32: =IF($C32<>"",$B32&"#"&COUNTIF($B$5:$B32,$B32),"")
T33: =IF($C33<>"",$B33&"#"&COUNTIF($B$5:$B33,$B33),"")
T34: =IF($C34<>"",$B34&"#"&COUNTIF($B$5:$B34,$B34),"")
... T40: =IF($C40<>"",$B40&"#"&COUNTIF($B$5:$B40,$B40),"")

Sheet 📋 May 2026
A1: 📋 MAY 2026 — CONVERSION TRACKER
A2: =COUNTA(B5:B60)&" Admits" -> 28 Admits | G2: 🤝 Ahbra referrals SENT this month →
A4: ✓ | B4: Client Name | C4: Admit | D4: DC Date | E4: LOS | F4: Meet & Greet | G4: Program | H4: LOC | I4: DC LOC | J4: Rep | K4: Ref Cat | L4: Referral Source | M4: Insurance | N4: Type | O4: Web Source | P4: ROR | Q4: Private Pay | R4: Private Room $ | S4: Deductible | T4: Copay | U4: OPM Collected | V4: Total Cash | X4: Notes | AB4: Tier
A5: ✓ | B5: Amber Buffalo | C5: 46143 | E5: =IF(C5="","",IF(D5="",INT(TODAY())-INT(C5),MAX(0,INT(D5)-INT(C5)))) -> 47 | F5: Yes | G5: HP | H5: RTC | J5: Amy | K5: Web | L5: Josh Pierce | M5: Blue Shield CA | N5: PPO | O5: Google Ads | V5: =IFERROR(IF(SUM($Q5,$R5,$S5,$T5,$U5)>0,SUM($Q5,$R5,$S5,$T5,$U5),""),"") | X5: met same day | AB5: New
A6: ✓ | B6: Blayne Olivier | C6: 46143 | E6: =IF(C6="","",IF(D6="",INT(TODAY())-INT(C6),MAX(0,INT(D6)-INT(C6)))) -> 47 | F6: Yes | G6: HP | H6: RTC | J6: Amy | K6: Professional Referral | L6: Steve J. | M6: Molina | N6: HMO | V6: =IFERROR(IF(SUM($Q6,$R6,$S6,$T6,$U6)>0,SUM($Q6,$R6,$S6,$T6,$U6),""),"") | X6: met same day | AB6: Alumni
A7: ✓ | B7: Brittany Watkins | C7: 46144 | E7: =IF(C7="","",IF(D7="",INT(TODAY())-INT(C7),MAX(0,INT(D7)-INT(C7)))) -> 46 | G7: HPE | H7: DTX RTC | J7: Amos | K7: Professional Referral | L7: Matt Allen | M7: Blue Shield CA | N7: HMO | V7: =IFERROR(IF(SUM($Q7,$R7,$S7,$T7,$U7)>0,SUM($Q7,$R7,$S7,$T7,$U7),""),"") | AB7: New
A8: ✓ | B8: Gerardo Jimenez | C8: 46145 | E8: =IF(C8="","",IF(D8="",INT(TODAY())-INT(C8),MAX(0,INT(D8)-INT(C8)))) -> 45 | F8: No | G8: HP | H8: DTX RTC | J8: Amy | K8: Professional Referral | L8: Rise | M8: Anthem BC | N8: HMO | V8: =IFERROR(IF(SUM($Q8,$R8,$S8,$T8,$U8)>0,SUM($Q8,$R8,$S8,$T8,$U8),""),"") | X8: dentist apt delay | AB8: New
A9: ✓ | B9: Nicholas Guerra | C9: 46147 | E9: =IF(C9="","",IF(D9="",INT(TODAY())-INT(C9),MAX(0,INT(D9)-INT(C9)))) -> 43 | F9: Yes | G9: HPE | H9: RTC | J9: Nelson | K9: Readmit | L9: Readmit | M9: Molina | N9: HMO | O9: Google Ads | P9: ROR | V9: =IFERROR(IF(SUM($Q9,$R9,$S9,$T9,$U9)>0,SUM($Q9,$R9,$S9,$T9,$U9),""),"") | X9: met same day | AB9: Alumni
A10: ✓ | B10: George Sutherland | C10: 46148 | E10: =IF(C10="","",IF(D10="",INT(TODAY())-INT(C10),MAX(0,INT(D10)-INT(C10)))) -> 42 | F10: Yes | G10: HPE | H10: DTX RTC | J10: Amos | K10: Web | L10: web | M10: Aetna | N10: HMO | O10: Google SEO | U10: 1500 | V10: =IFERROR(IF(SUM($Q10,$R10,$S10,$T10,$U10)>0,SUM($Q10,$R10,$S10,$T10,$U10),""),"") -> 1500 | X10: met same day | AB10: New
A11: ✓ | B11: Jake Sorkin | C11: 46148 | E11: =IF(C11="","",IF(D11="",INT(TODAY())-INT(C11),MAX(0,INT(D11)-INT(C11)))) -> 42 | F11: Yes | G11: HPE | H11: DTX RTC | J11: Amos | K11: Professional Referral | L11: DBH/Ahbra | M11: Blue Shield CA | N11: PPO | V11: =IFERROR(IF(SUM($Q11,$R11,$S11,$T11,$U11)>0,SUM($Q11,$R11,$S11,$T11,$U11),""),"") | AB11: New
A12: ✓ | B12: Daniel Feingersh | C12: 46149 | E12: =IF(C12="","",IF(D12="",INT(TODAY())-INT(C12),MAX(0,INT(D12)-INT(C12)))) -> 41 | F12: Yes | G12: HP | H12: DTX RTC | J12: Amy | K12: Web | L12: web | M12: UHC/Optum | N12: HMO | O12: Google SEO | V12: =IFERROR(IF(SUM($Q12,$R12,$S12,$T12,$U12)>0,SUM($Q12,$R12,$S12,$T12,$U12),""),"") | X12: met same day | AB12: New
A13: ✓ | B13: Jordan Sutphen | C13: 46151 | E13: =IF(C13="","",IF(D13="",INT(TODAY())-INT(C13),MAX(0,INT(D13)-INT(C13)))) -> 39 | G13: HPE | H13: DTX RTC | J13: Nelson | K13: Professional Referral | L13: Melissa/Ladder House | M13: Blue Shield CA | N13: HMO | V13: =IFERROR(IF(SUM($Q13,$R13,$S13,$T13,$U13)>0,SUM($Q13,$R13,$S13,$T13,$U13),""),"") | X13: Sat admit | AB13: New
A14: ✓ | B14: Nathaniel Varela | C14: 46152 | E14: =IF(C14="","",IF(D14="",INT(TODAY())-INT(C14),MAX(0,INT(D14)-INT(C14)))) -> 38 | G14: HPE | H14: DTX RTC | J14: Matthew | K14: Professional Referral | L14: Ladder House | M14: Blue Shield CA | N14: EPO | V14: =IFERROR(IF(SUM($Q14,$R14,$S14,$T14,$U14)>0,SUM($Q14,$R14,$S14,$T14,$U14),""),"") | AB14: New
A15: ✓ | B15: Rhiyen Sharp | C15: 46153 | E15: =IF(C15="","",IF(D15="",INT(TODAY())-INT(C15),MAX(0,INT(D15)-INT(C15)))) -> 37 | G15: HP | H15: DTX | J15: Matthew | K15: Readmit | L15: Readmit | M15: Blue Shield CA | N15: PPO | O15: Google SEO | V15: =IFERROR(IF(SUM($Q15,$R15,$S15,$T15,$U15)>0,SUM($Q15,$R15,$S15,$T15,$U15),""),"") | AB15: Alumni
A16: ✓ | B16: Alan Cervantes | C16: 46154 | E16: =IF(C16="","",IF(D16="",INT(TODAY())-INT(C16),MAX(0,INT(D16)-INT(C16)))) -> 36 | G16: HPE | H16: DTX RTC | J16: Amos | K16: Professional Referral | L16: Dr. Jessica Wang | M16: Blue Shield CA | N16: PPO | V16: =IFERROR(IF(SUM($Q16,$R16,$S16,$T16,$U16)>0,SUM($Q16,$R16,$S16,$T16,$U16),""),"") | AB16: New
A17: ✓ | B17: Sara Gordon | C17: 46158 | E17: =IF(C17="","",IF(D17="",INT(TODAY())-INT(C17),MAX(0,INT(D17)-INT(C17)))) -> 32 | F17: Yes | G17: HP | H17: DTX RTC | J17: Amy | K17: Readmit | L17: readmit/Rise | M17: Blue Shield CA | N17: PPO | U17: 626.82 | V17: =IFERROR(IF(SUM($Q17,$R17,$S17,$T17,$U17)>0,SUM($Q17,$R17,$S17,$T17,$U17),""),"") -> 626.82 | X17: met same day | AB17: Alumni
A18: ✓ | B18: Ellie Ferrero | C18: 46159 | E18: =IF(C18="","",IF(D18="",INT(TODAY())-INT(C18),MAX(0,INT(D18)-INT(C18)))) -> 31 | G18: HP | H18: DTX RTC | J18: Matthew | K18: Professional Referral | L18: Ahbra | M18: Blue Shield CA | N18: PPO | V18: =IFERROR(IF(SUM($Q18,$R18,$S18,$T18,$U18)>0,SUM($Q18,$R18,$S18,$T18,$U18),""),"") | AB18: Split
A19: ✓ | B19: Christopher Anderson | C19: 46161 | E19: =IF(C19="","",IF(D19="",INT(TODAY())-INT(C19),MAX(0,INT(D19)-INT(C19)))) -> 29 | G19: HP | H19: DTX RTC | J19: Amos | K19: Readmit | L19: Readmit/Ahbra | M19: Blue Shield CA | N19: PPO | V19: =IFERROR(IF(SUM($Q19,$R19,$S19,$T19,$U19)>0,SUM($Q19,$R19,$S19,$T19,$U19),""),"") | AB19: Alumni
A20: ✓ | B20: Amir Jawhary | C20: 46162 | E20: =IF(C20="","",IF(D20="",INT(TODAY())-INT(C20),MAX(0,INT(D20)-INT(C20)))) -> 28 | F20: Yes | G20: HP | H20: DTX RTC | J20: Nelson | K20: Web | L20: Web | M20: Cash Pay | O20: Google SEO | Q20: 12650 | V20: =IFERROR(IF(SUM($Q20,$R20,$S20,$T20,$U20)>0,SUM($Q20,$R20,$S20,$T20,$U20),""),"") -> 12650 | X20: Met at door | AB20: New
A21: ✓ | B21: Zachary Kane | C21: 46162 | E21: =IF(C21="","",IF(D21="",INT(TODAY())-INT(C21),MAX(0,INT(D21)-INT(C21)))) -> 28 | G21: HP | H21: DTX RTC | J21: Matthew | K21: Web | L21: web | M21: Blue Shield CA | N21: PPO | O21: Google SEO | V21: =IFERROR(IF(SUM($Q21,$R21,$S21,$T21,$U21)>0,SUM($Q21,$R21,$S21,$T21,$U21),""),"") | X21: PHP/IOP secured | AB21: New
A22: ✓ | B22: Jodana Sykes | C22: 46163 | D22: 46163 | E22: =IF(C22="","",IF(D22="",INT(TODAY())-INT(C22),MAX(0,INT(D22)-INT(C22)))) -> 0 | F22: No | G22: HPE | H22: DTX RTC | J22: Amy | K22: Readmit | L22: Readmit | M22: Anthem BC | N22: PPO | V22: =IFERROR(IF(SUM($Q22,$R22,$S22,$T22,$U22)>0,SUM($Q22,$R22,$S22,$T22,$U22),""),"") | X22: did not meet ct | AB22: Alumni
A23: ✓ | B23: Brian Tethers | C23: 46163 | E23: =IF(C23="","",IF(D23="",INT(TODAY())-INT(C23),MAX(0,INT(D23)-INT(C23)))) -> 27 | F23: Yes | G23: HP | H23: RTC | J23: Amy | K23: Professional Referral | L23: Michelle Onesto | M23: Aetna | N23: POS | O23: Yelp | V23: =IFERROR(IF(SUM($Q23,$R23,$S23,$T23,$U23)>0,SUM($Q23,$R23,$S23,$T23,$U23),""),"") | X23: met next day | AB23: New
A24: ✓ | B24: Jason Schnell | C24: 46164 | E24: =IF(C24="","",IF(D24="",INT(TODAY())-INT(C24),MAX(0,INT(D24)-INT(C24)))) -> 26 | F24: Yes | G24: HP | H24: DTX RTC | J24: Amy | K24: Readmit | L24: Readmit | M24: Blue Shield CA | V24: =IFERROR(IF(SUM($Q24,$R24,$S24,$T24,$U24)>0,SUM($Q24,$R24,$S24,$T24,$U24),""),"") | AB24: Alumni
A25: ✓ | B25: Rhonda Baim | C25: 46166 | E25: =IF(C25="","",IF(D25="",INT(TODAY())-INT(C25),MAX(0,INT(D25)-INT(C25)))) -> 24 | F25: No | G25: HPE | H25: DTX | J25: Nelson | K25: Web | L25: Web | M25: Anthem BC | N25: PPO | O25: Google SEO | S25: 500 | U25: 3000 | V25: =IFERROR(IF(SUM($Q25,$R25,$S25,$T25,$U25)>0,SUM($Q25,$R25,$S25,$T25,$U25),""),"") -> 3500 | X25: met 2 days later | AB25: New
A26: ✓ | B26: Jeongwoon Lee | C26: 46167 | E26: =IF(C26="","",IF(D26="",INT(TODAY())-INT(C26),MAX(0,INT(D26)-INT(C26)))) -> 23 | F26: Yes | G26: HPE | H26: RTC | J26: Nelson | K26: Web | L26: Web | M26: Aetna | N26: POS | O26: Google SEO | S26: 750 | U26: 1250 | V26: =IFERROR(IF(SUM($Q26,$R26,$S26,$T26,$U26)>0,SUM($Q26,$R26,$S26,$T26,$U26),""),"") -> 2000 | X26: met next day | AB26: New
A27: ✓ | B27: Christopher Avolio | C27: 46169 | E27: =IF(C27="","",IF(D27="",INT(TODAY())-INT(C27),MAX(0,INT(D27)-INT(C27)))) -> 21 | F27: Yes | G27: HP | H27: DTX RTC | J27: Amy | K27: Professional Referral | L27: Montare/Ahbra | M27: Blue Shield CA | N27: PPO | U27: 1117.84 | V27: =IFERROR(IF(SUM($Q27,$R27,$S27,$T27,$U27)>0,SUM($Q27,$R27,$S27,$T27,$U27),""),"") -> 1117.84 | X27: met upon admit | AB27: New
A28: ✓ | B28: Jonathan Serrano | C28: 46169 | E28: =IF(C28="","",IF(D28="",INT(TODAY())-INT(C28),MAX(0,INT(D28)-INT(C28)))) -> 21 | G28: HPE | H28: DTX RTC | J28: Matthew | K28: Web | L28: web | M28: Blue Shield CA | N28: HMO | O28: Google Ads | V28: =IFERROR(IF(SUM($Q28,$R28,$S28,$T28,$U28)>0,SUM($Q28,$R28,$S28,$T28,$U28),""),"") | AB28: New
A29: ✓ | B29: Cree Lamere | C29: 46170 | E29: =IF(C29="","",IF(D29="",INT(TODAY())-INT(C29),MAX(0,INT(D29)-INT(C29)))) -> 20 | F29: Yes | G29: HPE | H29: DTX RTC | J29: Amy | K29: Professional Referral | L29: Profound/Ahbra | M29: Blue Shield CA | N29: HMO | V29: =IFERROR(IF(SUM($Q29,$R29,$S29,$T29,$U29)>0,SUM($Q29,$R29,$S29,$T29,$U29),""),"") | X29: met day after | AB29: New
A30: ✓ | B30: Aaron Dufresne | C30: 46171 | E30: =IF(C30="","",IF(D30="",INT(TODAY())-INT(C30),MAX(0,INT(D30)-INT(C30)))) -> 19 | F30: Yes | G30: HPE | H30: DTX | J30: Nelson | K30: Professional Referral | L30: Action IOP/Ahbra | M30: UMR/UHC | N30: HMO | V30: =IFERROR(IF(SUM($Q30,$R30,$S30,$T30,$U30)>0,SUM($Q30,$R30,$S30,$T30,$U30),""),"") | X30: met same day | AB30: New
A31: ✓ | B31: Kurt Guisler | C31: 46172 | E31: =IF(C31="","",IF(D31="",INT(TODAY())-INT(C31),MAX(0,INT(D31)-INT(C31)))) -> 18 | F31: No | G31: HP | H31: DTX RTC | J31: Amy | K31: Professional Referral | L31: Skyline/Ahbra | M31: Blue Shield CA | N31: PPO | U31: 2507.08 | V31: =IFERROR(IF(SUM($Q31,$R31,$S31,$T31,$U31)>0,SUM($Q31,$R31,$S31,$T31,$U31),""),"") -> 2507.08 | X31: met Tuesday | AB31: New
A32: ✓ | B32: Pedro Mendoza | C32: 46172 | E32: =IF(C32="","",IF(D32="",INT(TODAY())-INT(C32),MAX(0,INT(D32)-INT(C32)))) -> 18 | G32: HPE | H32: DTX RTC | J32: Matthew | K32: Readmit | L32: readmit | M32: Blue Shield CA | N32: PPO | O32: Google GMB | S32: 4000 | V32: =IFERROR(IF(SUM($Q32,$R32,$S32,$T32,$U32)>0,SUM($Q32,$R32,$S32,$T32,$U32),""),"") -> 4000 | AB32: Alumni

Sheet 📋 Jun 2026
A1: 📋 JUNE 2026 — CONVERSION TRACKER
A2: =COUNTA(B5:B60)&" Admits" -> 13 Admits | G2: 🤝 Ahbra referrals SENT this month →
A4: ✓ | B4: Client Name | C4: Admit | D4: DC Date | E4: LOS | F4: Meet & Greet | G4: Program | H4: LOC | I4: DC LOC | J4: Rep | K4: Ref Cat | L4: Referral Source | M4: Insurance | N4: Type | O4: Web Source | P4: ROR | Q4: Private Pay | R4: Private Room $ | S4: Deductible | T4: Copay | U4: OPM Collected | V4: Total Cash | X4: Notes | AB4: Tier
A5: ✓ | B5: Jared Hamilton | C5: 46175 | E5: =IF(C5="","",IF(D5="",INT(TODAY())-INT(C5),MAX(0,INT(D5)-INT(C5)))) -> 15 | F5: Yes | G5: HPE | H5: DTX RTC | J5: Amy | K5: Professional Referral | L5: Rise | M5: Blue Shield CA | N5: PPO | S5: 750 | V5: =IFERROR(IF(SUM($Q5,$R5,$S5,$T5,$U5)>0,SUM($Q5,$R5,$S5,$T5,$U5),""),"") -> 750 | X5: met same day | AB5: New
A6: ✓ | B6: Sean Darling | C6: 46178 | E6: =IF(C6="","",IF(D6="",INT(TODAY())-INT(C6),MAX(0,INT(D6)-INT(C6)))) -> 12 | F6: Yes | G6: HPE | H6: DTX RTC | J6: Amy | K6: Professional Referral | L6: Destiny Recovery / Ahbra | M6: BCBS IL | N6: PPO | V6: =IFERROR(IF(SUM($Q6,$R6,$S6,$T6,$U6)>0,SUM($Q6,$R6,$S6,$T6,$U6),""),"") | X6: met same day | AB6: New
A7: ✓ | B7: Bejan Tajipour | C7: 46181 | E7: =IF(C7="","",IF(D7="",INT(TODAY())-INT(C7),MAX(0,INT(D7)-INT(C7)))) -> 9 | F7: Yes | G7: HP | H7: DTX RTC | J7: Nelson | K7: Web | L7: Web | M7: UHC/Optum | N7: POS | O7: Google Ads | S7: 2400 | U7: 1000 | V7: =IFERROR(IF(SUM($Q7,$R7,$S7,$T7,$U7)>0,SUM($Q7,$R7,$S7,$T7,$U7),""),"") -> 3400 | X7: met ct same day · DC’d ~6/10 (date needed) | AB7: New
A8: ✓ | B8: Darian Tucker | C8: 46181 | E8: =IF(C8="","",IF(D8="",INT(TODAY())-INT(C8),MAX(0,INT(D8)-INT(C8)))) -> 9 | F8: Yes | G8: HP | H8: DTX RTC | J8: Ahbra | K8: Professional Referral | L8: EleMental Treatment Center / Ahbra | M8: Blue Shield CA | N8: PPO | V8: =IFERROR(IF(SUM($Q8,$R8,$S8,$T8,$U8)>0,SUM($Q8,$R8,$S8,$T8,$U8),""),"") | X8: met same day | AB8: New
A9: ✓ | B9: Daniel Armiger | C9: 46182 | E9: =IF(C9="","",IF(D9="",INT(TODAY())-INT(C9),MAX(0,INT(D9)-INT(C9)))) -> 8 | G9: HPE | H9: DTX RTC | J9: Matthew | K9: Readmit | M9: Blue Shield CA | N9: HMO | V9: =IFERROR(IF(SUM($Q9,$R9,$S9,$T9,$U9)>0,SUM($Q9,$R9,$S9,$T9,$U9),""),"") | X9: NEEDS: Met-CT, financials
A10: ✓ | B10: Darian Loehner | C10: 46183 | E10: =IF(C10="","",IF(D10="",INT(TODAY())-INT(C10),MAX(0,INT(D10)-INT(C10)))) -> 7 | F10: Yes | G10: HP | H10: DTX | J10: Amy | K10: Readmit | M10: Aetna | N10: HMO | V10: =IFERROR(IF(SUM($Q10,$R10,$S10,$T10,$U10)>0,SUM($Q10,$R10,$S10,$T10,$U10),""),"") | X10: met ct at the door | AB10: Alumni
A11: ✓ | B11: Jamal Williams | C11: 46183 | E11: =IF(C11="","",IF(D11="",INT(TODAY())-INT(C11),MAX(0,INT(D11)-INT(C11)))) -> 7 | G11: HP | H11: DTX RTC | J11: Ahbra | K11: Professional Referral | M11: Blue Shield CA | N11: HMO | V11: =IFERROR(IF(SUM($Q11,$R11,$S11,$T11,$U11)>0,SUM($Q11,$R11,$S11,$T11,$U11),""),"") | X11: The Canyon · NEEDS: closer, Met-CT, financials
A12: ✓ | B12: Kyle Samia | C12: 46184 | E12: =IF(C12="","",IF(D12="",INT(TODAY())-INT(C12),MAX(0,INT(D12)-INT(C12)))) -> 6 | F12: Yes | G12: HP | H12: DTX RTC | J12: Matthew | K12: Web | M12: Cigna | N12: PPO | V12: =IFERROR(IF(SUM($Q12,$R12,$S12,$T12,$U12)>0,SUM($Q12,$R12,$S12,$T12,$U12),""),"") | X12: Nelson met this ct
A13: ✓ | B13: Monica Gamboa | C13: 46184 | E13: =IF(C13="","",IF(D13="",INT(TODAY())-INT(C13),MAX(0,INT(D13)-INT(C13)))) -> 6 | F13: Yes | G13: HP | H13: DTX RTC | J13: Amy | K13: Readmit | M13: Molina CA | N13: HMO | V13: =IFERROR(IF(SUM($Q13,$R13,$S13,$T13,$U13)>0,SUM($Q13,$R13,$S13,$T13,$U13),""),"") | X13: met ct next day (>24h — verify) | AB13: Alumni
B14: Blayne Olivier | C14: 46186 | F14: Yes | G14: HPE | H14: DTX/RTC | J14: Amy | K14: Readmit | M14: Molina | N14: HMO | V14: =IFERROR(IF(SUM($Q14,$R14,$S14,$T14,$U14)>0,SUM($Q14,$R14,$S14,$T14,$U14),""),"") | AB14: Alumni
B15: Garrett Johnson | C15: 46186 | F15: Yes | G15: HP | H15: RTC | J15: Nelson | K15: Web | L15: Web | M15: UHC | N15: POS | U15: 2000 | V15: =IFERROR(IF(SUM($Q15,$R15,$S15,$T15,$U15)>0,SUM($Q15,$R15,$S15,$T15,$U15),""),"") -> 2000 | X15: met same day
B16: Bradey Bauer | C16: 46186 | F16: No | G16: HPE | H16: DTX/RTC | J16: Matthew | K16: Readmit | M16: Anthem MPI | N16: PPO | V16: =IFERROR(IF(SUM($Q16,$R16,$S16,$T16,$U16)>0,SUM($Q16,$R16,$S16,$T16,$U16),""),"") | AB16: Alumni
B17: Jill Labate | C17: 46187 | F17: No | G17: HPE | H17: DTX/RTC | J17: Matthew | K17: Readmit | M17: Cigna | N17: HMO | V17: =IFERROR(IF(SUM($Q17,$R17,$S17,$T17,$U17)>0,SUM($Q17,$R17,$S17,$T17,$U17),""),"") | AB17: Alumni

Sheet 🏆 Leaderboard
A1: 🏆 ADMISSIONS LEADERBOARD
A2: Month: | B2: =INDEX('⚙ Lists'!$W$3:$W$10,'⚙ Lists'!$AB$8) -> 📋 Jun 2026 | C2: (current month · auto-updates) | D2: =SUMIF('⚙ Production Engine'!$A:$A,$B$2,'⚙ Production Engine'!$C:$C) -> 13
A4: Rank | B4: Rep | C4: Status | D4: Admits | E4: Goal | F4: Progress to Goal | G4: Met-CT % | H4: Pace
A5: =IF(D5=0,"—",IF(RANK(D5,$D$5:$D$9)=1,"🥇",IF(RANK(D5,$D$5:$D$9)=2,"🥈",IF(RANK(D5,$D$5:$D$9)=3,"🥉",RANK(D5,$D$5:$D$9))))) -> 🥇 | B5: Amy | C5: Active | D5: =SUMIFS('⚙ Production Engine'!$C:$C,'⚙ Production Engine'!$A:$A,$B$2,'⚙ Production Engine'!$B:$B,$B5) -> 5 | E5: 10 | F5: =REPT("█",MIN(20,ROUND(D5/E5*20,0)))&REPT("░",20-MIN(20,ROUND(D5/E5*20,0)))&" "&TEXT(D5/E5,"0%") -> ██████████░░░░░░░░░░ 50% | G5: =IFERROR(SUMIFS('⚙ Production Engine'!$D:$D,'⚙ Production Engine'!$A:$A,$B$2,'⚙ Production Engine'!$B:$B,$B5)/D5,"—") -> 1 | H5: =IF(D5>=E5,"🔥 Goal!",IF(D5>=E5*0.7,"On track","Behind")) -> Behind
A6: =IF(D6=0,"—",IF(RANK(D6,$D$5:$D$9)=1,"🥇",IF(RANK(D6,$D$5:$D$9)=2,"🥈",IF(RANK(D6,$D$5:$D$9)=3,"🥉",RANK(D6,$D$5:$D$9))))) -> 🥉 | B6: Nelson | C6: Active | D6: =SUMIFS('⚙ Production Engine'!$C:$C,'⚙ Production Engine'!$A:$A,$B$2,'⚙ Production Engine'!$B:$B,$B6) -> 2 | E6: 8 | F6: =REPT("█",MIN(20,ROUND(D6/E6*20,0)))&REPT("░",20-MIN(20,ROUND(D6/E6*20,0)))&" "&TEXT(D6/E6,"0%") -> █████░░░░░░░░░░░░░░░ 25% | G6: =IFERROR(SUMIFS('⚙ Production Engine'!$D:$D,'⚙ Production Engine'!$A:$A,$B$2,'⚙ Production Engine'!$B:$B,$B6)/D6,"—") -> 1 | H6: =IF(D6>=E6,"🔥 Goal!",IF(D6>=E6*0.7,"On track","Behind")) -> Behind
A7: =IF(D7=0,"—",IF(RANK(D7,$D$5:$D$9)=1,"🥇",IF(RANK(D7,$D$5:$D$9)=2,"🥈",IF(RANK(D7,$D$5:$D$9)=3,"🥉",RANK(D7,$D$5:$D$9))))) -> 🥈 | B7: Matthew | C7: Remote (MX) | D7: =SUMIFS('⚙ Production Engine'!$C:$C,'⚙ Production Engine'!$A:$A,$B$2,'⚙ Production Engine'!$B:$B,$B7) -> 4 | E7: 6 | F7: =REPT("█",MIN(20,ROUND(D7/E7*20,0)))&REPT("░",20-MIN(20,ROUND(D7/E7*20,0)))&" "&TEXT(D7/E7,"0%") -> █████████████░░░░░░░ 67% | G7: =IFERROR(SUMIFS('⚙ Production Engine'!$D:$D,'⚙ Production Engine'!$A:$A,$B$2,'⚙ Production Engine'!$B:$B,$B7)/D7,"—") -> 0.25 | H7: =IF(D7>=E7,"🔥 Goal!",IF(D7>=E7*0.7,"On track","Behind")) -> Behind
A8: =IF(D8=0,"—",IF(RANK(D8,$D$5:$D$9)=1,"🥇",IF(RANK(D8,$D$5:$D$9)=2,"🥈",IF(RANK(D8,$D$5:$D$9)=3,"🥉",RANK(D8,$D$5:$D$9))))) -> — | B8: Amos | C8: On Leave → ~Aug | D8: =SUMIFS('⚙ Production Engine'!$C:$C,'⚙ Production Engine'!$A:$A,$B$2,'⚙ Production Engine'!$B:$B,$B8) -> 0 | F8: =IF(D8=0,"",REPT("█",MIN(20,D8*2))) | G8: =IFERROR(SUMIFS('⚙ Production Engine'!$D:$D,'⚙ Production Engine'!$A:$A,$B$2,'⚙ Production Engine'!$B:$B,$B8)/D8,"—") -> — | H8: =""
A9: =IF(D9=0,"—",IF(RANK(D9,$D$5:$D$9)=1,"🥇",IF(RANK(D9,$D$5:$D$9)=2,"🥈",IF(RANK(D9,$D$5:$D$9)=3,"🥉",RANK(D9,$D$5:$D$9))))) -> 🥉 | B9: Ahbra | C9: PRN — no comm. | D9: =SUMIFS('⚙ Production Engine'!$C:$C,'⚙ Production Engine'!$A:$A,$B$2,'⚙ Production Engine'!$B:$B,$B9) -> 2 | F9: =IF(D9=0,"",REPT("█",MIN(20,D9*2))) -> ████ | G9: =IFERROR(SUMIFS('⚙ Production Engine'!$D:$D,'⚙ Production Engine'!$A:$A,$B$2,'⚙ Production Engine'!$B:$B,$B9)/D9,"—") -> 0.5 | H9: =""
B10: TEAM | D10: =SUM(D5:D9) -> 13 | E10: 28 | F10: =REPT("█",MIN(20,ROUND(D10/E10*20,0)))&REPT("░",20-MIN(20,ROUND(D10/E10*20,0)))&" "&TEXT(D10/E10,"0%") -> █████████░░░░░░░░░░░ 46%
A12: 🎖 THIS MONTH'S BADGES
A13: 🥇 Top Closer | D13: =INDEX($B$5:$B$9,MATCH(MAX($D$5:$D$9),$D$5:$D$9,0))&" ("&MAX($D$5:$D$9)&" admits)" -> Amy (5 admits)
A14: ⚡ Quality (Met-CT) | D14: =IFERROR(INDEX($B$5:$B$9,MATCH(MAX($G$5:$G$9),$G$5:$G$9,0))&" ("&TEXT(MAX($G$5:$G$9),"0%")&")","—") -> Amy (100%)
A17: 📈 YEAR-TO-DATE (admits)
A18: Rep | B18: YTD | C18: Avg/Mo | D18: Proj Yr | E18: vs last yr
A19: Amy | B19: ='📈 YTD Rollup'!N5 -> 40 | C19: ='📈 YTD Rollup'!O5 -> 6.7 | D19: ='📈 YTD Rollup'!P5 -> 80
A20: Nelson | B20: ='📈 YTD Rollup'!N6 -> 33 | C20: ='📈 YTD Rollup'!O6 -> 5.5 | D20: ='📈 YTD Rollup'!P6 -> 66
A21: Matthew | B21: ='📈 YTD Rollup'!N7 -> 10 | C21: ='📈 YTD Rollup'!O7 -> 1.7 | D21: ='📈 YTD Rollup'!P7 -> 20
A22: Amos | B22: ='📈 YTD Rollup'!N8 -> 24 | C22: ='📈 YTD Rollup'!O8 -> 4 | D22: ='📈 YTD Rollup'!P8 -> 48
A23: Ahbra | B23: ='📈 YTD Rollup'!N9 -> 2 | C23: ='📈 YTD Rollup'!O9 -> 0.3 | D23: ='📈 YTD Rollup'!P9 -> 4

Sheet 🔎 Insights
B1: ADMISSION CONTROL — INSIGHTS (live, updates as you use the workbook)
A3: OCCUPANCY & OPEN-BED REVENUE AT RISK
A4: House | B4: Occupied | C4: Capacity | D4: Open | E4: Occupancy
A5: Harmony Place (HP) | B5: =COUNTIF('🛏 HP Bed Board'!B10:B23,"Occupied") -> 11 | C5: 14 | D5: =COUNTIF('🛏 HP Bed Board'!B10:B23,"Open") -> 3 | E5: =IFERROR(B5/C5,0) -> 0.78571429
A6: Harmony Place East (HPE) | B6: =(COUNTIF('🛏 HPE Bed Board'!B11:B16,"Occupied")+COUNTIF('🛏 HPE Bed Board'!B18:B23,"Occupied")) -> 9 | C6: 12 | D6: =(COUNTIF('🛏 HPE Bed Board'!B11:B16,"Open")+COUNTIF('🛏 HPE Bed Board'!B18:B23,"Open")) -> 2 | E6: =IFERROR(B6/C6,0) -> 0.75
A7: COMBINED | B7: =B5+B6 -> 20 | C7: =C5+C6 -> 26 | D7: =D5+D6 -> 5 | E7: =IFERROR(B7/C7,0) -> 0.76923077
A9: Assumptions (edit these):
A10: Avg reimbursed bed-day rate | B10: 1150
A11: Billable days per month | B11: 30
A12: ⚠ Open-bed revenue at risk / month | B12: =D7*B10*B11 -> 172500
A13: Est. monthly billings at current census | B13: =B7*B10*B11 -> 690000
A15: =" THIS MONTH — PRODUCTION BY REP · "&'🏆 Leaderboard'!$B$2&" (change month on the Leaderboard)" -> THIS MONTH — PRODUCTION BY REP · 📋 Jun 2026 (change month on the Leaderboard)
A16: Rep | B16: Admits | C16: Cash collected
A17: Amy | B17: =SUMIFS('⚙ Production Engine'!$C:$C,'⚙ Production Engine'!$A:$A,'🏆 Leaderboard'!$B$2,'⚙ Production Engine'!$B:$B,$A17) -> 5 | C17: =SUMIFS('⚙ Production Engine'!$J:$J,'⚙ Production Engine'!$A:$A,'🏆 Leaderboard'!$B$2,'⚙ Production Engine'!$B:$B,$A17) -> 0
A18: Nelson | B18: =SUMIFS('⚙ Production Engine'!$C:$C,'⚙ Production Engine'!$A:$A,'🏆 Leaderboard'!$B$2,'⚙ Production Engine'!$B:$B,$A18) -> 2 | C18: =SUMIFS('⚙ Production Engine'!$J:$J,'⚙ Production Engine'!$A:$A,'🏆 Leaderboard'!$B$2,'⚙ Production Engine'!$B:$B,$A18) -> 0
A19: Matthew | B19: =SUMIFS('⚙ Production Engine'!$C:$C,'⚙ Production Engine'!$A:$A,'🏆 Leaderboard'!$B$2,'⚙ Production Engine'!$B:$B,$A19) -> 4 | C19: =SUMIFS('⚙ Production Engine'!$J:$J,'⚙ Production Engine'!$A:$A,'🏆 Leaderboard'!$B$2,'⚙ Production Engine'!$B:$B,$A19) -> 0
A20: Amos | B20: =SUMIFS('⚙ Production Engine'!$C:$C,'⚙ Production Engine'!$A:$A,'🏆 Leaderboard'!$B$2,'⚙ Production Engine'!$B:$B,$A20) -> 0 | C20: =SUMIFS('⚙ Production Engine'!$J:$J,'⚙ Production Engine'!$A:$A,'🏆 Leaderboard'!$B$2,'⚙ Production Engine'!$B:$B,$A20) -> 0
A21: TEAM | B21: =SUM(B17:B20) -> 11 | C21: =SUM(C17:C20) -> 0
A23: PIPELINE FUNNEL (live)
A24: Scheduled | B24: =COUNTIF('🔥 Pipeline'!$D$5:$D$40,"Scheduled") -> 1
A25: Prospect | B25: =COUNTIF('🔥 Pipeline'!$D$5:$D$40,"Prospect") -> 6
A26: Lead | B26: =COUNTIF('🔥 Pipeline'!$D$5:$D$40,"Lead") -> 5
A27: Hold | B27: =COUNTIF('🔥 Pipeline'!$D$5:$D$40,"Hold") -> 0
A28: Total active leads | B28: =SUM(B24:B27) -> 12
A29: ⚠ Leads owned by Amos (on leave) — reassign | B29: =COUNTIF('🔥 Pipeline'!$B$5:$B$40,"Amos") -> 0
A31: WATCH FLAGS
A32: Blue Shield CA share of this month’s admits | B32: =IFERROR(COUNTIF(CHOOSE('⚙ Lists'!$AB$6,'📋 May 2026'!$M$5:$M$60,'📋 Jun 2026'!$M$5:$M$60,'📋 Jul 2026'!$M$5:$M$60,'📋 Aug 2026'!$M$5:$M$60,'📋 Sep 2026'!$M$5:$M$60,'📋 Oct 2026'!$M$5:$M$60,'📋 Nov 2026'!$M$5:$M$60,'📋 Dec 2026'!$M$5:$M$60),"Blue Shield CA")/COUNTIF(CHOOSE('⚙ Lists'!$AB$6,'📋 May 2026'!$B$5:$B$60,'📋 Jun 2026'!$B$5:$B$60,'📋 Jul 2026'!$B$5:$B$60,'📋 Aug 2026'!$B$5:$B$60,'📋 Sep 2026'!$B$5:$B$60,'📋 Oct 2026'!$B$5:$B$60,'📋 Nov 2026'!$B$5:$B$60,'📋 Dec 2026'!$B$5:$B$60),"?*"),0) -> 0.30769231
A33: Pipeline leads on NON-contracted payers | B33: =SUMPRODUCT(COUNTIF(NON_CONTRACTED,'🔥 Pipeline'!$I$5:$I$40)) -> 0
A34: Weekday closers active (Amy, Nelson) | B34: 2

Sheet 📖 Instructions
B2: ADMISSION CONTROL — THE ADMISSIONS WORKBOOK
B4: HOW THE WORKBOOK FLOWS (START HERE)
B5: 1. Phone rings — the call is captured in Call Tracking Metrics (CTM), outside this workbook.
B6: 2. 🔥 PIPELINE — catalogue every qualified lead from CTM here, one row each. (CTM can't live-link to Excel; export a
B7: CSV from CTM and paste it in, or type leads directly. Set each lead's STATUS as it moves Lead → Prospect → Scheduled.)
B8: 3. 📋 MONTH TAB — when a lead admits, log them on the current month's Conversion Tracker. This is the ONLY sheet you
B9: type admits into; it feeds the Leaderboard, the Dashboard and the YTD Rollup.
B10: 4. LOS is automatic — leave DC DATE blank while the client is in-house and LOS counts up from the admit date on its own.
B11: Enter the DC DATE at discharge and LOS locks to the actual length of stay.
B12: 5. 🛏 BED BOARD — once placed in a house, add the client to HP or HPE. Rooms can change anytime: retype the patient into
B13: the new room's row and clear the old one. Census and open beds update live, up to the minute.
B15: WHAT YOU TYPE vs WHAT'S AUTOMATIC
... B44: ⚙ Lists, ⚙ Census Engine, and ⚙ Pipeline Engine are hidden sheets that run the math (dropdowns, live census, discharge watch, scheduled intakes). Leave them hidden — don't delete or edit them. Keep updating the Bed Boards, Pipeline, and month tabs, and everything else fills in automatically.

Sheet 🛏 Bed Map
A1: 🛏 BED MAP — live room/bed status
A3: HARMONY PLACE (HP)
A4: Census | B4: =COUNTIF('🛏 HP Bed Board'!B10:B23,"Occupied")&"/14" -> 11/14 | C4: Open | D4: =COUNTIF('🛏 HP Bed Board'!B10:B23,"Open") -> 3
A5: ROOM | B5: BED A | C5: BED B
A6: DTX | B6: =IFERROR(VLOOKUP("DTX-A",'🛏 HP Bed Board'!$A$10:$B$23,2,FALSE()),"") -> Open | C6: =IFERROR(VLOOKUP("DTX-B",'🛏 HP Bed Board'!$A$10:$B$23,2,FALSE()),"") -> Open
A7: M1 | B7: =IFERROR(VLOOKUP("M1-A",'🛏 HP Bed Board'!$A$10:$B$23,2,FALSE()),"") -> Occupied | C7: =IFERROR(VLOOKUP("M1-B",'🛏 HP Bed Board'!$A$10:$B$23,2,FALSE()),"") -> Occupied
A8: M2 | B8: =IFERROR(VLOOKUP("M2-A",'🛏 HP Bed Board'!$A$10:$B$23,2,FALSE()),"") -> Open | C8: =IFERROR(VLOOKUP("M2-B",'🛏 HP Bed Board'!$A$10:$B$23,2,FALSE()),"") -> Occupied
A9: M3 | B9: =IFERROR(VLOOKUP("M3-A",'🛏 HP Bed Board'!$A$10:$B$23,2,FALSE()),"") -> Occupied | C9: =IFERROR(VLOOKUP("M3-B",'🛏 HP Bed Board'!$A$10:$B$23,2,FALSE()),"") -> Occupied
A10: B1 | B10: =IFERROR(VLOOKUP("B1-A",'🛏 HP Bed Board'!$A$10:$B$23,2,FALSE()),"") -> Occupied | C10: =IFERROR(VLOOKUP("B1-B",'🛏 HP Bed Board'!$A$10:$B$23,2,FALSE()),"") -> Occupied
A11: B2 | B11: =IFERROR(VLOOKUP("B2-A",'🛏 HP Bed Board'!$A$10:$B$23,2,FALSE()),"") -> Occupied | C11: =IFERROR(VLOOKUP("B2-B",'🛏 HP Bed Board'!$A$10:$B$23,2,FALSE()),"") -> Occupied
A12: B3 | B12: =IFERROR(VLOOKUP("B3-A",'🛏 HP Bed Board'!$A$10:$B$23,2,FALSE()),"") -> Occupied | C12: =IFERROR(VLOOKUP("B3-B",'🛏 HP Bed Board'!$A$10:$B$23,2,FALSE()),"") -> Occupied
A14: HARMONY PLACE EAST (HPE)
A15: Census | B15: =(COUNTIF('🛏 HPE Bed Board'!B11:B16,"Occupied")+COUNTIF('🛏 HPE Bed Board'!B18:B23,"Occupied"))&"/12" -> 9/12 | C15: Open | D15: =(COUNTIF('🛏 HPE Bed Board'!B11:B16,"Open")+COUNTIF('🛏 HPE Bed Board'!B18:B23,"Open")) -> 2
A16: BED | B16: STATUS | C16: CLIENT
A17: ='🛏 HPE Bed Board'!A11 -> H1-1A | B17: ='🛏 HPE Bed Board'!B11 -> Occupied | C17: =IF('🛏 HPE Bed Board'!C11="","",'🛏 HPE Bed Board'!C11) -> Allisa Leuvrey
A18: ='🛏 HPE Bed Board'!A12 -> H1-1B | B18: ='🛏 HPE Bed Board'!B12 -> Occupied | C18: =IF('🛏 HPE Bed Board'!C12="","",'🛏 HPE Bed Board'!C12) -> Cree Lamere
A19: ='🛏 HPE Bed Board'!A13 -> H1-2A | B19: ='🛏 HPE Bed Board'!B13 -> Occupied | C19: =IF('🛏 HPE Bed Board'!C13="","",'🛏 HPE Bed Board'!C13) -> Rhonda Baim
A20: ='🛏 HPE Bed Board'!A14 -> H1-3A | B20: ='🛏 HPE Bed Board'!B14 -> Occupied | C20: =IF('🛏 HPE Bed Board'!C14="","",'🛏 HPE Bed Board'!C14) -> Aaron Dufresne
A21: ='🛏 HPE Bed Board'!A15 -> H1-3B | B21: ='🛏 HPE Bed Board'!B15 -> Open | C21: =IF('🛏 HPE Bed Board'!C15="","",'🛏 HPE Bed Board'!C15)
A22: ='🛏 HPE Bed Board'!A16 -> H1-4 | B22: ='🛏 HPE Bed Board'!B16 -> Occupied | C22: =IF('🛏 HPE Bed Board'!C16="","",'🛏 HPE Bed Board'!C16) -> Jared Hamilton
A23: ='🛏 HPE Bed Board'!A18 -> H2-2A | B23: ='🛏 HPE Bed Board'!B18 -> Reserved | C23: =IF('🛏 HPE Bed Board'!C18="","",'🛏 HPE Bed Board'!C18) -> Tara Shinde
A24: ='🛏 HPE Bed Board'!A19 -> H2-2B | B24: ='🛏 HPE Bed Board'!B19 -> Open | C24: =IF('🛏 HPE Bed Board'!C19="","",'🛏 HPE Bed Board'!C19)
A25: ='🛏 HPE Bed Board'!A20 -> H2-3A | B25: ='🛏 HPE Bed Board'!B20 -> Occupied | C25: =IF('🛏 HPE Bed Board'!C20="","",'🛏 HPE Bed Board'!C20) -> Daniel Armiger
A26: ='🛏 HPE Bed Board'!A21 -> H2-3B | B26: ='🛏 HPE Bed Board'!B21 -> Occupied | C26: =IF('🛏 HPE Bed Board'!C21="","",'🛏 HPE Bed Board'!C21) -> Blayne Olivier
A27: ='🛏 HPE Bed Board'!A22 -> H2-3C | B27: ='🛏 HPE Bed Board'!B22 -> Occupied | C27: =IF('🛏 HPE Bed Board'!C22="","",'🛏 HPE Bed Board'!C22) -> Bradey Bauer
A28: ='🛏 HPE Bed Board'!A23 -> H2-4 | B28: ='🛏 HPE Bed Board'!B23 -> Occupied | C28: =IF('🛏 HPE Bed Board'!C23="","",'🛏 HPE Bed Board'!C23) -> Jeongwoon Lee

Sheet 📈 YTD Rollup
A1: 📈 2026 ROLLING YTD — Admits by Rep by Month
A2: Jan–Apr = entered actuals (Marielle excluded — termed). May–Dec auto-count live from each month's Conversion Tracker tab. YTD, average & projection auto-calculate.
A4: REP | B4: Jan | C4: Feb | D4: Mar | E4: Apr | F4: May | G4: Jun | H4: Jul | I4: Aug | J4: Sep | K4: Oct | L4: Nov | M4: Dec | N4: YTD | O4: Avg/Mo | P4: Proj Yr
A5: Amy | B5: 5 | C5: 6 | D5: 8 | E5: 5 | F5: =COUNTIF('📋 May 2026'!$J$5:$J$60,$A5) -> 11 | G5: =IF(COUNTA('📋 Jun 2026'!$B$5:$B$60)=0,"",COUNTIF('📋 Jun 2026'!$J$5:$J$60,$A5)) -> 5 | H5: =IF(COUNTA('📋 Jul 2026'!$B$5:$B$60)=0,"",COUNTIF('📋 Jul 2026'!$J$5:$J$60,$A5)) | I5: =IF(COUNTA('📋 Aug 2026'!$B$5:$B$60)=0,"",COUNTIF('📋 Aug 2026'!$J$5:$J$60,$A5)) | J5: =IF(COUNTA('📋 Sep 2026'!$B$5:$B$60)=0,"",COUNTIF('📋 Sep 2026'!$J$5:$J$60,$A5)) | K5: =IF(COUNTA('📋 Oct 2026'!$B$5:$B$60)=0,"",COUNTIF('📋 Oct 2026'!$J$5:$J$60,$A5)) | L5: =IF(COUNTA('📋 Nov 2026'!$B$5:$B$60)=0,"",COUNTIF('📋 Nov 2026'!$J$5:$J$60,$A5)) | M5: =IF(COUNTA('📋 Dec 2026'!$B$5:$B$60)=0,"",COUNTIF('📋 Dec 2026'!$J$5:$J$60,$A5)) | N5: =SUM(B5:M5) -> 40 | O5: =IFERROR(ROUND(N5/COUNT(B5:M5),1),0) -> 6.7 | P5: =ROUND(O5*12,0) -> 80
A6: Nelson | B6: 4 | C6: 6 | D6: 7 | E6: 8 | F6: =COUNTIF('📋 May 2026'!$J$5:$J$60,$A6) -> 6 | G6: =IF(COUNTA('📋 Jun 2026'!$B$5:$B$60)=0,"",COUNTIF('📋 Jun 2026'!$J$5:$J$60,$A6)) -> 2 | H6: =IF(COUNTA('📋 Jul 2026'!$B$5:$B$60)=0,"",COUNTIF('📋 Jul 2026'!$J$5:$J$60,$A6)) | I6: =IF(COUNTA('📋 Aug 2026'!$B$5:$B$60)=0,"",COUNTIF('📋 Aug 2026'!$J$5:$J$60,$A6)) | J6: =IF(COUNTA('📋 Sep 2026'!$B$5:$B$60)=0,"",COUNTIF('📋 Sep 2026'!$J$5:$J$60,$A6)) | K6: =IF(COUNTA('📋 Oct 2026'!$B$5:$B$60)=0,"",COUNTIF('📋 Oct 2026'!$J$5:$J$60,$A6)) | L6: =IF(COUNTA('📋 Nov 2026'!$B$5:$B$60)=0,"",COUNTIF('📋 Nov 2026'!$J$5:$J$60,$A6)) | M6: =IF(COUNTA('📋 Dec 2026'!$B$5:$B$60)=0,"",COUNTIF('📋 Dec 2026'!$J$5:$J$60,$A6)) | N6: =SUM(B6:M6) -> 33 | O6: =IFERROR(ROUND(N6/COUNT(B6:M6),1),0) -> 5.5 | P6: =ROUND(O6*12,0) -> 66
A7: Matthew | B7: 0 | C7: 0 | D7: 0 | E7: 0 | F7: =COUNTIF('📋 May 2026'!$J$5:$J$60,$A7) -> 6 | G7: =IF(COUNTA('📋 Jun 2026'!$B$5:$B$60)=0,"",COUNTIF('📋 Jun 2026'!$J$5:$J$60,$A7)) -> 4 | H7: =IF(COUNTA('📋 Jul 2026'!$B$5:$B$60)=0,"",COUNTIF('📋 Jul 2026'!$J$5:$J$60,$A7)) | I7: =IF(COUNTA('📋 Aug 2026'!$B$5:$B$60)=0,"",COUNTIF('📋 Aug 2026'!$J$5:$J$60,$A7)) | J7: =IF(COUNTA('📋 Sep 2026'!$B$5:$B$60)=0,"",COUNTIF('📋 Sep 2026'!$J$5:$J$60,$A7)) | K7: =IF(COUNTA('📋 Oct 2026'!$B$5:$B$60)=0,"",COUNTIF('📋 Oct 2026'!$J$5:$J$60,$A7)) | L7: =IF(COUNTA('📋 Nov 2026'!$B$5:$B$60)=0,"",COUNTIF('📋 Nov 2026'!$J$5:$J$60,$A7)) | M7: =IF(COUNTA('📋 Dec 2026'!$B$5:$B$60)=0,"",COUNTIF('📋 Dec 2026'!$J$5:$J$60,$A7)) | N7: =SUM(B7:M7) -> 10 | O7: =IFERROR(ROUND(N7/COUNT(B7:M7),1),0) -> 1.7 | P7: =ROUND(O7*12,0) -> 20
A8: Amos | B8: 6 | C8: 2 | D8: 7 | E8: 4 | F8: =COUNTIF('📋 May 2026'!$J$5:$J$60,$A8) -> 5 | G8: =IF(COUNTA('📋 Jun 2026'!$B$5:$B$60)=0,"",COUNTIF('📋 Jun 2026'!$J$5:$J$60,$A8)) -> 0 | H8: =IF(COUNTA('📋 Jul 2026'!$B$5:$B$60)=0,"",COUNTIF('📋 Jul 2026'!$J$5:$J$60,$A8)) | I8: =IF(COUNTA('📋 Aug 2026'!$B$5:$B$60)=0,"",COUNTIF('📋 Aug 2026'!$J$5:$J$60,$A8)) | J8: =IF(COUNTA('📋 Sep 2026'!$B$5:$B$60)=0,"",COUNTIF('📋 Sep 2026'!$J$5:$J$60,$A8)) | K8: =IF(COUNTA('📋 Oct 2026'!$B$5:$B$60)=0,"",COUNTIF('📋 Oct 2026'!$J$5:$J$60,$A8)) | L8: =IF(COUNTA('📋 Nov 2026'!$B$5:$B$60)=0,"",COUNTIF('📋 Nov 2026'!$J$5:$J$60,$A8)) | M8: =IF(COUNTA('📋 Dec 2026'!$B$5:$B$60)=0,"",COUNTIF('📋 Dec 2026'!$J$5:$J$60,$A8)) | N8: =SUM(B8:M8) -> 24 | O8: =IFERROR(ROUND(N8/COUNT(B8:M8),1),0) -> 4 | P8: =ROUND(O8*12,0) -> 48
A9: Ahbra | B9: 0 | C9: 0 | D9: 0 | E9: 0 | F9: =COUNTIF('📋 May 2026'!$J$5:$J$60,$A9) -> 0 | G9: =IF(COUNTA('📋 Jun 2026'!$B$5:$B$60)=0,"",COUNTIF('📋 Jun 2026'!$J$5:$J$60,$A9)) -> 2 | H9: =IF(COUNTA('📋 Jul 2026'!$B$5:$B$60)=0,"",COUNTIF('📋 Jul 2026'!$J$5:$J$60,$A9)) | I9: =IF(COUNTA('📋 Aug 2026'!$B$5:$B$60)=0,"",COUNTIF('📋 Aug 2026'!$J$5:$J$60,$A9)) | J9: =IF(COUNTA('📋 Sep 2026'!$B$5:$B$60)=0,"",COUNTIF('📋 Sep 2026'!$J$5:$J$60,$A9)) | K9: =IF(COUNTA('📋 Oct 2026'!$B$5:$B$60)=0,"",COUNTIF('📋 Oct 2026'!$J$5:$J$60,$A9)) | L9: =IF(COUNTA('📋 Nov 2026'!$B$5:$B$60)=0,"",COUNTIF('📋 Nov 2026'!$J$5:$J$60,$A9)) | M9: =IF(COUNTA('📋 Dec 2026'!$B$5:$B$60)=0,"",COUNTIF('📋 Dec 2026'!$J$5:$J$60,$A9)) | N9: =SUM(B9:M9) -> 2 | O9: =IFERROR(ROUND(N9/COUNT(B9:M9),1),0) -> 0.3 | P9: =ROUND(O9*12,0) -> 4
A10: TEAM | B10: =SUM(B5:B9) -> 15 | C10: =SUM(C5:C9) -> 14 | D10: =SUM(D5:D9) -> 22 | E10: =SUM(E5:E9) -> 17 | F10: =SUM(F5:F9) -> 28 | G10: =SUM(G5:G9) -> 13 | H10: =SUM(H5:H9) -> 0 | I10: =SUM(I5:I9) -> 0 | ... P10: =SUM(P5:P9) -> 218

Sheet 📋 Insurance & Rates
A1: 📋 ADMISSION CONTROL | INSURANCE CONTRACTS & RATES — HP & HPE
A2: 🟢 OK TO ADMIT | 🔴 DO NOT ADMIT | 🟡 OON / Pending | Updated from Google Sheets bed board — Last reviewed May 2026
A4: 💰 CONTRACTED RATES — Per Diem by Level of Care
A5: Rates shown are contracted per diem rates. Verify current rates with billing before admission.
A6: Insurance | B6: Detox (DTX) | C6: RTC/Res | D6: PHP | E6: IOP | F6: Notes
A7: Anthem | B7: $1,224 | C7: $1,122 | D7: $816 | E7: $434 | F7: Detox $1,200 | RTC $1,100
A8: Blue Shield | B8: — | C8: $700 | D8: $400 | E8: $300 | F8: CARF required for DTX
A9: Aetna | B9: — | C9: $725 | D9: $450 | E9: $345 | F9: Detox eff 6/1/2023 at HP
A10: Kaiser | B10: $1,020 | C10: $945 | D10: $473 | E10: $341 | F10: DTX + RTC only — no PHP
A11: Carelon/Beacon | B11: $700 | C11: $595 | D11: $285 | E11: — | F11: HP: RTC + PHP only (no DTX)
A12: Humana | B12: $920 | C12: $550 | D12: $450 | E12: — | F12: DO NOT ADMIT — no longer accepting
A13: First Health | B13: $1,500 | C13: $1,050 | D13: $550 | E13: $375 | F13: Carve-out
A14: HMC/Uprise | B14: $1,300 | C14: $700 | D14: $475 | E14: $350 | F14: HPE only for DTX+RTC — under Manifest
A15: Optum (HP only) | B15: — | C15: $951 | D15: $452 | E15: $299 | F15: HP only — HPE OON
A16: Cigna/Evernorth | B16: $1,003 | C16: $750 | D16: $500 | E16: — | F16: HP only — HPE OON per Jeff
A17: Molina | B17: $900 | C17: $1,100 | D17: $350 | E17: $200 | F17: Eff 11/1/2024 all locations
... A20: Tricare/TriWest | B20: — | C20: ✅ | D20: ✅ | E20: — | F20: *Pre-auth req for DTX — eff 11/1/2025
A22: 🏥 HP — HARMONY PLACE (Hatteras) | JMG Investments TIN: 38-3941572 NPI: 1386041580
A23: Payer / Insurance | B23: Eff. Date | C23: DTX | D23: RTC | E23: PHP | F23: IOP | G23: Notes
A24: ✅ Aetna | B24: 8/15/2022 | C24: X | D24: X | E24: X | F24: — | G24: Detox eff 6/1/2023 | SUD & MH
A25: ✅ Anthem | B25: 3/15/2021 | C25: X | D25: X | E25: X | F25: — | G25: Under Monterey contract | PHP added 3/4/22
A26: ✅ Blue Shield | B26: 10/15/2025 | C26: — | D26: X | E26: X | F26: — | G26: CARF required for Detox
A27: ✅ Carelon/Beacon | B27: 9/30/2022 | C27: — | D27: X | E27: X | F27: — | G27: No DTX as of 1/19/2024
A28: ✅ Cigna/Evernorth | B28: 8/10/2024 | C28: X | D28: X | E28: X | F28: — | G28: Covers both 23041 & 23043
A29: ✅ ComPsych | B29: 3/23/2021 | C29: X | D29: X | E29: X | F29: —
A30: ✅ First Health | B30: 11/15/2021 | C30: X | D30: X | E30: X | F30: — | G30: RTC = SUD & MH
A31: 🔴 HealthNet | B31: N/A | C31: — | D31: — | E31: — | F31: — | G31: Application on hold Q4 2025
A32: 🔴 Kaiser | B32: 12/1/2023 | C32: — | D32: — | E32: — | F32: — | G32: No longer INN — DO NOT ADMIT
A33: 🔴 HMC/Uprise | B33: N/A | C33: — | D33: — | E33: — | F33: — | G33: DO NOT ADMIT
A34: 🔴 Humana | B34: OON | C34: — | D34: — | E34: — | F34: — | G34: DO NOT ADMIT — OON
A35: ✅ Magellan | B35: 5/16/2025 | C35: X | D35: X | E35: X | F35: — | G35: RTC = SUD & MH
A36: 🔴 MHN | B36: Cancelled | C36: — | D36: — | E36: — | F36: — | G36: CONTRACT CANCELLED BY PAYER
A37: ✅ Molina | B37: 11/1/2024 | C37: X | D37: X | E37: X | F37: —
A38: ✅ Multiplan | B38: 10/15/2019 | C38: X | D38: X | E38: X | F38: — | G38: PHP & RTC = SUD & MH
A39: ✅ Optum | B39: 7/15/2024 | C39: — | D39: X | E39: — | F39: — | G39: RTC 3.5 only — No DTX
A40: 🔵 Oscar | B40: OON | C40: — | D40: — | E40: — | F40: — | G40: Applications in progress
A41: ✅ Tricare/TriWest | B41: 11/1/2025 | C41: * | D41: X | E41: X | F41: — | G41: *Pre-auth req for DTX
A43: 🏥 HPE — HARMONY PLACE EAST (Burbank) | Dolorosa Operations TIN: 81-2343037 NPI: 1932656170
A44: Payer / Insurance | B44: Eff. Date | C44: DTX | D44: RTC | E44: PHP | F44: IOP | G44: Notes
A45: ✅ Aetna | B45: 6/1/2023 | C45: X | D45: X | E45: X | F45: — | G45: Both 22913 & 22915 loaded — confirmed 6/5/23
A46: ✅ Anthem | B46: 11/18/2022 | C46: X | D46: X | E46: X | F46: — | G46: PHP updated 2/9/2024 | Address updated to Burbank
A47: ✅ Blue Shield | B47: 10/15/2025 | C47: — | D47: X | E47: X | F47: — | G47: CARF required for Detox
A48: ✅ Carelon/Beacon | B48: 4/14/2023 | C48: X | D48: X | E48: — | F48: — | G48: No PHP
A49: 🟡 Cigna/Evernorth | B49: OON | C49: — | D49: — | E49: — | F49: — | G49: Jeff wants to stay OON at this location
A50: ✅ ComPsych | B50: 3/23/2021 | C50: X | D50: X | E50: — | F50: — | G50: Address updated to Burbank Blvd
A51: ✅ First Health | B51: 11/1/2022 | C51: X | D51: X | E51: X | F51: — | G51: Rates confirmed & loaded 5/30/23
A52: 🔴 HealthNet | B52: N/A | C52: — | D52: — | E52: — | F52: — | G52: Application on hold Q4 2025
A53: 🔴 Kaiser | B53: 12/1/2023 | C53: — | D53: — | E53: — | F53: — | G53: No longer INN — DO NOT ADMIT
A54: 🔴 HMC/Uprise | B54: N/A | C54: — | D54: — | E54: — | F54: — | G54: Still under Manifest — unresponsive
A55: 🔴 Humana | B55: OON | C55: — | D55: — | E55: — | F55: — | G55: DO NOT ADMIT — OON
A56: ✅ Magellan | B56: 6/3/2025 | C56: X | D56: X | E56: X | F56: —
A57: 🔴 MHN | B57: Cancelled | C57: — | D57: — | E57: — | F57: — | G57: CONTRACT CANCELLED BY PAYER
A58: ✅ Molina | B58: 11/1/2024 | C58: X | D58: X | E58: X | F58: — | G58: Agreement received 11/7/24
A59: ✅ Multiplan | B59: 3/27/2023 | C59: X | D59: X | E59: — | F59: — | G59: 22915 added 4/4/23
A60: 🟡 Optum | B60: OON | C60: — | D60: — | E60: — | F60: — | G60: Per Jeff Schwartz — stay OON
A61: ✅ Tricare/TriWest | B61: 11/1/2025 | C61: * | D61: X | E61: X | F61: — | G61: *Pre-auth req for DTX
A63: 🏥 VRC — VALLEY RESTORATION CENTER (Woodland Hills) | NPI: 1417328618 TIN: 47-5188505 | PHP & IOP ONLY — No DTX/RTC
A64: Payer / Insurance | B64: Eff. Date | C64: DTX | D64: RTC | E64: PHP | F64: IOP | G64: Notes
A65: ✅ Aetna | B65: 8/1/2022 | C65: — | D65: — | E65: X | F65: X | G65: SUD & MH
A66: ✅ Anthem | B66: 2/9/2024 | C66: — | D66: — | E66: X | F66: X | G66: SUD & MH
A67: ✅ Carelon/Beacon | B67: 11/29/2022 | C67: — | D67: — | E67: X | F67: X
A68: ✅ Cigna/Evernorth | B68: 7/30/2024 | C68: — | D68: — | E68: X | F68: X | G68: SUD & MH
A69: ✅ ComPsych | B69: 3/23/2021 | C69: — | D69: — | E69: X | F69: X | G69: SUD & Dual Dx
A70: ✅ First Health | B70: 8/1/2022 | C70: — | D70: — | E70: X | F70: X | G70: SUD & MH
A71: 🔴 HealthNet | B71: N/A | C71: — | D71: — | E71: — | F71: — | G71: Application on hold
A72: ✅ Kaiser | B72: 12/1/2023 | C72: — | D72: — | E72: X | F72: X
A73: 🔴 HMC/Uprise | B73: OON | C73: — | D73: — | E73: — | F73: — | G73: OON
A74: 🔴 Humana | B74: OON | C74: — | D74: — | E74: — | F74: — | G74: DO NOT ADMIT
A75: ✅ Magellan | B75: 3/19/2025 | C75: — | D75: — | E75: X | F75: X | G75: SUD & MH
A76: ✅ Molina | B76: 3/1/2025 | C76: — | D76: — | E76: X | F76: X | G76: SUD & MH
A77: ✅ Multiplan | B77: 11/15/2019 | C77: — | D77: — | E77: X | F77: X | G77: PHP & IOP = SUD & MH
A78: ✅ Optum | B78: 8/15/2024 | C78: — | D78: — | E78: X | F78: X | G78: SUD & MH
A80: 🔍 INSURANCE PREFIX LOOKUP — Identify carrier from member ID prefix
A81: Use the 3-letter prefix on the insurance card to quickly identify the correct carrier and whether we can admit
A82: Prefix | B82: Carrier | C82: State | D82: Type | E82: Carve-Out | F82: Can Admit? | G82: Notes
A83: JQO | B83: Anthem | C83: California | D83: HMO | E83: — | F83: NO | G83: Pathways — DO NOT ADMIT
A84: JQU | B84: Anthem | C84: California | D84: PPO | E84: — | F84: YES | G84: Anthem CA Group policy
A85: MPI | B85: Anthem | C85: California | D85: PPO | E85: Optum | F85: YES | G85: Motion Picture Industry — OON at HPE
A86: NCF | B86: Anthem | C86: California | D86: Any | E86: — | F86: YES | G86: LAUSD / City of LA
A87: NSA | B87: Anthem | C87: California | D87: PPO | E87: Carelon/Beacon | F87: YES | G87: SAG policies
A88: WRX | B88: Anthem | C88: California | D88: — | E88: — | F88: YES | G88: Writer's Guild policy
A89: XED | B89: Blue Shield | C89: California | D89: PPO | E89: Magellan | F89: YES | G89: Has OON benefits
A90: XEH | B90: Blue Shield | C90: California | D90: HMO | E90: Magellan | F90: YES | G90: Run VOB to confirm Magellan
A91: XEK | B91: Blue Shield | C91: California | D91: PPO | E91: Magellan | F91: YES | G91: Private insurance, off exchange
A92: XEO | B92: Blue Shield | C92: California | D92: HMO | E92: Magellan | F92: YES | G92: On exchange
A93: XEQ | B93: Blue Shield | C93: California | D93: HMO | E93: Magellan | F93: YES | G93: Marketplace CA Blue Shield Trio HMO
A94: BEG | B94: BCBS | C94: Alabama | D94: PPO | E94: — | F94: PARTIAL | G94: Only covers PHP/IOP
A95: GHP | B95: BCBS | C95: Michigan | D95: — | E95: — | F95: YES
A96: QMF | B96: BCBS | C96: Illinois | D96: Both | E96: — | F96: NO | G96: HMO = no OOS benefits; PPO very difficult
A97: YUQ | B97: BCBS | C97: Oklahoma | D97: Any | E97: — | F97: NO | G97: No OOS benefits as of Jan 1 2025
A98: YUN | B98: BCBS | C98: Oklahoma | D98: Any | E98: — | F98: NO
A100: ⛔ DO NOT ADMIT — Anthem/BCBS Plans That Are Excluded
A101: Plan | B101: Reason
A102: BCBS Delaware | B102: Do not accept for any LOC
A103: BCBS Oklahoma | B103: Do not accept for any LOC
A104: BCBS Alabama | B104: Only covers PHP/IOP — no DTX/RTC
A105: BCBS Montana | B105: Do not accept for any LOC
A106: BCBS North Carolina | B106: Do not accept for any LOC
A107: BCBS Federal | B107: Do not accept for any LOC
A108: Anthem HMO Select Plus | B108: Do not accept for any LOC
...

Sheet 📅 Schedule
A1: 🗓 HARMONY PLACE ADMISSIONS — TEAM SCHEDULE | Amos Leave Period (May–Aug 2026)
A2: Amy: 40hrs/wk · Nelson: 40hrs/wk · Matthew: 22hrs/wk (Wed eve + Sat/Sun) · Ahbra: 7hrs/wk PRN (Mon/Thu/Fri eves) · ROR = Ring of Responsibility
B4: Monday | E4: Tuesday | G4: Wednesday | J4: Thursday | M4: Friday | P4: Saturday | Q4: Sunday
A5: TIME | B5: Amy | C5: Nelson | D5: Ahbra | E5: Amy | F5: Nelson | G5: Amy | H5: Nelson | I5: Matthew | J5: Amy | K5: Nelson | L5: Ahbra | M5: Amy | N5: Nelson | O5: Ahbra | P5: Matthew | Q5: Matthew
A6: 7:00 AM | B6: ROR | C6: ROR | D6: ROR | E6: ROR | F6: ROR | G6: ROR | H6: ROR | I6: ROR | J6: ROR | K6: ROR | L6: ROR | M6: ROR | N6: ROR | O6: ROR | P6: ROR | Q6: ROR
A7: 9:00 AM | C7: 9am–6pm | E7: 11am–7pm | F7: 9am–5pm | G7: 9am–5pm | H7: 9am–5pm | J7: 9am–5pm | K7: 9am–4pm | N7: 9am–5pm | P7: 9am–7pm | Q7: 9am–7pm
A8: 10:00 AM | B8: 10am–6pm | M8: 10am–6pm
A9: 12:00 PM
A10: 2:00 PM | D10: 2–5pm PRN | O10: 2–5pm PRN
A11: 4:00 PM | L11: 4–7pm ⭐ Weekly Mtg
A12: 5:00 PM | D12: 5–7pm ⭐ Weekly Mtg | I12: 5–7pm | K12: ⭐ Weekly Mtg | O12: 5–7pm ⭐ Weekly Mtg
A13: 6:00 PM | J13: ⭐ Admissions Meeting
A14: 7:00 PM | B14: ROR | C14: ROR | D14: ROR | E14: ROR | F14: ROR | G14: ROR | H14: ROR | I14: ROR | J14: ROR | K14: ROR | L14: ROR | M14: ROR | N14: ROR | O14: ROR | P14: ROR | Q14: ROR
A16: ⚠️ SCHEDULE EXCEPTIONS & AHBRA CONFLICTS
A17: Fri May 29 | B17: Amy 11am–7pm | J17: → Ahbra at WCSAD
A18: Thu Jun 11 | B18: Matthew 5–7pm covers | J18: → Ahbra has H&I
A19: Mon Jun 15 | B19: Amy 11am–7pm | J19: → Ahbra H&I — last meeting as chair
A20: Thu Jul 2 | B20: Matthew 5–7pm covers | J20: → Ahbra surgery Jun 30
A21: Thu Jul 9 | B21: Matthew 5–7pm covers | J21: → Ahbra has H&I
A22: Thu Aug 13 | B22: Matthew 5–7pm covers | J22: → Ahbra has H&I

Sheet 📱 Mobile View
A1: 🏥 HARMONY PLACE — LIVE BED STATUS
A2: ="HP: "&COUNTIF('🛏 HP Bed Board'!B10:B23,"Occupied")&"/14 · HPE: "&(COUNTIF('🛏 HPE Bed Board'!B11:B16,"Occupied")+COUNTIF('🛏 HPE Bed Board'!B18:B23,"Occupied"))&"/12 · Total: "&(COUNTIF('🛏 HP Bed Board'!B10:B23,"Occupied")+(COUNTIF('🛏 HPE Bed Board'!B11:B16,"Occupied")+COUNTIF('🛏 HPE Bed Board'!B18:B23,"Occupied")))&"/26" -> HP: 11/14 · HPE: 9/12 · Total: 20/26
A3: =IF((COUNTIFS('🛏 HP Bed Board'!B10:B23,"Occupied",'🛏 HP Bed Board'!H10:H23,">="&TODAY(),'🛏 HP Bed Board'!H10:H23,"<="&TODAY()+7)+COUNTIFS('🛏 HPE Bed Board'!B11:B16,"Occupied",'🛏 HPE Bed Board'!H11:H16,">="&TODAY(),'🛏 HPE Bed Board'!H11:H16,"<="&TODAY()+7)+COUNTIFS('🛏 HPE Bed Board'!B18:B23,"Occupied",'🛏 HPE Bed Board'!H18:H23,">="&TODAY(),'🛏 HPE Bed Board'!H18:H23,"<="&TODAY()+7))=0,"✅ No discharges in next 7 days",(COUNTIFS('🛏 HP Bed Board'!B10:B23,"Occupied",'🛏 HP Bed Board'!H10:H23,">="&TODAY(),'🛏 HP Bed Board'!H10:H23,"<="&TODAY()+7)+COUNTIFS('🛏 HPE Bed Board'!B11:B16,"Occupied",'🛏 HPE Bed Board'!H11:H16,">="&TODAY(),'🛏 HPE Bed Board'!H11:H16,"<="&TODAY()+7)+COUNTIFS('🛏 HPE Bed Board'!B18:B23,"Occupied",'🛏 HPE Bed Board'!H18:H23,">="&TODAY(),'🛏 HPE Bed Board'!H18:H23,"<="&TODAY()+7))&" client(s) DC within 7 days") -> 4 client(s) DC within 7 days
A5: 🛏 HP — HATTERAS ST (14 beds)
A6: ROOM | B6: CLIENT | C6: LOC | D6: DC / DAYS
A7: ='🛏 HP Bed Board'!A10 -> DTX-A | B7: =IF('🛏 HP Bed Board'!B10="Occupied",'🛏 HP Bed Board'!C10,IF('🛏 HP Bed Board'!B10="Reserved","Reserved: "&'🛏 HP Bed Board'!C10,IF('🛏 HP Bed Board'!B10="Open","— open —",""))) -> — open — | C7: =IF('🛏 HP Bed Board'!B10="Occupied",IF('🛏 HP Bed Board'!F10<>"",'🛏 HP Bed Board'!F10,'🛏 HP Bed Board'!E10),"") | D7: =IF('🛏 HP Bed Board'!B10="Occupied",IF('🛏 HP Bed Board'!H10="","—",IF('🛏 HP Bed Board'!H10<TODAY(),"PAST",IF('🛏 HP Bed Board'!H10=TODAY(),"TODAY","DC "&TEXT('🛏 HP Bed Board'!H10,"M/D")&" ("&INT('🛏 HP Bed Board'!H10-TODAY())&"d)"))),"—") -> —
A8: ='🛏 HP Bed Board'!A11 -> DTX-B | B8: =IF('🛏 HP Bed Board'!B11="Occupied",'🛏 HP Bed Board'!C11,IF('🛏 HP Bed Board'!B11="Reserved","Reserved: "&'🛏 HP Bed Board'!C11,IF('🛏 HP Bed Board'!B11="Open","— open —",""))) -> — open — | C8: =IF('🛏 HP Bed Board'!B11="Occupied",IF('🛏 HP Bed Board'!F11<>"",'🛏 HP Bed Board'!F11,'🛏 HP Bed Board'!E11),"") | D8: =IF('🛏 HP Bed Board'!B11="Occupied",IF('🛏 HP Bed Board'!H11="","—",IF('🛏 HP Bed Board'!H11<TODAY(),"PAST",IF('🛏 HP Bed Board'!H11=TODAY(),"TODAY","DC "&TEXT('🛏 HP Bed Board'!H11,"M/D")&" ("&INT('🛏 HP Bed Board'!H11-TODAY())&"d)"))),"—") -> —
A9: ='🛏 HP Bed Board'!A12 -> M1-A | B9: =IF('🛏 HP Bed Board'!B12="Occupied",'🛏 HP Bed Board'!C12,IF('🛏 HP Bed Board'!B12="Reserved","Reserved: "&'🛏 HP Bed Board'!C12,IF('🛏 HP Bed Board'!B12="Open","— open —",""))) -> Kurt Guisler | C9: =IF('🛏 HP Bed Board'!B12="Occupied",IF('🛏 HP Bed Board'!F12<>"",'🛏 HP Bed Board'!F12,'🛏 HP Bed Board'!E12),"") -> DTX/RTC | D9: =IF('🛏 HP Bed Board'!B12="Occupied",IF('🛏 HP Bed Board'!H12="","—",IF('🛏 HP Bed Board'!H12<TODAY(),"PAST",IF('🛏 HP Bed Board'!H12=TODAY(),"TODAY","DC "&TEXT('🛏 HP Bed Board'!H12,"M/D")&" ("&INT('🛏 HP Bed Board'!H12-TODAY())&"d)"))),"—") -> DC 6/28 (11d)
A10: ='🛏 HP Bed Board'!A13 -> M1-B | B10: =IF('🛏 HP Bed Board'!B13="Occupied",'🛏 HP Bed Board'!C13,IF('🛏 HP Bed Board'!B13="Reserved","Reserved: "&'🛏 HP Bed Board'!C13,IF('🛏 HP Bed Board'!B13="Open","— open —",""))) -> Pedro Mendoza | C10: =IF('🛏 HP Bed Board'!B13="Occupied",IF('🛏 HP Bed Board'!F13<>"",'🛏 HP Bed Board'!F13,'🛏 HP Bed Board'!E13),"") -> DTX/RTC | D10: =IF('🛏 HP Bed Board'!B13="Occupied",IF('🛏 HP Bed Board'!H13="","—",IF('🛏 HP Bed Board'!H13<TODAY(),"PAST",IF('🛏 HP Bed Board'!H13=TODAY(),"TODAY","DC "&TEXT('🛏 HP Bed Board'!H13,"M/D")&" ("&INT('🛏 HP Bed Board'!H13-TODAY())&"d)"))),"—") -> DC 7/2 (15d)
A11: ='🛏 HP Bed Board'!A14 -> M2-A | B11: =IF('🛏 HP Bed Board'!B14="Occupied",'🛏 HP Bed Board'!C14,IF('🛏 HP Bed Board'!B14="Reserved","Reserved: "&'🛏 HP Bed Board'!C14,IF('🛏 HP Bed Board'!B14="Open","— open —",""))) -> — open — | C11: =IF('🛏 HP Bed Board'!B14="Occupied",IF('🛏 HP Bed Board'!F14<>"",'🛏 HP Bed Board'!F14,'🛏 HP Bed Board'!E14),"") | D11: =IF('🛏 HP Bed Board'!B14="Occupied",IF('🛏 HP Bed Board'!H14="","—",IF('🛏 HP Bed Board'!H14<TODAY(),"PAST",IF('🛏 HP Bed Board'!H14=TODAY(),"TODAY","DC "&TEXT('🛏 HP Bed Board'!H14,"M/D")&" ("&INT('🛏 HP Bed Board'!H14-TODAY())&"d)"))),"—") -> —
A12: ='🛏 HP Bed Board'!A15 -> M2-B | B12: =IF('🛏 HP Bed Board'!B15="Occupied",'🛏 HP Bed Board'!C15,IF('🛏 HP Bed Board'!B15="Reserved","Reserved: "&'🛏 HP Bed Board'!C15,IF('🛏 HP Bed Board'!B15="Open","— open —",""))) -> Darian Loehner | C12: =IF('🛏 HP Bed Board'!B15="Occupied",IF('🛏 HP Bed Board'!F15<>"",'🛏 HP Bed Board'!F15,'🛏 HP Bed Board'!E15),"") -> DTX | D12: =IF('🛏 HP Bed Board'!B15="Occupied",IF('🛏 HP Bed Board'!H15="","—",IF('🛏 HP Bed Board'!H15<TODAY(),"PAST",IF('🛏 HP Bed Board'!H15=TODAY(),"TODAY","DC "&TEXT('🛏 HP Bed Board'!H15,"M/D")&" ("&INT('🛏 HP Bed Board'!H15-TODAY())&"d)"))),"—") -> DC 6/20 (3d)
A13: ='🛏 HP Bed Board'!A16 -> M3-A | B13: =IF('🛏 HP Bed Board'!B16="Occupied",'🛏 HP Bed Board'!C16,IF('🛏 HP Bed Board'!B16="Reserved","Reserved: "&'🛏 HP Bed Board'!C16,IF('🛏 HP Bed Board'!B16="Open","— open —",""))) -> Jill Labate | C13: =IF('🛏 HP Bed Board'!B16="Occupied",IF('🛏 HP Bed Board'!F16<>"",'🛏 HP Bed Board'!F16,'🛏 HP Bed Board'!E16),"") -> DTX/RTC | D13: =IF('🛏 HP Bed Board'!B16="Occupied",IF('🛏 HP Bed Board'!H16="","—",IF('🛏 HP Bed Board'!H16<TODAY(),"PAST",IF('🛏 HP Bed Board'!H16=TODAY(),"TODAY","DC "&TEXT('🛏 HP Bed Board'!H16,"M/D")&" ("&INT('🛏 HP Bed Board'!H16-TODAY())&"d)"))),"—") -> DC 7/5 (18d)
A14: ='🛏 HP Bed Board'!A17 -> M3-B | B14: =IF('🛏 HP Bed Board'!B17="Occupied",'🛏 HP Bed Board'!C17,IF('🛏 HP Bed Board'!B17="Reserved","Reserved: "&'🛏 HP Bed Board'!C17,IF('🛏 HP Bed Board'!B17="Open","— open —",""))) -> Monica Gamboa | C14: =IF('🛏 HP Bed Board'!B17="Occupied",IF('🛏 HP Bed Board'!F17<>"",'🛏 HP Bed Board'!F17,'🛏 HP Bed Board'!E17),"") -> DTX/RTC | D14: =IF('🛏 HP Bed Board'!B17="Occupied",IF('🛏 HP Bed Board'!H17="","—",IF('🛏 HP Bed Board'!H17<TODAY(),"PAST",IF('🛏 HP Bed Board'!H17=TODAY(),"TODAY","DC "&TEXT('🛏 HP Bed Board'!H17,"M/D")&" ("&INT('🛏 HP Bed Board'!H17-TODAY())&"d)"))),"—") -> DC 6/21 (4d)
A15: ='🛏 HP Bed Board'!A18 -> B1-A | B15: =IF('🛏 HP Bed Board'!B18="Occupied",'🛏 HP Bed Board'!C18,IF('🛏 HP Bed Board'!B18="Reserved","Reserved: "&'🛏 HP Bed Board'!C18,IF('🛏 HP Bed Board'!B18="Open","— open —",""))) -> Bradey Bauer | C15: =IF('🛏 HP Bed Board'!B18="Occupied",IF('🛏 HP Bed Board'!F18<>"",'🛏 HP Bed Board'!F18,'🛏 HP Bed Board'!E18),"") -> DTX/RTC | D15: =IF('🛏 HP Bed Board'!B18="Occupied",IF('🛏 HP Bed Board'!H18="","—",IF('🛏 HP Bed Board'!H18<TODAY(),"PAST",IF('🛏 HP Bed Board'!H18=TODAY(),"TODAY","DC "&TEXT('🛏 HP Bed Board'!H18,"M/D")&" ("&INT('🛏 HP Bed Board'!H18-TODAY())&"d)"))),"—") -> DC 7/13 (26d)
A16: ='🛏 HP Bed Board'!A19 -> B1-B | B16: =IF('🛏 HP Bed Board'!B19="Occupied",'🛏 HP Bed Board'!C19,IF('🛏 HP Bed Board'!B19="Reserved","Reserved: "&'🛏 HP Bed Board'!C19,IF('🛏 HP Bed Board'!B19="Open","— open —",""))) -> Garrett Johnson | C16: =IF('🛏 HP Bed Board'!B19="Occupied",IF('🛏 HP Bed Board'!F19<>"",'🛏 HP Bed Board'!F19,'🛏 HP Bed Board'!E19),"") -> RTC | D16: =IF('🛏 HP Bed Board'!B19="Occupied",IF('🛏 HP Bed Board'!H19="","—",IF('🛏 HP Bed Board'!H19<TODAY(),"PAST",IF('🛏 HP Bed Board'!H19=TODAY(),"TODAY","DC "&TEXT('🛏 HP Bed Board'!H19,"M/D")&" ("&INT('🛏 HP Bed Board'!H19-TODAY())&"d)"))),"—") -> DC 7/13 (26d)
A17: ='🛏 HP Bed Board'!A20 -> B2-A | B17: =IF('🛏 HP Bed Board'!B20="Occupied",'🛏 HP Bed Board'!C20,IF('🛏 HP Bed Board'!B20="Reserved","Reserved: "&'🛏 HP Bed Board'!C20,IF('🛏 HP Bed Board'!B20="Open","— open —",""))) -> Kyle Samia | C17: =IF('🛏 HP Bed Board'!B20="Occupied",IF('🛏 HP Bed Board'!F20<>"",'🛏 HP Bed Board'!F20,'🛏 HP Bed Board'!E20),"") -> DTX/RTC | D17: =IF('🛏 HP Bed Board'!B20="Occupied",IF('🛏 HP Bed Board'!H20="","—",IF('🛏 HP Bed Board'!H20<TODAY(),"PAST",IF('🛏 HP Bed Board'!H20=TODAY(),"TODAY","DC "&TEXT('🛏 HP Bed Board'!H20,"M/D")&" ("&INT('🛏 HP Bed Board'!H20-TODAY())&"d)"))),"—") -> DC 7/11 (24d)
A18: ='🛏 HP Bed Board'!A21 -> B2-B | B18: =IF('🛏 HP Bed Board'!B21="Occupied",'🛏 HP Bed Board'!C21,IF('🛏 HP Bed Board'!B21="Reserved","Reserved: "&'🛏 HP Bed Board'!C21,IF('🛏 HP Bed Board'!B21="Open","— open —",""))) -> Jamal Williams | C18: =IF('🛏 HP Bed Board'!B21="Occupied",IF('🛏 HP Bed Board'!F21<>"",'🛏 HP Bed Board'!F21,'🛏 HP Bed Board'!E21),"") -> DTX/RTC | D18: =IF('🛏 HP Bed Board'!B21="Occupied",IF('🛏 HP Bed Board'!H21="","—",IF('🛏 HP Bed Board'!H21<TODAY(),"PAST",IF('🛏 HP Bed Board'!H21=TODAY(),"TODAY","DC "&TEXT('🛏 HP Bed Board'!H21,"M/D")&" ("&INT('🛏 HP Bed Board'!H21-TODAY())&"d)"))),"—") -> DC 7/10 (23d)
... A20: ='🛏 HP Bed Board'!A23 -> B3-B | B20: =IF('🛏 HP Bed Board'!B23="Occupied",'🛏 HP Bed Board'!C23,IF('🛏 HP Bed Board'!B23="Reserved","Reserved: "&'🛏 HP Bed Board'!C23,IF('🛏 HP Bed Board'!B23="Open","— open —",""))) -> Jason Schnell | C20: =IF('🛏 HP Bed Board'!B23="Occupied",IF('🛏 HP Bed Board'!F23<>"",'🛏 HP Bed Board'!F23,'🛏 HP Bed Board'!E23),"") -> DTX/RTC | D20: =IF('🛏 HP Bed Board'!B23="Occupied",IF('🛏 HP Bed Board'!H23="","—",IF('🛏 HP Bed Board'!H23<TODAY(),"PAST",IF('🛏 HP Bed Board'!H23=TODAY(),"TODAY","DC "&TEXT('🛏 HP Bed Board'!H23,"M/D")&" ("&INT('🛏 HP Bed Board'!H23-TODAY())&"d)"))),"—") -> DC 6/30 (13d)
A22: 🛏 HPE — BURBANK BLVD (12 beds)
A23: ROOM | B23: CLIENT | C23: LOC | D23: DC / DAYS
A24: ='🛏 HPE Bed Board'!A11 -> H1-1A | B24: =IF('🛏 HPE Bed Board'!B11="Occupied",'🛏 HPE Bed Board'!C11,IF('🛏 HPE Bed Board'!B11="Reserved","Reserved: "&'🛏 HPE Bed Board'!C11,IF('🛏 HPE Bed Board'!B11="Open","— open —",""))) -> Allisa Leuvrey | C24: =IF('🛏 HPE Bed Board'!B11="Occupied",IF('🛏 HPE Bed Board'!F11<>"",'🛏 HPE Bed Board'!F11,'🛏 HPE Bed Board'!E11),"") -> DTX | D24: =IF('🛏 HPE Bed Board'!B11="Occupied",IF('🛏 HPE Bed Board'!H11="","—",IF('🛏 HPE Bed Board'!H11<TODAY(),"PAST",IF('🛏 HPE Bed Board'!H11=TODAY(),"TODAY","DC "&TEXT('🛏 HPE Bed Board'!H11,"M/D")&" ("&INT('🛏 HPE Bed Board'!H11-TODAY())&"d)"))),"—") -> DC 6/19 (2d)
A25: ='🛏 HPE Bed Board'!A12 -> H1-1B | B25: =IF('🛏 HPE Bed Board'!B12="Occupied",'🛏 HPE Bed Board'!C12,IF('🛏 HPE Bed Board'!B12="Reserved","Reserved: "&'🛏 HPE Bed Board'!C12,IF('🛏 HPE Bed Board'!B12="Open","— open —",""))) -> Cree Lamere | C25: =IF('🛏 HPE Bed Board'!B12="Occupied",IF('🛏 HPE Bed Board'!F12<>"",'🛏 HPE Bed Board'!F12,'🛏 HPE Bed Board'!E12),"") -> DTX/RTC | D25: =IF('🛏 HPE Bed Board'!B12="Occupied",IF('🛏 HPE Bed Board'!H12="","—",IF('🛏 HPE Bed Board'!H12<TODAY(),"PAST",IF('🛏 HPE Bed Board'!H12=TODAY(),"TODAY","DC "&TEXT('🛏 HPE Bed Board'!H12,"M/D")&" ("&INT('🛏 HPE Bed Board'!H12-TODAY())&"d)"))),"—") -> DC 6/29 (12d)
A26: ='🛏 HPE Bed Board'!A13 -> H1-2A | B26: =IF('🛏 HPE Bed Board'!B13="Occupied",'🛏 HPE Bed Board'!C13,IF('🛏 HPE Bed Board'!B13="Reserved","Reserved: "&'🛏 HPE Bed Board'!C13,IF('🛏 HPE Bed Board'!B13="Open","— open —",""))) -> Rhonda Baim | C26: =IF('🛏 HPE Bed Board'!B13="Occupied",IF('🛏 HPE Bed Board'!F13<>"",'🛏 HPE Bed Board'!F13,'🛏 HPE Bed Board'!E13),"") -> DTX | D26: =IF('🛏 HPE Bed Board'!B13="Occupied",IF('🛏 HPE Bed Board'!H13="","—",IF('🛏 HPE Bed Board'!H13<TODAY(),"PAST",IF('🛏 HPE Bed Board'!H13=TODAY(),"TODAY","DC "&TEXT('🛏 HPE Bed Board'!H13,"M/D")&" ("&INT('🛏 HPE Bed Board'!H13-TODAY())&"d)"))),"—") -> DC 6/23 (6d)
A27: ='🛏 HPE Bed Board'!A14 -> H1-3A | B27: =IF('🛏 HPE Bed Board'!B14="Occupied",'🛏 HPE Bed Board'!C14,IF('🛏 HPE Bed Board'!B14="Reserved","Reserved: "&'🛏 HPE Bed Board'!C14,IF('🛏 HPE Bed Board'!B14="Open","— open —",""))) -> Aaron Dufresne | C27: =IF('🛏 HPE Bed Board'!B14="Occupied",IF('🛏 HPE Bed Board'!F14<>"",'🛏 HPE Bed Board'!F14,'🛏 HPE Bed Board'!E14),"") -> DTX | D27: =IF('🛏 HPE Bed Board'!B14="Occupied",IF('🛏 HPE Bed Board'!H14="","—",IF('🛏 HPE Bed Board'!H14<TODAY(),"PAST",IF('🛏 HPE Bed Board'!H14=TODAY(),"TODAY","DC "&TEXT('🛏 HPE Bed Board'!H14,"M/D")&" ("&INT('🛏 HPE Bed Board'!H14-TODAY())&"d)"))),"—") -> DC 6/28 (11d)
A28: ='🛏 HPE Bed Board'!A15 -> H1-3B | B28: =IF('🛏 HPE Bed Board'!B15="Occupied",'🛏 HPE Bed Board'!C15,IF('🛏 HPE Bed Board'!B15="Reserved","Reserved: "&'🛏 HPE Bed Board'!C15,IF('🛏 HPE Bed Board'!B15="Open","— open —",""))) -> — open — | C28: =IF('🛏 HPE Bed Board'!B15="Occupied",IF('🛏 HPE Bed Board'!F15<>"",'🛏 HPE Bed Board'!F15,'🛏 HPE Bed Board'!E15),"") | D28: =IF('🛏 HPE Bed Board'!B15="Occupied",IF('🛏 HPE Bed Board'!H15="","—",IF('🛏 HPE Bed Board'!H15<TODAY(),"PAST",IF('🛏 HPE Bed Board'!H15=TODAY(),"TODAY","DC "&TEXT('🛏 HPE Bed Board'!H15,"M/D")&" ("&INT('🛏 HPE Bed Board'!H15-TODAY())&"d)"))),"—") -> —
A29: ='🛏 HPE Bed Board'!A16 -> H1-4 | B29: =IF('🛏 HPE Bed Board'!B16="Occupied",'🛏 HPE Bed Board'!C16,IF('🛏 HPE Bed Board'!B16="Reserved","Reserved: "&'🛏 HPE Bed Board'!C16,IF('🛏 HPE Bed Board'!B16="Open","— open —",""))) -> Jared Hamilton | C29: =IF('🛏 HPE Bed Board'!B16="Occupied",IF('🛏 HPE Bed Board'!F16<>"",'🛏 HPE Bed Board'!F16,'🛏 HPE Bed Board'!E16),"") -> DTX/RTC | D29: =IF('🛏 HPE Bed Board'!B16="Occupied",IF('🛏 HPE Bed Board'!H16="","—",IF('🛏 HPE Bed Board'!H16<TODAY(),"PAST",IF('🛏 HPE Bed Board'!H16=TODAY(),"TODAY","DC "&TEXT('🛏 HPE Bed Board'!H16,"M/D")&" ("&INT('🛏 HPE Bed Board'!H16-TODAY())&"d)"))),"—") -> DC 7/2 (15d)
A30: ='🛏 HPE Bed Board'!A18 -> H2-2A | B30: =IF('🛏 HPE Bed Board'!B18="Occupied",'🛏 HPE Bed Board'!C18,IF('🛏 HPE Bed Board'!B18="Reserved","Reserved: "&'🛏 HPE Bed Board'!C18,IF('🛏 HPE Bed Board'!B18="Open","— open —",""))) -> Reserved: Tara Shinde | C30: =IF('🛏 HPE Bed Board'!B18="Occupied",IF('🛏 HPE Bed Board'!F18<>"",'🛏 HPE Bed Board'!F18,'🛏 HPE Bed Board'!E18),"") | D30: =IF('🛏 HPE Bed Board'!B18="Occupied",IF('🛏 HPE Bed Board'!H18="","—",IF('🛏 HPE Bed Board'!H18<TODAY(),"PAST",IF('🛏 HPE Bed Board'!H18=TODAY(),"TODAY","DC "&TEXT('🛏 HPE Bed Board'!H18,"M/D")&" ("&INT('🛏 HPE Bed Board'!H18-TODAY())&"d)"))),"—") -> —
A31: ='🛏 HPE Bed Board'!A19 -> H2-2B | B31: =IF('🛏 HPE Bed Board'!B19="Occupied",'🛏 HPE Bed Board'!C19,IF('🛏 HPE Bed Board'!B19="Reserved","Reserved: "&'🛏 HPE Bed Board'!C19,IF('🛏 HPE Bed Board'!B19="Open","— open —",""))) -> — open — | C31: =IF('🛏 HPE Bed Board'!B19="Occupied",IF('🛏 HPE Bed Board'!F19<>"",'🛏 HPE Bed Board'!F19,'🛏 HPE Bed Board'!E19),"") | D31: =IF('🛏 HPE Bed Board'!B19="Occupied",IF('🛏 HPE Bed Board'!H19="","—",IF('🛏 HPE Bed Board'!H19<TODAY(),"PAST",IF('🛏 HPE Bed Board'!H19=TODAY(),"TODAY","DC "&TEXT('🛏 HPE Bed Board'!H19,"M/D")&" ("&INT('🛏 HPE Bed Board'!H19-TODAY())&"d)"))),"—") -> —
A32: ='🛏 HPE Bed Board'!A20 -> H2-3A | B32: =IF('🛏 HPE Bed Board'!B20="Occupied",'🛏 HPE Bed Board'!C20,IF('🛏 HPE Bed Board'!B20="Reserved","Reserved: "&'🛏 HPE Bed Board'!C20,IF('🛏 HPE Bed Board'!B20="Open","— open —",""))) -> Daniel Armiger | C32: =IF('🛏 HPE Bed Board'!B20="Occupied",IF('🛏 HPE Bed Board'!F20<>"",'🛏 HPE Bed Board'!F20,'🛏 HPE Bed Board'!E20),"") -> RTC | D32: =IF('🛏 HPE Bed Board'!B20="Occupied",IF('🛏 HPE Bed Board'!H20="","—",IF('🛏 HPE Bed Board'!H20<TODAY(),"PAST",IF('🛏 HPE Bed Board'!H20=TODAY(),"TODAY","DC "&TEXT('🛏 HPE Bed Board'!H20,"M/D")&" ("&INT('🛏 HPE Bed Board'!H20-TODAY())&"d)"))),"—") -> DC 7/9 (22d)
A33: ='🛏 HPE Bed Board'!A21 -> H2-3B | B33: =IF('🛏 HPE Bed Board'!B21="Occupied",'🛏 HPE Bed Board'!C21,IF('🛏 HPE Bed Board'!B21="Reserved","Reserved: "&'🛏 HPE Bed Board'!C21,IF('🛏 HPE Bed Board'!B21="Open","— open —",""))) -> Blayne Olivier | C33: =IF('🛏 HPE Bed Board'!B21="Occupied",IF('🛏 HPE Bed Board'!F21<>"",'🛏 HPE Bed Board'!F21,'🛏 HPE Bed Board'!E21),"") -> 0 | D33: =IF('🛏 HPE Bed Board'!B21="Occupied",IF('🛏 HPE Bed Board'!H21="","—",IF('🛏 HPE Bed Board'!H21<TODAY(),"PAST",IF('🛏 HPE Bed Board'!H21=TODAY(),"TODAY","DC "&TEXT('🛏 HPE Bed Board'!H21,"M/D")&" ("&INT('🛏 HPE Bed Board'!H21-TODAY())&"d)"))),"—") -> DC 7/13 (26d)
A34: ='🛏 HPE Bed Board'!A22 -> H2-3C | B34: =IF('🛏 HPE Bed Board'!B22="Occupied",'🛏 HPE Bed Board'!C22,IF('🛏 HPE Bed Board'!B22="Reserved","Reserved: "&'🛏 HPE Bed Board'!C22,IF('🛏 HPE Bed Board'!B22="Open","— open —",""))) -> Bradey Bauer | C34: =IF('🛏 HPE Bed Board'!B22="Occupied",IF('🛏 HPE Bed Board'!F22<>"",'🛏 HPE Bed Board'!F22,'🛏 HPE Bed Board'!E22),"") -> 0 | D34: =IF('🛏 HPE Bed Board'!B22="Occupied",IF('🛏 HPE Bed Board'!H22="","—",IF('🛏 HPE Bed Board'!H22<TODAY(),"PAST",IF('🛏 HPE Bed Board'!H22=TODAY(),"TODAY","DC "&TEXT('🛏 HPE Bed Board'!H22,"M/D")&" ("&INT('🛏 HPE Bed Board'!H22-TODAY())&"d)"))),"—") -> DC 7/13 (26d)
A35: ='🛏 HPE Bed Board'!A23 -> H2-4 | B35: =IF('🛏 HPE Bed Board'!B23="Occupied",'🛏 HPE Bed Board'!C23,IF('🛏 HPE Bed Board'!B23="Reserved","Reserved: "&'🛏 HPE Bed Board'!C23,IF('🛏 HPE Bed Board'!B23="Open","— open —",""))) -> Jeongwoon Lee | C35: =IF('🛏 HPE Bed Board'!B23="Occupied",IF('🛏 HPE Bed Board'!F23<>"",'🛏 HPE Bed Board'!F23,'🛏 HPE Bed Board'!E23),"") -> RTC | D35: =IF('🛏 HPE Bed Board'!B23="Occupied",IF('🛏 HPE Bed Board'!H23="","—",IF('🛏 HPE Bed Board'!H23<TODAY(),"PAST",IF('🛏 HPE Bed Board'!H23=TODAY(),"TODAY","DC "&TEXT('🛏 HPE Bed Board'!H23,"M/D")&" ("&INT('🛏 HPE Bed Board'!H23-TODAY())&"d)"))),"—") -> DC 6/26 (9d)
A37: 📋 SCHEDULED INTAKES
A38: ROOM | B38: CLIENT | C38: LOC | D38: DC / DAYS
A39: =IF('🔥 Pipeline'!D5="Scheduled",'🔥 Pipeline'!C5,"") | B39: =IF('🔥 Pipeline'!D5="Scheduled",'🔥 Pipeline'!I5,"") | C39: =IF('🔥 Pipeline'!D5="Scheduled",'🔥 Pipeline'!E5,"") | D39: =IF('🔥 Pipeline'!D5="Scheduled",'🔥 Pipeline'!H5,"")
A40: =IF('🔥 Pipeline'!D6="Scheduled",'🔥 Pipeline'!C6,"") | B40: =IF('🔥 Pipeline'!D6="Scheduled",'🔥 Pipeline'!I6,"") | C40: =IF('🔥 Pipeline'!D6="Scheduled",'🔥 Pipeline'!E6,"") | D40: =IF('🔥 Pipeline'!D6="Scheduled",'🔥 Pipeline'!H6,"")
A41: =IF('🔥 Pipeline'!D7="Scheduled",'🔥 Pipeline'!C7,"") -> Tara Shinde | B41: =IF('🔥 Pipeline'!D7="Scheduled",'🔥 Pipeline'!I7,"") -> BCBS IL | C41: =IF('🔥 Pipeline'!D7="Scheduled",'🔥 Pipeline'!E7,"") -> DTX/RTC | D41: =IF('🔥 Pipeline'!D7="Scheduled",'🔥 Pipeline'!H7,"") -> 46192
A42: =IF('🔥 Pipeline'!D8="Scheduled",'🔥 Pipeline'!C8,"") | B42: =IF('🔥 Pipeline'!D8="Scheduled",'🔥 Pipeline'!I8,"") | C42: =IF('🔥 Pipeline'!D8="Scheduled",'🔥 Pipeline'!E8,"") | D42: =IF('🔥 Pipeline'!D8="Scheduled",'🔥 Pipeline'!H8,"")
A43: =IF('🔥 Pipeline'!D9="Scheduled",'🔥 Pipeline'!C9,"") | B43: =IF('🔥 Pipeline'!D9="Scheduled",'🔥 Pipeline'!I9,"") | C43: =IF('🔥 Pipeline'!D9="Scheduled",'🔥 Pipeline'!E9,"") | D43: =IF('🔥 Pipeline'!D9="Scheduled",'🔥 Pipeline'!H9,"")
A44: =IF('🔥 Pipeline'!D10="Scheduled",'🔥 Pipeline'!C10,"") | B44: =IF('🔥 Pipeline'!D10="Scheduled",'🔥 Pipeline'!I10,"") | C44: =IF('🔥 Pipeline'!D10="Scheduled",'🔥 Pipeline'!E10,"") | D44: =IF('🔥 Pipeline'!D10="Scheduled",'🔥 Pipeline'!H10,"")
A45: =IF('🔥 Pipeline'!D11="Scheduled",'🔥 Pipeline'!C11,"") | B45: =IF('🔥 Pipeline'!D11="Scheduled",'🔥 Pipeline'!I11,"") | C45: =IF('🔥 Pipeline'!D11="Scheduled",'🔥 Pipeline'!E11,"") | D45: =IF('🔥 Pipeline'!D11="Scheduled",'🔥 Pipeline'!H11,"")
A46: =IF('🔥 Pipeline'!D12="Scheduled",'🔥 Pipeline'!C12,"") | B46: =IF('🔥 Pipeline'!D12="Scheduled",'🔥 Pipeline'!I12,"") | C46: =IF('🔥 Pipeline'!D12="Scheduled",'🔥 Pipeline'!E12,"") | D46: =IF('🔥 Pipeline'!D12="Scheduled",'🔥 Pipeline'!H12,"")
